Workbook

Sheet 总览
A1: 总览
A3: 蓝色格填写；灰色格自动计算。当前持仓比例按市值计算，月度购买金额按目标比例计算。
A4: 基础月投 USD | B4: 500 | D4: 每月计划日 | E4: 10 | G4: 新投入：VOO 90%＋QQQM 10%；SMH 为历史持仓，后续计划投入 0。
A7: ETF | B7: 目标比例 | C7: 基础计划 USD | D7: 现价 USD／份 | E7: 价格日期 | F7: 当前份额 | G7: 持仓成本 USD | H7: 平均成本／份 | I7: 市值 USD | J7: 未实现盈亏 USD | K7: 持仓收益率 | L7: 市值占比 | M7: 偏离目标 | N7: 状态
A8: VOO | B8: 0.9 | C8: =$B$4*B8 -> 450 | D8: 712.32 | E8: 46301 | F8: =IF(COUNTIF(交易记录!$B$6:$B$605,A8)=0,0,IF(COUNTIFS(交易记录!$B$6:$B$605,A8,交易记录!$K$6:$K$605,"<>已记录")>0,"",SUMIF(交易记录!$B$6:$B$605,A8,交易记录!$I$6:$I$605))) -> 0.5373 | G8: =IF(F8="","",SUMIF(交易记录!$B$6:$B$605,A8,交易记录!$H$6:$H$605)) -> 375 | H8: =IF(OR(F8="",F8=0),"",G8/F8) -> 697.93412 | I8: =IF(F8="","",IF(F8=0,0,IF(OR(D8="",D8<=0),"",F8*D8))) -> 382.72954 | J8: =IF(I8="","",I8-G8) -> 7.729536 | K8: =IF(OR(J8="",G8=0),"",J8/G8) -> 0.020612096 | L8: =IF(OR($I$12="",$I$12=0,I8=""),"",I8/$I$12) -> 0.73807916 | M8: =IF(L8="","",L8-B8) -> -0.16192084 | N8: =IF(COUNTIFS(交易记录!$B$6:$B$605,A8,交易记录!$K$6:$K$605,"<>已记录")>0,"待补交易信息",IF(F8=0,"无持仓",IF(D8="","待填现价",IF(E8="","待填价格日期","已计算")))) -> 已计算
A9: QQQM | B9: 0.1 | C9: =$B$4*B9 -> 50 | D9: 311.4 | E9: 46301 | F9: =IF(COUNTIF(交易记录!$B$6:$B$605,A9)=0,0,IF(COUNTIFS(交易记录!$B$6:$B$605,A9,交易记录!$K$6:$K$605,"<>已记录")>0,"",SUMIF(交易记录!$B$6:$B$605,A9,交易记录!$I$6:$I$605))) -> 0.256 | G9: =IF(F9="","",SUMIF(交易记录!$B$6:$B$605,A9,交易记录!$H$6:$H$605)) -> 75 | H9: =IF(OR(F9="",F9=0),"",G9/F9) -> 292.96875 | I9: =IF(F9="","",IF(F9=0,0,IF(OR(D9="",D9<=0),"",F9*D9))) -> 79.7184 | J9: =IF(I9="","",I9-G9) -> 4.7184 | K9: =IF(OR(J9="",G9=0),"",J9/G9) -> 0.062912 | L9: =IF(OR($I$12="",$I$12=0,I9=""),"",I9/$I$12) -> 0.15373386 | M9: =IF(L9="","",L9-B9) -> 0.053733862 | N9: =IF(COUNTIFS(交易记录!$B$6:$B$605,A9,交易记录!$K$6:$K$605,"<>已记录")>0,"待补交易信息",IF(F9=0,"无持仓",IF(D9="","待填现价",IF(E9="","待填价格日期","已计算")))) -> 已计算
A10: SMH | B10: 0 | C10: =$B$4*B10 -> 0 | D10: 633.9 | E10: 46301 | F10: =IF(COUNTIF(交易记录!$B$6:$B$605,A10)=0,0,IF(COUNTIFS(交易记录!$B$6:$B$605,A10,交易记录!$K$6:$K$605,"<>已记录")>0,"",SUMIF(交易记录!$B$6:$B$605,A10,交易记录!$I$6:$I$605))) -> 0.0885 | G10: =IF(F10="","",SUMIF(交易记录!$B$6:$B$605,A10,交易记录!$H$6:$H$605)) -> 50 | H10: =IF(OR(F10="",F10=0),"",G10/F10) -> 564.97175 | I10: =IF(F10="","",IF(F10=0,0,IF(OR(D10="",D10<=0),"",F10*D10))) -> 56.10015 | J10: =IF(I10="","",I10-G10) -> 6.10015 | K10: =IF(OR(J10="",G10=0),"",J10/G10) -> 0.122003 | L10: =IF(OR($I$12="",$I$12=0,I10=""),"",I10/$I$12) -> 0.10818698 | M10: =IF(L10="","",L10-B10) -> 0.10818698 | N10: =IF(COUNTIFS(交易记录!$B$6:$B$605,A10,交易记录!$K$6:$K$605,"<>已记录")>0,"待补交易信息",IF(F10=0,"无持仓",IF(D10="","待填现价",IF(E10="","待填价格日期","已计算")))) -> 已计算
A12: 合计 | B12: =SUM(B8:B10) -> 1 | C12: =SUM(C8:C10) -> 500 | G12: =IF(COUNT(G8:G10)<3,"",SUM(G8:G10)) -> 500 | I12: =IF(COUNT(I8:I10)<3,"",SUM(I8:I10)) -> 518.54809 | J12: =IF(COUNT(J8:J10)<3,"",SUM(J8:J10)) -> 18.548086 | K12: =IF(OR(J12="",G12=0),"",J12/G12) -> 0.037096172
A14: 现金 USD | B14: 1804.86 | D14: 总值 USD | E14: =IF(OR(I12="",B14=""),"",I12+B14) -> 2323.4081 | G14: 现金请按嘉信余额手动填写；账户总值＝ETF 市值＋现金。
A16: 累计买入 | C16: =SUMIF(交易记录!C6:C605,"买入",交易记录!D6:D605)+SUMIF(交易记录!C6:C605,"买入",交易记录!E6:E605) -> 500 | D16: 到账 USD | E16: =SUMIFS(换汇记录!L6:L246,换汇记录!F6:F246,"嘉信证券")+SUMIFS(入金记录!G6:G245,入金记录!F6:F245,"嘉信证券",入金记录!D6:D245,"USD",入金记录!C6:C245,"<>嘉信证券",入金记录!H6:H245,">0") -> 2303.8 | G16: 税后分红 | I16: =SUM(分红记录!F6:F245) -> 0 | J16: 已实现盈亏 | M16: =IF(COUNTIFS(交易记录!C6:C605,"卖出",交易记录!K6:K605,"<>已记录")>0,"",SUM(交易记录!J6:J605)) -> 0
A18: 每月先填回撤计划指数数据，再分别记录换汇、转账和ETF成交。已保留你填写的各笔金额、日期、账户、备注、份额及行情；美元到账按实际终端记录汇总，避免重复计入。
A21: 说明：持仓收益率为未实现盈亏 ÷ 当前持仓成本，并非年化收益率。买卖成本采用移动加权平均法作投资分析；券商成交记录和税务成本口径可能不同。已有 SMH 只记录，不触发卖出。
A24: 本表执行500／750／1000美元回撤计划，额外预算累计5000美元，实际耗尽后回到500。目标比例90%／10%；SMH历史持仓继续记录。修改基础额、预算或目标会重算计划及统计，请先备份。
A28: 额外预算 USD | C28: =回撤计划!E4 -> 5000 | E28: 实际加投按回撤计划记录扣减。分红再投／其他买入在交易记录P列分类；必要时在回撤计划O列修正实际使用额外预算。嘉信可用现金仍按实际账户余额手动更新。
A29: 额外已用 USD | C29: =回撤计划!K4 -> 0
A30: 额外剩余 USD | C30: =回撤计划!N4 -> 5000

Sheet 回撤计划
A1: 回撤计划
A3: 10%以下500；10%至不足20%为750；20%及以上1000。5000美元仅约束额外投入，按实际买入扣减，用完恢复500。每月10日交易前填最近已结束美股交易日收盘；遇休市顺延。
A4: 基础月投 USD | B4: =总览!B4 -> 500 | D4: 额外预算 USD | E4: 5000 | G4: 起始历史高收盘 | H4: 7794.35 | J4: 额外已用 USD | K4: =SUM(P9:P128) -> 0 | M4: 额外剩余 USD | N4: =MAX(0,E4-K4) -> 5000
A5: 先在H4填写核对过的起始历史最高收盘；后续出现更高收盘，填对应月D列（当月收盘创新高也会自动上调）。高点不随反弹下调；预算不自动重置。
A6: 实际定投仅计VOO／QQQM买入及手续费，排除P列“分红再投／其他”。额外参考=max(当月实际定投−500,0)；若资金用途不同，在O列填实际动用预算（0也有效）。交易未记入前不扣预算。
A8: 计划日期 | B8: 观察收盘日 | C8: 标普500收盘 | D8: 新历史高收盘 | E8: 沿用历史高点 | F8: 回撤幅度 | G8: 标准月额 USD | H8: 月初加投余款 | I8: 计划额外 USD | J8: 本月合计 USD | K8: VOO计划 USD | L8: QQQM计划 USD | M8: 实际定投 USD | N8: 额外支出参考 | O8: 实际额外（选填） | P8: 已用额外 USD | Q8: 月底加投余款 | R8: 状态 | S8: 备注
A9: =月度计划!A6 -> 46305 | E9: =IF(MAX($H$4,$H$4,D9)<=0,"",MAX($H$4,$H$4,D9,C9)) -> 7794.35 | F9: =IF(AND(ISNUMBER(B9),ISNUMBER(C9),C9>0,ISNUMBER(E9),E9>0),MAX(0,1-C9/E9),"") | G9: =IF(F9="","",IF(ROUND(F9,10)<0.1,$B$4,IF(ROUND(F9,10)<0.2,$B$4+250,$B$4+500))) | H9: =MAX(0,$E$4) -> 5000 | I9: =IF(G9="",0,MIN(MAX(0,G9-$B$4),H9)) -> 0 | J9: =$B$4+I9 -> 500 | K9: =J9*总览!$B$8 -> 450 | L9: =J9*总览!$B$9 -> 50 | M9: =SUMIFS(交易记录!$D$6:$D$605,交易记录!$A$6:$A$605,">="&DATE(YEAR(A9),MONTH(A9),1),交易记录!$A$6:$A$605,"<"&DATE(YEAR(A9),MONTH(A9)+1,1),交易记录!$C$6:$C$605,"买入",交易记录!$P$6:$P$605,"<>分红再投",交易记录!$P$6:$P$605,"<>其他",交易记录!$B$6:$B$605,"VOO")+SUMIFS(交易记录!$D$6:$D$605,交易记录!$A$6:$A$605,">="&DATE(YEAR(A9),MONTH(A9),1),交易记录!$A$6:$A$605,"<"&DATE(YEAR(A9),MONTH(A9)+1,1),交易记录!$C$6:$C$605,"买入",交易记录!$P$6:$P$605,"<>分红再投",交易记录!$P$6:$P$605,"<>其他",交易记录!$B$6:$B$605,"QQQM")+SUMIFS(交易记录!$E$6:$E$605,交易记录!$A$6:$A$605,">="&DATE(YEAR(A9),MONTH(A9),1),交易记录!$A$6:$A$605,"<"&DATE(YEAR(A9),MONTH(A9)+1,1),交易记录!$C$6:$C$605,"买入",交易记录!$P$6:$P$605,"<>分红再投",交易记录!$P$6:$P$605,"<>其他",交易记录!$B$6:$B$605,"VOO")+SUMIFS(交易记录!$E$6:$E$605,交易记录!$A$6:$A$605,">="&DATE(YEAR(A9),MONTH(A9),1),交易记录!$A$6:$A$605,"<"&DATE(YEAR(A9),MONTH(A9)+1,1),交易记录!$C$6:$C$605,"买入",交易记录!$P$6:$P$605,"<>分红再投",交易记录!$P$6:$P$605,"<>其他",交易记录!$B$6:$B$605,"QQQM") -> 0 | N9: =MAX(0,M9-$B$4) -> 0 | P9: =IF(O9="",N9,O9) -> 0 | Q9: =MAX(0,H9-P9) -> 5000 | R9: =IF(P9>H9+0.005,"实际加投超剩余预算，请核对",IF(H9=0,"预算用完：基础定投",IF(F9="","待补指数收盘／历史基准；先列基础额",IF(AND(B9>A9,M9=0),"核对观察日是否在实际交易前",IF(AND(O9<>"",ABS(O9-N9)>0.005),"已按手填额外支出扣预算",IF(M9=0,"已计算，尚未记录买入",IF(ABS(M9-J9)<0.01,"已按计划记录","实际定投与计划有差额"))))))) -> 待补指数收盘／历史基准；先列基础额
A10: =月度计划!A7 -> 46336 | E10: =IF(MAX($H$4,E9,D10)<=0,"",MAX($H$4,E9,D10,C10)) -> 7794.35 | F10: =IF(AND(ISNUMBER(B10),ISNUMBER(C10),C10>0,ISNUMBER(E10),E10>0),MAX(0,1-C10/E10),"") | G10: =IF(F10="","",IF(ROUND(F10,10)<0.1,$B$4,IF(ROUND(F10,10)<0.2,$B$4+250,$B$4+500))) | H10: =MAX(0,$E$4-SUM($P$9:P9)) -> 5000 | I10: =IF(G10="",0,MIN(MAX(0,G10-$B$4),H10)) -> 0 | J10: =$B$4+I10 -> 500 | K10: =J10*总览!$B$8 -> 450 | L10: =J10*总览!$B$9 -> 50 | M10: =SUMIFS(交易记录!$D$6:$D$605,交易记录!$A$6:$A$605,">="&DATE(YEAR(A10),MONTH(A10),1),交易记录!$A$6:$A$605,"<"&DATE(YEAR(A10),MONTH(A10)+1,1),交易记录!$C$6:$C$605,"买入",交易记录!$P$6:$P$605,"<>分红再投",交易记录!$P$6:$P$605,"<>其他",交易记录!$B$6:$B$605,"VOO")+SUMIFS(交易记录!$D$6:$D$605,交易记录!$A$6:$A$605,">="&DATE(YEAR(A10),MONTH(A10),1),交易记录!$A$6:$A$605,"<"&DATE(YEAR(A10),MONTH(A10)+1,1),交易记录!$C$6:$C$605,"买入",交易记录!$P$6:$P$605,"<>分红再投",交易记录!$P$6:$P$605,"<>其他",交易记录!$B$6:$B$605,"QQQM")+SUMIFS(交易记录!$E$6:$E$605,交易记录!$A$6:$A$605,">="&DATE(YEAR(A10),MONTH(A10),1),交易记录!$A$6:$A$605,"<"&DATE(YEAR(A10),MONTH(A10)+1,1),交易记录!$C$6:$C$605,"买入",交易记录!$P$6:$P$605,"<>分红再投",交易记录!$P$6:$P$605,"<>其他",交易记录!$B$6:$B$605,"VOO")+SUMIFS(交易记录!$E$6:$E$605,交易记录!$A$6:$A$605,">="&DATE(YEAR(A10),MONTH(A10),1),交易记录!$A$6:$A$605,"<"&DATE(YEAR(A10),MONTH(A10)+1,1),交易记录!$C$6:$C$605,"买入",交易记录!$P$6:$P$605,"<>分红再投",交易记录!$P$6:$P$605,"<>其他",交易记录!$B$6:$B$605,"QQQM") -> 0 | N10: =MAX(0,M10-$B$4) -> 0 | P10: =IF(O10="",N10,O10) -> 0 | Q10: =MAX(0,H10-P10) -> 5000 | R10: =IF(P10>H10+0.005,"实际加投超剩余预算，请核对",IF(H10=0,"预算用完：基础定投",IF(F10="","待补指数收盘／历史基准；先列基础额",IF(AND(B10>A10,M10=0),"核对观察日是否在实际交易前",IF(AND(O10<>"",ABS(O10-N10)>0.005),"已按手填额外支出扣预算",IF(M10=0,"已计算，尚未记录买入",IF(ABS(M10-J10)<0.01,"已按计划记录","实际定投与计划有差额"))))))) -> 待补指数收盘／历史基准；先列基础额
A11: =月度计划!A8 -> 46366 | E11: =IF(MAX($H$4,E10,D11)<=0,"",MAX($H$4,E10,D11,C11)) -> 7794.35 | F11: =IF(AND(ISNUMBER(B11),ISNUMBER(C11),C11>0,ISNUMBER(E11),E11>0),MAX(0,1-C11/E11),"") | G11: =IF(F11="","",IF(ROUND(F11,10)<0.1,$B$4,IF(ROUND(F11,10)<0.2,$B$4+250,$B$4+500))) | H11: =MAX(0,$E$4-SUM($P$9:P10)) -> 5000 | I11: =IF(G11="",0,MIN(MAX(0,G11-$B$4),H11)) -> 0 | J11: =$B$4+I11 -> 500 | K11: =J11*总览!$B$8 -> 450 | L11: =J11*总览!$B$9 -> 50 | M11: =SUMIFS(交易记录!$D$6:$D$605,交易记录!$A$6:$A$605,">="&DATE(YEAR(A11),MONTH(A11),1),交易记录!$A$6:$A$605,"<"&DATE(YEAR(A11),MONTH(A11)+1,1),交易记录!$C$6:$C$605,"买入",交易记录!$P$6:$P$605,"<>分红再投",交易记录!$P$6:$P$605,"<>其他",交易记录!$B$6:$B$605,"VOO")+SUMIFS(交易记录!$D$6:$D$605,交易记录!$A$6:$A$605,">="&DATE(YEAR(A11),MONTH(A11),1),交易记录!$A$6:$A$605,"<"&DATE(YEAR(A11),MONTH(A11)+1,1),交易记录!$C$6:$C$605,"买入",交易记录!$P$6:$P$605,"<>分红再投",交易记录!$P$6:$P$605,"<>其他",交易记录!$B$6:$B$605,"QQQM")+SUMIFS(交易记录!$E$6:$E$605,交易记录!$A$6:$A$605,">="&DATE(YEAR(A11),MONTH(A11),1),交易记录!$A$6:$A$605,"<"&DATE(YEAR(A11),MONTH(A11)+1,1),交易记录!$C$6:$C$605,"买入",交易记录!$P$6:$P$605,"<>分红再投",交易记录!$P$6:$P$605,"<>其他",交易记录!$B$6:$B$605,"VOO")+SUMIFS(交易记录!$E$6:$E$605,交易记录!$A$6:$A$605,">="&DATE(YEAR(A11),MONTH(A11),1),交易记录!$A$6:$A$605,"<"&DATE(YEAR(A11),MONTH(A11)+1,1),交易记录!$C$6:$C$605,"买入",交易记录!$P$6:$P$605,"<>分红再投",交易记录!$P$6:$P$605,"<>其他",交易记录!$B$6:$B$605,"QQQM") -> 0 | N11: =MAX(0,M11-$B$4) -> 0 | P11: =IF(O11="",N11,O11) -> 0 | Q11: =MAX(0,H11-P11) -> 5000 | R11: =IF(P11>H11+0.005,"实际加投超剩余预算，请核对",IF(H11=0,"预算用完：基础定投",IF(F11="","待补指数收盘／历史基准；先列基础额",IF(AND(B11>A11,M11=0),"核对观察日是否在实际交易前",IF(AND(O11<>"",ABS(O11-N11)>0.005),"已按手填额外支出扣预算",IF(M11=0,"已计算，尚未记录买入",IF(ABS(M11-J11)<0.01,"已按计划记录","实际定投与计划有差额"))))))) -> 待补指数收盘／历史基准；先列基础额
A12: =月度计划!A9 -> 46397 | E12: =IF(MAX($H$4,E11,D12)<=0,"",MAX($H$4,E11,D12,C12)) -> 7794.35 | F12: =IF(AND(ISNUMBER(B12),ISNUMBER(C12),C12>0,ISNUMBER(E12),E12>0),MAX(0,1-C12/E12),"") | G12: =IF(F12="","",IF(ROUND(F12,10)<0.1,$B$4,IF(ROUND(F12,10)<0.2,$B$4+250,$B$4+500))) | H12: =MAX(0,$E$4-SUM($P$9:P11)) -> 5000 | I12: =IF(G12="",0,MIN(MAX(0,G12-$B$4),H12)) -> 0 | J12: =$B$4+I12 -> 500 | K12: =J12*总览!$B$8 -> 450 | L12: =J12*总览!$B$9 -> 50 | M12: =SUMIFS(交易记录!$D$6:$D$605,交易记录!$A$6:$A$605,">="&DATE(YEAR(A12),MONTH(A12),1),交易记录!$A$6:$A$605,"<"&DATE(YEAR(A12),MONTH(A12)+1,1),交易记录!$C$6:$C$605,"买入",交易记录!$P$6:$P$605,"<>分红再投",交易记录!$P$6:$P$605,"<>其他",交易记录!$B$6:$B$605,"VOO")+SUMIFS(交易记录!$D$6:$D$605,交易记录!$A$6:$A$605,">="&DATE(YEAR(A12),MONTH(A12),1),交易记录!$A$6:$A$605,"<"&DATE(YEAR(A12),MONTH(A12)+1,1),交易记录!$C$6:$C$605,"买入",交易记录!$P$6:$P$605,"<>分红再投",交易记录!$P$6:$P$605,"<>其他",交易记录!$B$6:$B$605,"QQQM")+SUMIFS(交易记录!$E$6:$E$605,交易记录!$A$6:$A$605,">="&DATE(YEAR(A12),MONTH(A12),1),交易记录!$A$6:$A$605,"<"&DATE(YEAR(A12),MONTH(A12)+1,1),交易记录!$C$6:$C$605,"买入",交易记录!$P$6:$P$605,"<>分红再投",交易记录!$P$6:$P$605,"<>其他",交易记录!$B$6:$B$605,"VOO")+SUMIFS(交易记录!$E$6:$E$605,交易记录!$A$6:$A$605,">="&DATE(YEAR(A12),MONTH(A12),1),交易记录!$A$6:$A$605,"<"&DATE(YEAR(A12),MONTH(A12)+1,1),交易记录!$C$6:$C$605,"买入",交易记录!$P$6:$P$605,"<>分红再投",交易记录!$P$6:$P$605,"<>其他",交易记录!$B$6:$B$605,"QQQM") -> 0 | N12: =MAX(0,M12-$B$4) -> 0 | P12: =IF(O12="",N12,O12) -> 0 | Q12: =MAX(0,H12-P12) -> 5000 | R12: =IF(P12>H12+0.005,"实际加投超剩余预算，请核对",IF(H12=0,"预算用完：基础定投",IF(F12="","待补指数收盘／历史基准；先列基础额",IF(AND(B12>A12,M12=0),"核对观察日是否在实际交易前",IF(AND(O12<>"",ABS(O12-N12)>0.005),"已按手填额外支出扣预算",IF(M12=0,"已计算，尚未记录买入",IF(ABS(M12-J12)<0.01,"已按计划记录","实际定投与计划有差额"))))))) -> 待补指数收盘／历史基准；先列基础额
A13: =月度计划!A10 -> 46428 | E13: =IF(MAX($H$4,E12,D13)<=0,"",MAX($H$4,E12,D13,C13)) -> 7794.35 | F13: =IF(AND(ISNUMBER(B13),ISNUMBER(C13),C13>0,ISNUMBER(E13),E13>0),MAX(0,1-C13/E13),"") | G13: =IF(F13="","",IF(ROUND(F13,10)<0.1,$B$4,IF(ROUND(F13,10)<0.2,$B$4+250,$B$4+500))) | H13: =MAX(0,$E$4-SUM($P$9:P12)) -> 5000 | I13: =IF(G13="",0,MIN(MAX(0,G13-$B$4),H13)) -> 0 | J13: =$B$4+I13 -> 500 | K13: =J13*总览!$B$8 -> 450 | L13: =J13*总览!$B$9 -> 50 | M13: =SUMIFS(交易记录!$D$6:$D$605,交易记录!$A$6:$A$605,">="&DATE(YEAR(A13),MONTH(A13),1),交易记录!$A$6:$A$605,"<"&DATE(YEAR(A13),MONTH(A13)+1,1),交易记录!$C$6:$C$605,"买入",交易记录!$P$6:$P$605,"<>分红再投",交易记录!$P$6:$P$605,"<>其他",交易记录!$B$6:$B$605,"VOO")+SUMIFS(交易记录!$D$6:$D$605,交易记录!$A$6:$A$605,">="&DATE(YEAR(A13),MONTH(A13),1),交易记录!$A$6:$A$605,"<"&DATE(YEAR(A13),MONTH(A13)+1,1),交易记录!$C$6:$C$605,"买入",交易记录!$P$6:$P$605,"<>分红再投",交易记录!$P$6:$P$605,"<>其他",交易记录!$B$6:$B$605,"QQQM")+SUMIFS(交易记录!$E$6:$E$605,交易记录!$A$6:$A$605,">="&DATE(YEAR(A13),MONTH(A13),1),交易记录!$A$6:$A$605,"<"&DATE(YEAR(A13),MONTH(A13)+1,1),交易记录!$C$6:$C$605,"买入",交易记录!$P$6:$P$605,"<>分红再投",交易记录!$P$6:$P$605,"<>其他",交易记录!$B$6:$B$605,"VOO")+SUMIFS(交易记录!$E$6:$E$605,交易记录!$A$6:$A$605,">="&DATE(YEAR(A13),MONTH(A13),1),交易记录!$A$6:$A$605,"<"&DATE(YEAR(A13),MONTH(A13)+1,1),交易记录!$C$6:$C$605,"买入",交易记录!$P$6:$P$605,"<>分红再投",交易记录!$P$6:$P$605,"<>其他",交易记录!$B$6:$B$605,"QQQM") -> 0 | N13: =MAX(0,M13-$B$4) -> 0 | P13: =IF(O13="",N13,O13) -> 0 | Q13: =MAX(0,H13-P13) -> 5000 | R13: =IF(P13>H13+0.005,"实际加投超剩余预算，请核对",IF(H13=0,"预算用完：基础定投",IF(F13="","待补指数收盘／历史基准；先列基础额",IF(AND(B13>A13,M13=0),"核对观察日是否在实际交易前",IF(AND(O13<>"",ABS(O13-N13)>0.005),"已按手填额外支出扣预算",IF(M13=0,"已计算，尚未记录买入",IF(ABS(M13-J13)<0.01,"已按计划记录","实际定投与计划有差额"))))))) -> 待补指数收盘／历史基准；先列基础额
A14: =月度计划!A11 -> 46456 | E14: =IF(MAX($H$4,E13,D14)<=0,"",MAX($H$4,E13,D14,C14)) -> 7794.35 | F14: =IF(AND(ISNUMBER(B14),ISNUMBER(C14),C14>0,ISNUMBER(E14),E14>0),MAX(0,1-C14/E14),"") | G14: =IF(F14="","",IF(ROUND(F14,10)<0.1,$B$4,IF(ROUND(F14,10)<0.2,$B$4+250,$B$4+500))) | H14: =MAX(0,$E$4-SUM($P$9:P13)) -> 5000 | I14: =IF(G14="",0,MIN(MAX(0,G14-$B$4),H14)) -> 0 | J14: =$B$4+I14 -> 500 | K14: =J14*总览!$B$8 -> 450 | L14: =J14*总览!$B$9 -> 50 | M14: =SUMIFS(交易记录!$D$6:$D$605,交易记录!$A$6:$A$605,">="&DATE(YEAR(A14),MONTH(A14),1),交易记录!$A$6:$A$605,"<"&DATE(YEAR(A14),MONTH(A14)+1,1),交易记录!$C$6:$C$605,"买入",交易记录!$P$6:$P$605,"<>分红再投",交易记录!$P$6:$P$605,"<>其他",交易记录!$B$6:$B$605,"VOO")+SUMIFS(交易记录!$D$6:$D$605,交易记录!$A$6:$A$605,">="&DATE(YEAR(A14),MONTH(A14),1),交易记录!$A$6:$A$605,"<"&DATE(YEAR(A14),MONTH(A14)+1,1),交易记录!$C$6:$C$605,"买入",交易记录!$P$6:$P$605,"<>分红再投",交易记录!$P$6:$P$605,"<>其他",交易记录!$B$6:$B$605,"QQQM")+SUMIFS(交易记录!$E$6:$E$605,交易记录!$A$6:$A$605,">="&DATE(YEAR(A14),MONTH(A14),1),交易记录!$A$6:$A$605,"<"&DATE(YEAR(A14),MONTH(A14)+1,1),交易记录!$C$6:$C$605,"买入",交易记录!$P$6:$P$605,"<>分红再投",交易记录!$P$6:$P$605,"<>其他",交易记录!$B$6:$B$605,"VOO")+SUMIFS(交易记录!$E$6:$E$605,交易记录!$A$6:$A$605,">="&DATE(YEAR(A14),MONTH(A14),1),交易记录!$A$6:$A$605,"<"&DATE(YEAR(A14),MONTH(A14)+1,1),交易记录!$C$6:$C$605,"买入",交易记录!$P$6:$P$605,"<>分红再投",交易记录!$P$6:$P$605,"<>其他",交易记录!$B$6:$B$605,"QQQM") -> 0 | N14: =MAX(0,M14-$B$4) -> 0 | P14: =IF(O14="",N14,O14) -> 0 | Q14: =MAX(0,H14-P14) -> 5000 | R14: =IF(P14>H14+0.005,"实际加投超剩余预算，请核对",IF(H14=0,"预算用完：基础定投",IF(F14="","待补指数收盘／历史基准；先列基础额",IF(AND(B14>A14,M14=0),"核对观察日是否在实际交易前",IF(AND(O14<>"",ABS(O14-N14)>0.005),"已按手填额外支出扣预算",IF(M14=0,"已计算，尚未记录买入",IF(ABS(M14-J14)<0.01,"已按计划记录","实际定投与计划有差额"))))))) -> 待补指数收盘／历史基准；先列基础额
A15: =月度计划!A12 -> 46487 | E15: =IF(MAX($H$4,E14,D15)<=0,"",MAX($H$4,E14,D15,C15)) -> 7794.35 | F15: =IF(AND(ISNUMBER(B15),ISNUMBER(C15),C15>0,ISNUMBER(E15),E15>0),MAX(0,1-C15/E15),"") | G15: =IF(F15="","",IF(ROUND(F15,10)<0.1,$B$4,IF(ROUND(F15,10)<0.2,$B$4+250,$B$4+500))) | H15: =MAX(0,$E$4-SUM($P$9:P14)) -> 5000 | I15: =IF(G15="",0,MIN(MAX(0,G15-$B$4),H15)) -> 0 | J15: =$B$4+I15 -> 500 | K15: =J15*总览!$B$8 -> 450 | L15: =J15*总览!$B$9 -> 50 | M15: =SUMIFS(交易记录!$D$6:$D$605,交易记录!$A$6:$A$605,">="&DATE(YEAR(A15),MONTH(A15),1),交易记录!$A$6:$A$605,"<"&DATE(YEAR(A15),MONTH(A15)+1,1),交易记录!$C$6:$C$605,"买入",交易记录!$P$6:$P$605,"<>分红再投",交易记录!$P$6:$P$605,"<>其他",交易记录!$B$6:$B$605,"VOO")+SUMIFS(交易记录!$D$6:$D$605,交易记录!$A$6:$A$605,">="&DATE(YEAR(A15),MONTH(A15),1),交易记录!$A$6:$A$605,"<"&DATE(YEAR(A15),MONTH(A15)+1,1),交易记录!$C$6:$C$605,"买入",交易记录!$P$6:$P$605,"<>分红再投",交易记录!$P$6:$P$605,"<>其他",交易记录!$B$6:$B$605,"QQQM")+SUMIFS(交易记录!$E$6:$E$605,交易记录!$A$6:$A$605,">="&DATE(YEAR(A15),MONTH(A15),1),交易记录!$A$6:$A$605,"<"&DATE(YEAR(A15),MONTH(A15)+1,1),交易记录!$C$6:$C$605,"买入",交易记录!$P$6:$P$605,"<>分红再投",交易记录!$P$6:$P$605,"<>其他",交易记录!$B$6:$B$605,"VOO")+SUMIFS(交易记录!$E$6:$E$605,交易记录!$A$6:$A$605,">="&DATE(YEAR(A15),MONTH(A15),1),交易记录!$A$6:$A$605,"<"&DATE(YEAR(A15),MONTH(A15)+1,1),交易记录!$C$6:$C$605,"买入",交易记录!$P$6:$P$605,"<>分红再投",交易记录!$P$6:$P$605,"<>其他",交易记录!$B$6:$B$605,"QQQM") -> 0 | N15: =MAX(0,M15-$B$4) -> 0 | P15: =IF(O15="",N15,O15) -> 0 | Q15: =MAX(0,H15-P15) -> 5000 | R15: =IF(P15>H15+0.005,"实际加投超剩余预算，请核对",IF(H15=0,"预算用完：基础定投",IF(F15="","待补指数收盘／历史基准；先列基础额",IF(AND(B15>A15,M15=0),"核对观察日是否在实际交易前",IF(AND(O15<>"",ABS(O15-N15)>0.005),"已按手填额外支出扣预算",IF(M15=0,"已计算，尚未记录买入",IF(ABS(M15-J15)<0.01,"已按计划记录","实际定投与计划有差额"))))))) -> 待补指数收盘／历史基准；先列基础额
A16: =月度计划!A13 -> 46517 | E16: =IF(MAX($H$4,E15,D16)<=0,"",MAX($H$4,E15,D16,C16)) -> 7794.35 | F16: =IF(AND(ISNUMBER(B16),ISNUMBER(C16),C16>0,ISNUMBER(E16),E16>0),MAX(0,1-C16/E16),"") | G16: =IF(F16="","",IF(ROUND(F16,10)<0.1,$B$4,IF(ROUND(F16,10)<0.2,$B$4+250,$B$4+500))) | H16: =MAX(0,$E$4-SUM($P$9:P15)) -> 5000 | I16: =IF(G16="",0,MIN(MAX(0,G16-$B$4),H16)) -> 0 | J16: =$B$4+I16 -> 500 | K16: =J16*总览!$B$8 -> 450 | L16: =J16*总览!$B$9 -> 50 | M16: =SUMIFS(交易记录!$D$6:$D$605,交易记录!$A$6:$A$605,">="&DATE(YEAR(A16),MONTH(A16),1),交易记录!$A$6:$A$605,"<"&DATE(YEAR(A16),MONTH(A16)+1,1),交易记录!$C$6:$C$605,"买入",交易记录!$P$6:$P$605,"<>分红再投",交易记录!$P$6:$P$605,"<>其他",交易记录!$B$6:$B$605,"VOO")+SUMIFS(交易记录!$D$6:$D$605,交易记录!$A$6:$A$605,">="&DATE(YEAR(A16),MONTH(A16),1),交易记录!$A$6:$A$605,"<"&DATE(YEAR(A16),MONTH(A16)+1,1),交易记录!$C$6:$C$605,"买入",交易记录!$P$6:$P$605,"<>分红再投",交易记录!$P$6:$P$605,"<>其他",交易记录!$B$6:$B$605,"QQQM")+SUMIFS(交易记录!$E$6:$E$605,交易记录!$A$6:$A$605,">="&DATE(YEAR(A16),MONTH(A16),1),交易记录!$A$6:$A$605,"<"&DATE(YEAR(A16),MONTH(A16)+1,1),交易记录!$C$6:$C$605,"买入",交易记录!$P$6:$P$605,"<>分红再投",交易记录!$P$6:$P$605,"<>其他",交易记录!$B$6:$B$605,"VOO")+SUMIFS(交易记录!$E$6:$E$605,交易记录!$A$6:$A$605,">="&DATE(YEAR(A16),MONTH(A16),1),交易记录!$A$6:$A$605,"<"&DATE(YEAR(A16),MONTH(A16)+1,1),交易记录!$C$6:$C$605,"买入",交易记录!$P$6:$P$605,"<>分红再投",交易记录!$P$6:$P$605,"<>其他",交易记录!$B$6:$B$605,"QQQM") -> 0 | N16: =MAX(0,M16-$B$4) -> 0 | P16: =IF(O16="",N16,O16) -> 0 | Q16: =MAX(0,H16-P16) -> 5000 | R16: =IF(P16>H16+0.005,"实际加投超剩余预算，请核对",IF(H16=0,"预算用完：基础定投",IF(F16="","待补指数收盘／历史基准；先列基础额",IF(AND(B16>A16,M16=0),"核对观察日是否在实际交易前",IF(AND(O16<>"",ABS(O16-N16)>0.005),"已按手填额外支出扣预算",IF(M16=0,"已计算，尚未记录买入",IF(ABS(M16-J16)<0.01,"已按计划记录","实际定投与计划有差额"))))))) -> 待补指数收盘／历史基准；先列基础额
A17: =月度计划!A14 -> 46548 | E17: =IF(MAX($H$4,E16,D17)<=0,"",MAX($H$4,E16,D17,C17)) -> 7794.35 | F17: =IF(AND(ISNUMBER(B17),ISNUMBER(C17),C17>0,ISNUMBER(E17),E17>0),MAX(0,1-C17/E17),"") | G17: =IF(F17="","",IF(ROUND(F17,10)<0.1,$B$4,IF(ROUND(F17,10)<0.2,$B$4+250,$B$4+500))) | H17: =MAX(0,$E$4-SUM($P$9:P16)) -> 5000 | I17: =IF(G17="",0,MIN(MAX(0,G17-$B$4),H17)) -> 0 | J17: =$B$4+I17 -> 500 | K17: =J17*总览!$B$8 -> 450 | L17: =J17*总览!$B$9 -> 50 | M17: =SUMIFS(交易记录!$D$6:$D$605,交易记录!$A$6:$A$605,">="&DATE(YEAR(A17),MONTH(A17),1),交易记录!$A$6:$A$605,"<"&DATE(YEAR(A17),MONTH(A17)+1,1),交易记录!$C$6:$C$605,"买入",交易记录!$P$6:$P$605,"<>分红再投",交易记录!$P$6:$P$605,"<>其他",交易记录!$B$6:$B$605,"VOO")+SUMIFS(交易记录!$D$6:$D$605,交易记录!$A$6:$A$605,">="&DATE(YEAR(A17),MONTH(A17),1),交易记录!$A$6:$A$605,"<"&DATE(YEAR(A17),MONTH(A17)+1,1),交易记录!$C$6:$C$605,"买入",交易记录!$P$6:$P$605,"<>分红再投",交易记录!$P$6:$P$605,"<>其他",交易记录!$B$6:$B$605,"QQQM")+SUMIFS(交易记录!$E$6:$E$605,交易记录!$A$6:$A$605,">="&DATE(YEAR(A17),MONTH(A17),1),交易记录!$A$6:$A$605,"<"&DATE(YEAR(A17),MONTH(A17)+1,1),交易记录!$C$6:$C$605,"买入",交易记录!$P$6:$P$605,"<>分红再投",交易记录!$P$6:$P$605,"<>其他",交易记录!$B$6:$B$605,"VOO")+SUMIFS(交易记录!$E$6:$E$605,交易记录!$A$6:$A$605,">="&DATE(YEAR(A17),MONTH(A17),1),交易记录!$A$6:$A$605,"<"&DATE(YEAR(A17),MONTH(A17)+1,1),交易记录!$C$6:$C$605,"买入",交易记录!$P$6:$P$605,"<>分红再投",交易记录!$P$6:$P$605,"<>其他",交易记录!$B$6:$B$605,"QQQM") -> 0 | N17: =MAX(0,M17-$B$4) -> 0 | P17: =IF(O17="",N17,O17) -> 0 | Q17: =MAX(0,H17-P17) -> 5000 | R17: =IF(P17>H17+0.005,"实际加投超剩余预算，请核对",IF(H17=0,"预算用完：基础定投",IF(F17="","待补指数收盘／历史基准；先列基础额",IF(AND(B17>A17,M17=0),"核对观察日是否在实际交易前",IF(AND(O17<>"",ABS(O17-N17)>0.005),"已按手填额外支出扣预算",IF(M17=0,"已计算，尚未记录买入",IF(ABS(M17-J17)<0.01,"已按计划记录","实际定投与计划有差额"))))))) -> 待补指数收盘／历史基准；先列基础额
A18: =月度计划!A15 -> 46578 | E18: =IF(MAX($H$4,E17,D18)<=0,"",MAX($H$4,E17,D18,C18)) -> 7794.35 | F18: =IF(AND(ISNUMBER(B18),ISNUMBER(C18),C18>0,ISNUMBER(E18),E18>0),MAX(0,1-C18/E18),"") | G18: =IF(F18="","",IF(ROUND(F18,10)<0.1,$B$4,IF(ROUND(F18,10)<0.2,$B$4+250,$B$4+500))) | H18: =MAX(0,$E$4-SUM($P$9:P17)) -> 5000 | I18: =IF(G18="",0,MIN(MAX(0,G18-$B$4),H18)) -> 0 | J18: =$B$4+I18 -> 500 | K18: =J18*总览!$B$8 -> 450 | L18: =J18*总览!$B$9 -> 50 | M18: =SUMIFS(交易记录!$D$6:$D$605,交易记录!$A$6:$A$605,">="&DATE(YEAR(A18),MONTH(A18),1),交易记录!$A$6:$A$605,"<"&DATE(YEAR(A18),MONTH(A18)+1,1),交易记录!$C$6:$C$605,"买入",交易记录!$P$6:$P$605,"<>分红再投",交易记录!$P$6:$P$605,"<>其他",交易记录!$B$6:$B$605,"VOO")+SUMIFS(交易记录!$D$6:$D$605,交易记录!$A$6:$A$605,">="&DATE(YEAR(A18),MONTH(A18),1),交易记录!$A$6:$A$605,"<"&DATE(YEAR(A18),MONTH(A18)+1,1),交易记录!$C$6:$C$605,"买入",交易记录!$P$6:$P$605,"<>分红再投",交易记录!$P$6:$P$605,"<>其他",交易记录!$B$6:$B$605,"QQQM")+SUMIFS(交易记录!$E$6:$E$605,交易记录!$A$6:$A$605,">="&DATE(YEAR(A18),MONTH(A18),1),交易记录!$A$6:$A$605,"<"&DATE(YEAR(A18),MONTH(A18)+1,1),交易记录!$C$6:$C$605,"买入",交易记录!$P$6:$P$605,"<>分红再投",交易记录!$P$6:$P$605,"<>其他",交易记录!$B$6:$B$605,"VOO")+SUMIFS(交易记录!$E$6:$E$605,交易记录!$A$6:$A$605,">="&DATE(YEAR(A18),MONTH(A18),1),交易记录!$A$6:$A$605,"<"&DATE(YEAR(A18),MONTH(A18)+1,1),交易记录!$C$6:$C$605,"买入",交易记录!$P$6:$P$605,"<>分红再投",交易记录!$P$6:$P$605,"<>其他",交易记录!$B$6:$B$605,"QQQM") -> 0 | N18: =MAX(0,M18-$B$4) -> 0 | P18: =IF(O18="",N18,O18) -> 0 | Q18: =MAX(0,H18-P18) -> 5000 | R18: =IF(P18>H18+0.005,"实际加投超剩余预算，请核对",IF(H18=0,"预算用完：基础定投",IF(F18="","待补指数收盘／历史基准；先列基础额",IF(AND(B18>A18,M18=0),"核对观察日是否在实际交易前",IF(AND(O18<>"",ABS(O18-N18)>0.005),"已按手填额外支出扣预算",IF(M18=0,"已计算，尚未记录买入",IF(ABS(M18-J18)<0.01,"已按计划记录","实际定投与计划有差额"))))))) -> 待补指数收盘／历史基准；先列基础额
A19: =月度计划!A16 -> 46609 | E19: =IF(MAX($H$4,E18,D19)<=0,"",MAX($H$4,E18,D19,C19)) -> 7794.35 | F19: =IF(AND(ISNUMBER(B19),ISNUMBER(C19),C19>0,ISNUMBER(E19),E19>0),MAX(0,1-C19/E19),"") | G19: =IF(F19="","",IF(ROUND(F19,10)<0.1,$B$4,IF(ROUND(F19,10)<0.2,$B$4+250,$B$4+500))) | H19: =MAX(0,$E$4-SUM($P$9:P18)) -> 5000 | I19: =IF(G19="",0,MIN(MAX(0,G19-$B$4),H19)) -> 0 | J19: =$B$4+I19 -> 500 | K19: =J19*总览!$B$8 -> 450 | L19: =J19*总览!$B$9 -> 50 | M19: =SUMIFS(交易记录!$D$6:$D$605,交易记录!$A$6:$A$605,">="&DATE(YEAR(A19),MONTH(A19),1),交易记录!$A$6:$A$605,"<"&DATE(YEAR(A19),MONTH(A19)+1,1),交易记录!$C$6:$C$605,"买入",交易记录!$P$6:$P$605,"<>分红再投",交易记录!$P$6:$P$605,"<>其他",交易记录!$B$6:$B$605,"VOO")+SUMIFS(交易记录!$D$6:$D$605,交易记录!$A$6:$A$605,">="&DATE(YEAR(A19),MONTH(A19),1),交易记录!$A$6:$A$605,"<"&DATE(YEAR(A19),MONTH(A19)+1,1),交易记录!$C$6:$C$605,"买入",交易记录!$P$6:$P$605,"<>分红再投",交易记录!$P$6:$P$605,"<>其他",交易记录!$B$6:$B$605,"QQQM")+SUMIFS(交易记录!$E$6:$E$605,交易记录!$A$6:$A$605,">="&DATE(YEAR(A19),MONTH(A19),1),交易记录!$A$6:$A$605,"<"&DATE(YEAR(A19),MONTH(A19)+1,1),交易记录!$C$6:$C$605,"买入",交易记录!$P$6:$P$605,"<>分红再投",交易记录!$P$6:$P$605,"<>其他",交易记录!$B$6:$B$605,"VOO")+SUMIFS(交易记录!$E$6:$E$605,交易记录!$A$6:$A$605,">="&DATE(YEAR(A19),MONTH(A19),1),交易记录!$A$6:$A$605,"<"&DATE(YEAR(A19),MONTH(A19)+1,1),交易记录!$C$6:$C$605,"买入",交易记录!$P$6:$P$605,"<>分红再投",交易记录!$P$6:$P$605,"<>其他",交易记录!$B$6:$B$605,"QQQM") -> 0 | N19: =MAX(0,M19-$B$4) -> 0 | P19: =IF(O19="",N19,O19) -> 0 | Q19: =MAX(0,H19-P19) -> 5000 | R19: =IF(P19>H19+0.005,"实际加投超剩余预算，请核对",IF(H19=0,"预算用完：基础定投",IF(F19="","待补指数收盘／历史基准；先列基础额",IF(AND(B19>A19,M19=0),"核对观察日是否在实际交易前",IF(AND(O19<>"",ABS(O19-N19)>0.005),"已按手填额外支出扣预算",IF(M19=0,"已计算，尚未记录买入",IF(ABS(M19-J19)<0.01,"已按计划记录","实际定投与计划有差额"))))))) -> 待补指数收盘／历史基准；先列基础额
A20: =月度计划!A17 -> 46640 | E20: =IF(MAX($H$4,E19,D20)<=0,"",MAX($H$4,E19,D20,C20)) -> 7794.35 | F20: =IF(AND(ISNUMBER(B20),ISNUMBER(C20),C20>0,ISNUMBER(E20),E20>0),MAX(0,1-C20/E20),"") | G20: =IF(F20="","",IF(ROUND(F20,10)<0.1,$B$4,IF(ROUND(F20,10)<0.2,$B$4+250,$B$4+500))) | H20: =MAX(0,$E$4-SUM($P$9:P19)) -> 5000 | I20: =IF(G20="",0,MIN(MAX(0,G20-$B$4),H20)) -> 0 | J20: =$B$4+I20 -> 500 | K20: =J20*总览!$B$8 -> 450 | L20: =J20*总览!$B$9 -> 50 | M20: =SUMIFS(交易记录!$D$6:$D$605,交易记录!$A$6:$A$605,">="&DATE(YEAR(A20),MONTH(A20),1),交易记录!$A$6:$A$605,"<"&DATE(YEAR(A20),MONTH(A20)+1,1),交易记录!$C$6:$C$605,"买入",交易记录!$P$6:$P$605,"<>分红再投",交易记录!$P$6:$P$605,"<>其他",交易记录!$B$6:$B$605,"VOO")+SUMIFS(交易记录!$D$6:$D$605,交易记录!$A$6:$A$605,">="&DATE(YEAR(A20),MONTH(A20),1),交易记录!$A$6:$A$605,"<"&DATE(YEAR(A20),MONTH(A20)+1,1),交易记录!$C$6:$C$605,"买入",交易记录!$P$6:$P$605,"<>分红再投",交易记录!$P$6:$P$605,"<>其他",交易记录!$B$6:$B$605,"QQQM")+SUMIFS(交易记录!$E$6:$E$605,交易记录!$A$6:$A$605,">="&DATE(YEAR(A20),MONTH(A20),1),交易记录!$A$6:$A$605,"<"&DATE(YEAR(A20),MONTH(A20)+1,1),交易记录!$C$6:$C$605,"买入",交易记录!$P$6:$P$605,"<>分红再投",交易记录!$P$6:$P$605,"<>其他",交易记录!$B$6:$B$605,"VOO")+SUMIFS(交易记录!$E$6:$E$605,交易记录!$A$6:$A$605,">="&DATE(YEAR(A20),MONTH(A20),1),交易记录!$A$6:$A$605,"<"&DATE(YEAR(A20),MONTH(A20)+1,1),交易记录!$C$6:$C$605,"买入",交易记录!$P$6:$P$605,"<>分红再投",交易记录!$P$6:$P$605,"<>其他",交易记录!$B$6:$B$605,"QQQM") -> 0 | N20: =MAX(0,M20-$B$4) -> 0 | P20: =IF(O20="",N20,O20) -> 0 | Q20: =MAX(0,H20-P20) -> 5000 | R20: =IF(P20>H20+0.005,"实际加投超剩余预算，请核对",IF(H20=0,"预算用完：基础定投",IF(F20="","待补指数收盘／历史基准；先列基础额",IF(AND(B20>A20,M20=0),"核对观察日是否在实际交易前",IF(AND(O20<>"",ABS(O20-N20)>0.005),"已按手填额外支出扣预算",IF(M20=0,"已计算，尚未记录买入",IF(ABS(M20-J20)<0.01,"已按计划记录","实际定投与计划有差额"))))))) -> 待补指数收盘／历史基准；先列基础额
A21: =月度计划!A18 -> 46670 | E21: =IF(MAX($H$4,E20,D21)<=0,"",MAX($H$4,E20,D21,C21)) -> 7794.35 | F21: =IF(AND(ISNUMBER(B21),ISNUMBER(C21),C21>0,ISNUMBER(E21),E21>0),MAX(0,1-C21/E21),"") | G21: =IF(F21="","",IF(ROUND(F21,10)<0.1,$B$4,IF(ROUND(F21,10)<0.2,$B$4+250,$B$4+500))) | H21: =MAX(0,$E$4-SUM($P$9:P20)) -> 5000 | I21: =IF(G21="",0,MIN(MAX(0,G21-$B$4),H21)) -> 0 | J21: =$B$4+I21 -> 500 | K21: =J21*总览!$B$8 -> 450 | L21: =J21*总览!$B$9 -> 50 | M21: =SUMIFS(交易记录!$D$6:$D$605,交易记录!$A$6:$A$605,">="&DATE(YEAR(A21),MONTH(A21),1),交易记录!$A$6:$A$605,"<"&DATE(YEAR(A21),MONTH(A21)+1,1),交易记录!$C$6:$C$605,"买入",交易记录!$P$6:$P$605,"<>分红再投",交易记录!$P$6:$P$605,"<>其他",交易记录!$B$6:$B$605,"VOO")+SUMIFS(交易记录!$D$6:$D$605,交易记录!$A$6:$A$605,">="&DATE(YEAR(A21),MONTH(A21),1),交易记录!$A$6:$A$605,"<"&DATE(YEAR(A21),MONTH(A21)+1,1),交易记录!$C$6:$C$605,"买入",交易记录!$P$6:$P$605,"<>分红再投",交易记录!$P$6:$P$605,"<>其他",交易记录!$B$6:$B$605,"QQQM")+SUMIFS(交易记录!$E$6:$E$605,交易记录!$A$6:$A$605,">="&DATE(YEAR(A21),MONTH(A21),1),交易记录!$A$6:$A$605,"<"&DATE(YEAR(A21),MONTH(A21)+1,1),交易记录!$C$6:$C$605,"买入",交易记录!$P$6:$P$605,"<>分红再投",交易记录!$P$6:$P$605,"<>其他",交易记录!$B$6:$B$605,"VOO")+SUMIFS(交易记录!$E$6:$E$605,交易记录!$A$6:$A$605,">="&DATE(YEAR(A21),MONTH(A21),1),交易记录!$A$6:$A$605,"<"&DATE(YEAR(A21),MONTH(A21)+1,1),交易记录!$C$6:$C$605,"买入",交易记录!$P$6:$P$605,"<>分红再投",交易记录!$P$6:$P$605,"<>其他",交易记录!$B$6:$B$605,"QQQM") -> 0 | N21: =MAX(0,M21-$B$4) -> 0 | P21: =IF(O21="",N21,O21) -> 0 | Q21: =MAX(0,H21-P21) -> 5000 | R21: =IF(P21>H21+0.005,"实际加投超剩余预算，请核对",IF(H21=0,"预算用完：基础定投",IF(F21="","待补指数收盘／历史基准；先列基础额",IF(AND(B21>A21,M21=0),"核对观察日是否在实际交易前",IF(AND(O21<>"",ABS(O21-N21)>0.005),"已按手填额外支出扣预算",IF(M21=0,"已计算，尚未记录买入",IF(ABS(M21-J21)<0.01,"已按计划记录","实际定投与计划有差额"))))))) -> 待补指数收盘／历史基准；先列基础额
... A128: =月度计划!A125 -> 49928 | E128: =IF(MAX($H$4,E127,D128)<=0,"",MAX($H$4,E127,D128,C128)) -> 7794.35 | F128: =IF(AND(ISNUMBER(B128),ISNUMBER(C128),C128>0,ISNUMBER(E128),E128>0),MAX(0,1-C128/E128),"") | G128: =IF(F128="","",IF(ROUND(F128,10)<0.1,$B$4,IF(ROUND(F128,10)<0.2,$B$4+250,$B$4+500))) | H128: =MAX(0,$E$4-SUM($P$9:P127)) -> 5000 | I128: =IF(G128="",0,MIN(MAX(0,G128-$B$4),H128)) -> 0 | J128: =$B$4+I128 -> 500 | K128: =J128*总览!$B$8 -> 450 | L128: =J128*总览!$B$9 -> 50 | M128: =SUMIFS(交易记录!$D$6:$D$605,交易记录!$A$6:$A$605,">="&DATE(YEAR(A128),MONTH(A128),1),交易记录!$A$6:$A$605,"<"&DATE(YEAR(A128),MONTH(A128)+1,1),交易记录!$C$6:$C$605,"买入",交易记录!$P$6:$P$605,"<>分红再投",交易记录!$P$6:$P$605,"<>其他",交易记录!$B$6:$B$605,"VOO")+SUMIFS(交易记录!$D$6:$D$605,交易记录!$A$6:$A$605,">="&DATE(YEAR(A128),MONTH(A128),1),交易记录!$A$6:$A$605,"<"&DATE(YEAR(A128),MONTH(A128)+1,1),交易记录!$C$6:$C$605,"买入",交易记录!$P$6:$P$605,"<>分红再投",交易记录!$P$6:$P$605,"<>其他",交易记录!$B$6:$B$605,"QQQM")+SUMIFS(交易记录!$E$6:$E$605,交易记录!$A$6:$A$605,">="&DATE(YEAR(A128),MONTH(A128),1),交易记录!$A$6:$A$605,"<"&DATE(YEAR(A128),MONTH(A128)+1,1),交易记录!$C$6:$C$605,"买入",交易记录!$P$6:$P$605,"<>分红再投",交易记录!$P$6:$P$605,"<>其他",交易记录!$B$6:$B$605,"VOO")+SUMIFS(交易记录!$E$6:$E$605,交易记录!$A$6:$A$605,">="&DATE(YEAR(A128),MONTH(A128),1),交易记录!$A$6:$A$605,"<"&DATE(YEAR(A128),MONTH(A128)+1,1),交易记录!$C$6:$C$605,"买入",交易记录!$P$6:$P$605,"<>分红再投",交易记录!$P$6:$P$605,"<>其他",交易记录!$B$6:$B$605,"QQQM") -> 0 | N128: =MAX(0,M128-$B$4) -> 0 | P128: =IF(O128="",N128,O128) -> 0 | Q128: =MAX(0,H128-P128) -> 5000 | R128: =IF(P128>H128+0.005,"实际加投超剩余预算，请核对",IF(H128=0,"预算用完：基础定投",IF(F128="","待补指数收盘／历史基准；先列基础额",IF(AND(B128>A128,M128=0),"核对观察日是否在实际交易前",IF(AND(O128<>"",ABS(O128-N128)>0.005),"已按手填额外支出扣预算",IF(M128=0,"已计算，尚未记录买入",IF(ABS(M128-J128)<0.01,"已按计划记录","实际定投与计划有差额"))))))) -> 待补指数收盘／历史基准；先列基础额

Sheet 月度计划
A1: 月度计划
A3: 每月金额关联“回撤计划”，VOO 90%／QQQM 10%。指数资料未填时仅列基础500；实际买入含手续费，分红再投／其他仍显示在实际合计，请结合回撤表常规定投核对。
A5: 计划日期 | B5: 回撤计划总额 USD | C5: VOO计划 USD | D5: QQQM计划 USD | E5: SMH计划 USD | F5: VOO实际 USD | G5: QQQM实际 USD | H5: SMH实际 USD | I5: 实际合计 USD | J5: 实际－预算 USD | K5: 执行状态
A6: =DATE(2026,10,总览!$E$4) -> 46305 | B6: =回撤计划!J9 -> 500 | C6: =B6*总览!$B$8 -> 450 | D6: =B6*总览!$B$9 -> 50 | E6: =B6*总览!$B$10 -> 0 | F6: =SUMIFS(交易记录!$D$6:$D$605,交易记录!$A$6:$A$605,">="&DATE(YEAR(A6),MONTH(A6),1),交易记录!$A$6:$A$605,"<"&DATE(YEAR(A6),MONTH(A6)+1,1),交易记录!$B$6:$B$605,"VOO",交易记录!$C$6:$C$605,"买入")+SUMIFS(交易记录!$E$6:$E$605,交易记录!$A$6:$A$605,">="&DATE(YEAR(A6),MONTH(A6),1),交易记录!$A$6:$A$605,"<"&DATE(YEAR(A6),MONTH(A6)+1,1),交易记录!$B$6:$B$605,"VOO",交易记录!$C$6:$C$605,"买入") -> 0 | G6: =SUMIFS(交易记录!$D$6:$D$605,交易记录!$A$6:$A$605,">="&DATE(YEAR(A6),MONTH(A6),1),交易记录!$A$6:$A$605,"<"&DATE(YEAR(A6),MONTH(A6)+1,1),交易记录!$B$6:$B$605,"QQQM",交易记录!$C$6:$C$605,"买入")+SUMIFS(交易记录!$E$6:$E$605,交易记录!$A$6:$A$605,">="&DATE(YEAR(A6),MONTH(A6),1),交易记录!$A$6:$A$605,"<"&DATE(YEAR(A6),MONTH(A6)+1,1),交易记录!$B$6:$B$605,"QQQM",交易记录!$C$6:$C$605,"买入") -> 0 | H6: =SUMIFS(交易记录!$D$6:$D$605,交易记录!$A$6:$A$605,">="&DATE(YEAR(A6),MONTH(A6),1),交易记录!$A$6:$A$605,"<"&DATE(YEAR(A6),MONTH(A6)+1,1),交易记录!$B$6:$B$605,"SMH",交易记录!$C$6:$C$605,"买入")+SUMIFS(交易记录!$E$6:$E$605,交易记录!$A$6:$A$605,">="&DATE(YEAR(A6),MONTH(A6),1),交易记录!$A$6:$A$605,"<"&DATE(YEAR(A6),MONTH(A6)+1,1),交易记录!$B$6:$B$605,"SMH",交易记录!$C$6:$C$605,"买入") -> 0 | I6: =SUM(F6:H6) -> 0 | J6: =IF(I6=0,"",I6-B6) | K6: =IF(I6=0,"尚未记录买入",IF(ABS(J6)<0.01,"已记录预算金额","已记录，金额有差额")) -> 尚未记录买入
A7: =DATE(2026,11,总览!$E$4) -> 46336 | B7: =回撤计划!J10 -> 500 | C7: =B7*总览!$B$8 -> 450 | D7: =B7*总览!$B$9 -> 50 | E7: =B7*总览!$B$10 -> 0 | F7: =SUMIFS(交易记录!$D$6:$D$605,交易记录!$A$6:$A$605,">="&DATE(YEAR(A7),MONTH(A7),1),交易记录!$A$6:$A$605,"<"&DATE(YEAR(A7),MONTH(A7)+1,1),交易记录!$B$6:$B$605,"VOO",交易记录!$C$6:$C$605,"买入")+SUMIFS(交易记录!$E$6:$E$605,交易记录!$A$6:$A$605,">="&DATE(YEAR(A7),MONTH(A7),1),交易记录!$A$6:$A$605,"<"&DATE(YEAR(A7),MONTH(A7)+1,1),交易记录!$B$6:$B$605,"VOO",交易记录!$C$6:$C$605,"买入") -> 0 | G7: =SUMIFS(交易记录!$D$6:$D$605,交易记录!$A$6:$A$605,">="&DATE(YEAR(A7),MONTH(A7),1),交易记录!$A$6:$A$605,"<"&DATE(YEAR(A7),MONTH(A7)+1,1),交易记录!$B$6:$B$605,"QQQM",交易记录!$C$6:$C$605,"买入")+SUMIFS(交易记录!$E$6:$E$605,交易记录!$A$6:$A$605,">="&DATE(YEAR(A7),MONTH(A7),1),交易记录!$A$6:$A$605,"<"&DATE(YEAR(A7),MONTH(A7)+1,1),交易记录!$B$6:$B$605,"QQQM",交易记录!$C$6:$C$605,"买入") -> 0 | H7: =SUMIFS(交易记录!$D$6:$D$605,交易记录!$A$6:$A$605,">="&DATE(YEAR(A7),MONTH(A7),1),交易记录!$A$6:$A$605,"<"&DATE(YEAR(A7),MONTH(A7)+1,1),交易记录!$B$6:$B$605,"SMH",交易记录!$C$6:$C$605,"买入")+SUMIFS(交易记录!$E$6:$E$605,交易记录!$A$6:$A$605,">="&DATE(YEAR(A7),MONTH(A7),1),交易记录!$A$6:$A$605,"<"&DATE(YEAR(A7),MONTH(A7)+1,1),交易记录!$B$6:$B$605,"SMH",交易记录!$C$6:$C$605,"买入") -> 0 | I7: =SUM(F7:H7) -> 0 | J7: =IF(I7=0,"",I7-B7) | K7: =IF(I7=0,"尚未记录买入",IF(ABS(J7)<0.01,"已记录预算金额","已记录，金额有差额")) -> 尚未记录买入
A8: =DATE(2026,12,总览!$E$4) -> 46366 | B8: =回撤计划!J11 -> 500 | C8: =B8*总览!$B$8 -> 450 | D8: =B8*总览!$B$9 -> 50 | E8: =B8*总览!$B$10 -> 0 | F8: =SUMIFS(交易记录!$D$6:$D$605,交易记录!$A$6:$A$605,">="&DATE(YEAR(A8),MONTH(A8),1),交易记录!$A$6:$A$605,"<"&DATE(YEAR(A8),MONTH(A8)+1,1),交易记录!$B$6:$B$605,"VOO",交易记录!$C$6:$C$605,"买入")+SUMIFS(交易记录!$E$6:$E$605,交易记录!$A$6:$A$605,">="&DATE(YEAR(A8),MONTH(A8),1),交易记录!$A$6:$A$605,"<"&DATE(YEAR(A8),MONTH(A8)+1,1),交易记录!$B$6:$B$605,"VOO",交易记录!$C$6:$C$605,"买入") -> 0 | G8: =SUMIFS(交易记录!$D$6:$D$605,交易记录!$A$6:$A$605,">="&DATE(YEAR(A8),MONTH(A8),1),交易记录!$A$6:$A$605,"<"&DATE(YEAR(A8),MONTH(A8)+1,1),交易记录!$B$6:$B$605,"QQQM",交易记录!$C$6:$C$605,"买入")+SUMIFS(交易记录!$E$6:$E$605,交易记录!$A$6:$A$605,">="&DATE(YEAR(A8),MONTH(A8),1),交易记录!$A$6:$A$605,"<"&DATE(YEAR(A8),MONTH(A8)+1,1),交易记录!$B$6:$B$605,"QQQM",交易记录!$C$6:$C$605,"买入") -> 0 | H8: =SUMIFS(交易记录!$D$6:$D$605,交易记录!$A$6:$A$605,">="&DATE(YEAR(A8),MONTH(A8),1),交易记录!$A$6:$A$605,"<"&DATE(YEAR(A8),MONTH(A8)+1,1),交易记录!$B$6:$B$605,"SMH",交易记录!$C$6:$C$605,"买入")+SUMIFS(交易记录!$E$6:$E$605,交易记录!$A$6:$A$605,">="&DATE(YEAR(A8),MONTH(A8),1),交易记录!$A$6:$A$605,"<"&DATE(YEAR(A8),MONTH(A8)+1,1),交易记录!$B$6:$B$605,"SMH",交易记录!$C$6:$C$605,"买入") -> 0 | I8: =SUM(F8:H8) -> 0 | J8: =IF(I8=0,"",I8-B8) | K8: =IF(I8=0,"尚未记录买入",IF(ABS(J8)<0.01,"已记录预算金额","已记录，金额有差额")) -> 尚未记录买入
A9: =DATE(2027,1,总览!$E$4) -> 46397 | B9: =回撤计划!J12 -> 500 | C9: =B9*总览!$B$8 -> 450 | D9: =B9*总览!$B$9 -> 50 | E9: =B9*总览!$B$10 -> 0 | F9: =SUMIFS(交易记录!$D$6:$D$605,交易记录!$A$6:$A$605,">="&DATE(YEAR(A9),MONTH(A9),1),交易记录!$A$6:$A$605,"<"&DATE(YEAR(A9),MONTH(A9)+1,1),交易记录!$B$6:$B$605,"VOO",交易记录!$C$6:$C$605,"买入")+SUMIFS(交易记录!$E$6:$E$605,交易记录!$A$6:$A$605,">="&DATE(YEAR(A9),MONTH(A9),1),交易记录!$A$6:$A$605,"<"&DATE(YEAR(A9),MONTH(A9)+1,1),交易记录!$B$6:$B$605,"VOO",交易记录!$C$6:$C$605,"买入") -> 0 | G9: =SUMIFS(交易记录!$D$6:$D$605,交易记录!$A$6:$A$605,">="&DATE(YEAR(A9),MONTH(A9),1),交易记录!$A$6:$A$605,"<"&DATE(YEAR(A9),MONTH(A9)+1,1),交易记录!$B$6:$B$605,"QQQM",交易记录!$C$6:$C$605,"买入")+SUMIFS(交易记录!$E$6:$E$605,交易记录!$A$6:$A$605,">="&DATE(YEAR(A9),MONTH(A9),1),交易记录!$A$6:$A$605,"<"&DATE(YEAR(A9),MONTH(A9)+1,1),交易记录!$B$6:$B$605,"QQQM",交易记录!$C$6:$C$605,"买入") -> 0 | H9: =SUMIFS(交易记录!$D$6:$D$605,交易记录!$A$6:$A$605,">="&DATE(YEAR(A9),MONTH(A9),1),交易记录!$A$6:$A$605,"<"&DATE(YEAR(A9),MONTH(A9)+1,1),交易记录!$B$6:$B$605,"SMH",交易记录!$C$6:$C$605,"买入")+SUMIFS(交易记录!$E$6:$E$605,交易记录!$A$6:$A$605,">="&DATE(YEAR(A9),MONTH(A9),1),交易记录!$A$6:$A$605,"<"&DATE(YEAR(A9),MONTH(A9)+1,1),交易记录!$B$6:$B$605,"SMH",交易记录!$C$6:$C$605,"买入") -> 0 | I9: =SUM(F9:H9) -> 0 | J9: =IF(I9=0,"",I9-B9) | K9: =IF(I9=0,"尚未记录买入",IF(ABS(J9)<0.01,"已记录预算金额","已记录，金额有差额")) -> 尚未记录买入
A10: =DATE(2027,2,总览!$E$4) -> 46428 | B10: =回撤计划!J13 -> 500 | C10: =B10*总览!$B$8 -> 450 | D10: =B10*总览!$B$9 -> 50 | E10: =B10*总览!$B$10 -> 0 | F10: =SUMIFS(交易记录!$D$6:$D$605,交易记录!$A$6:$A$605,">="&DATE(YEAR(A10),MONTH(A10),1),交易记录!$A$6:$A$605,"<"&DATE(YEAR(A10),MONTH(A10)+1,1),交易记录!$B$6:$B$605,"VOO",交易记录!$C$6:$C$605,"买入")+SUMIFS(交易记录!$E$6:$E$605,交易记录!$A$6:$A$605,">="&DATE(YEAR(A10),MONTH(A10),1),交易记录!$A$6:$A$605,"<"&DATE(YEAR(A10),MONTH(A10)+1,1),交易记录!$B$6:$B$605,"VOO",交易记录!$C$6:$C$605,"买入") -> 0 | G10: =SUMIFS(交易记录!$D$6:$D$605,交易记录!$A$6:$A$605,">="&DATE(YEAR(A10),MONTH(A10),1),交易记录!$A$6:$A$605,"<"&DATE(YEAR(A10),MONTH(A10)+1,1),交易记录!$B$6:$B$605,"QQQM",交易记录!$C$6:$C$605,"买入")+SUMIFS(交易记录!$E$6:$E$605,交易记录!$A$6:$A$605,">="&DATE(YEAR(A10),MONTH(A10),1),交易记录!$A$6:$A$605,"<"&DATE(YEAR(A10),MONTH(A10)+1,1),交易记录!$B$6:$B$605,"QQQM",交易记录!$C$6:$C$605,"买入") -> 0 | H10: =SUMIFS(交易记录!$D$6:$D$605,交易记录!$A$6:$A$605,">="&DATE(YEAR(A10),MONTH(A10),1),交易记录!$A$6:$A$605,"<"&DATE(YEAR(A10),MONTH(A10)+1,1),交易记录!$B$6:$B$605,"SMH",交易记录!$C$6:$C$605,"买入")+SUMIFS(交易记录!$E$6:$E$605,交易记录!$A$6:$A$605,">="&DATE(YEAR(A10),MONTH(A10),1),交易记录!$A$6:$A$605,"<"&DATE(YEAR(A10),MONTH(A10)+1,1),交易记录!$B$6:$B$605,"SMH",交易记录!$C$6:$C$605,"买入") -> 0 | I10: =SUM(F10:H10) -> 0 | J10: =IF(I10=0,"",I10-B10) | K10: =IF(I10=0,"尚未记录买入",IF(ABS(J10)<0.01,"已记录预算金额","已记录，金额有差额")) -> 尚未记录买入
A11: =DATE(2027,3,总览!$E$4) -> 46456 | B11: =回撤计划!J14 -> 500 | C11: =B11*总览!$B$8 -> 450 | D11: =B11*总览!$B$9 -> 50 | E11: =B11*总览!$B$10 -> 0 | F11: =SUMIFS(交易记录!$D$6:$D$605,交易记录!$A$6:$A$605,">="&DATE(YEAR(A11),MONTH(A11),1),交易记录!$A$6:$A$605,"<"&DATE(YEAR(A11),MONTH(A11)+1,1),交易记录!$B$6:$B$605,"VOO",交易记录!$C$6:$C$605,"买入")+SUMIFS(交易记录!$E$6:$E$605,交易记录!$A$6:$A$605,">="&DATE(YEAR(A11),MONTH(A11),1),交易记录!$A$6:$A$605,"<"&DATE(YEAR(A11),MONTH(A11)+1,1),交易记录!$B$6:$B$605,"VOO",交易记录!$C$6:$C$605,"买入") -> 0 | G11: =SUMIFS(交易记录!$D$6:$D$605,交易记录!$A$6:$A$605,">="&DATE(YEAR(A11),MONTH(A11),1),交易记录!$A$6:$A$605,"<"&DATE(YEAR(A11),MONTH(A11)+1,1),交易记录!$B$6:$B$605,"QQQM",交易记录!$C$6:$C$605,"买入")+SUMIFS(交易记录!$E$6:$E$605,交易记录!$A$6:$A$605,">="&DATE(YEAR(A11),MONTH(A11),1),交易记录!$A$6:$A$605,"<"&DATE(YEAR(A11),MONTH(A11)+1,1),交易记录!$B$6:$B$605,"QQQM",交易记录!$C$6:$C$605,"买入") -> 0 | H11: =SUMIFS(交易记录!$D$6:$D$605,交易记录!$A$6:$A$605,">="&DATE(YEAR(A11),MONTH(A11),1),交易记录!$A$6:$A$605,"<"&DATE(YEAR(A11),MONTH(A11)+1,1),交易记录!$B$6:$B$605,"SMH",交易记录!$C$6:$C$605,"买入")+SUMIFS(交易记录!$E$6:$E$605,交易记录!$A$6:$A$605,">="&DATE(YEAR(A11),MONTH(A11),1),交易记录!$A$6:$A$605,"<"&DATE(YEAR(A11),MONTH(A11)+1,1),交易记录!$B$6:$B$605,"SMH",交易记录!$C$6:$C$605,"买入") -> 0 | I11: =SUM(F11:H11) -> 0 | J11: =IF(I11=0,"",I11-B11) | K11: =IF(I11=0,"尚未记录买入",IF(ABS(J11)<0.01,"已记录预算金额","已记录，金额有差额")) -> 尚未记录买入
A12: =DATE(2027,4,总览!$E$4) -> 46487 | B12: =回撤计划!J15 -> 500 | C12: =B12*总览!$B$8 -> 450 | D12: =B12*总览!$B$9 -> 50 | E12: =B12*总览!$B$10 -> 0 | F12: =SUMIFS(交易记录!$D$6:$D$605,交易记录!$A$6:$A$605,">="&DATE(YEAR(A12),MONTH(A12),1),交易记录!$A$6:$A$605,"<"&DATE(YEAR(A12),MONTH(A12)+1,1),交易记录!$B$6:$B$605,"VOO",交易记录!$C$6:$C$605,"买入")+SUMIFS(交易记录!$E$6:$E$605,交易记录!$A$6:$A$605,">="&DATE(YEAR(A12),MONTH(A12),1),交易记录!$A$6:$A$605,"<"&DATE(YEAR(A12),MONTH(A12)+1,1),交易记录!$B$6:$B$605,"VOO",交易记录!$C$6:$C$605,"买入") -> 0 | G12: =SUMIFS(交易记录!$D$6:$D$605,交易记录!$A$6:$A$605,">="&DATE(YEAR(A12),MONTH(A12),1),交易记录!$A$6:$A$605,"<"&DATE(YEAR(A12),MONTH(A12)+1,1),交易记录!$B$6:$B$605,"QQQM",交易记录!$C$6:$C$605,"买入")+SUMIFS(交易记录!$E$6:$E$605,交易记录!$A$6:$A$605,">="&DATE(YEAR(A12),MONTH(A12),1),交易记录!$A$6:$A$605,"<"&DATE(YEAR(A12),MONTH(A12)+1,1),交易记录!$B$6:$B$605,"QQQM",交易记录!$C$6:$C$605,"买入") -> 0 | H12: =SUMIFS(交易记录!$D$6:$D$605,交易记录!$A$6:$A$605,">="&DATE(YEAR(A12),MONTH(A12),1),交易记录!$A$6:$A$605,"<"&DATE(YEAR(A12),MONTH(A12)+1,1),交易记录!$B$6:$B$605,"SMH",交易记录!$C$6:$C$605,"买入")+SUMIFS(交易记录!$E$6:$E$605,交易记录!$A$6:$A$605,">="&DATE(YEAR(A12),MONTH(A12),1),交易记录!$A$6:$A$605,"<"&DATE(YEAR(A12),MONTH(A12)+1,1),交易记录!$B$6:$B$605,"SMH",交易记录!$C$6:$C$605,"买入") -> 0 | I12: =SUM(F12:H12) -> 0 | J12: =IF(I12=0,"",I12-B12) | K12: =IF(I12=0,"尚未记录买入",IF(ABS(J12)<0.01,"已记录预算金额","已记录，金额有差额")) -> 尚未记录买入
A13: =DATE(2027,5,总览!$E$4) -> 46517 | B13: =回撤计划!J16 -> 500 | C13: =B13*总览!$B$8 -> 450 | D13: =B13*总览!$B$9 -> 50 | E13: =B13*总览!$B$10 -> 0 | F13: =SUMIFS(交易记录!$D$6:$D$605,交易记录!$A$6:$A$605,">="&DATE(YEAR(A13),MONTH(A13),1),交易记录!$A$6:$A$605,"<"&DATE(YEAR(A13),MONTH(A13)+1,1),交易记录!$B$6:$B$605,"VOO",交易记录!$C$6:$C$605,"买入")+SUMIFS(交易记录!$E$6:$E$605,交易记录!$A$6:$A$605,">="&DATE(YEAR(A13),MONTH(A13),1),交易记录!$A$6:$A$605,"<"&DATE(YEAR(A13),MONTH(A13)+1,1),交易记录!$B$6:$B$605,"VOO",交易记录!$C$6:$C$605,"买入") -> 0 | G13: =SUMIFS(交易记录!$D$6:$D$605,交易记录!$A$6:$A$605,">="&DATE(YEAR(A13),MONTH(A13),1),交易记录!$A$6:$A$605,"<"&DATE(YEAR(A13),MONTH(A13)+1,1),交易记录!$B$6:$B$605,"QQQM",交易记录!$C$6:$C$605,"买入")+SUMIFS(交易记录!$E$6:$E$605,交易记录!$A$6:$A$605,">="&DATE(YEAR(A13),MONTH(A13),1),交易记录!$A$6:$A$605,"<"&DATE(YEAR(A13),MONTH(A13)+1,1),交易记录!$B$6:$B$605,"QQQM",交易记录!$C$6:$C$605,"买入") -> 0 | H13: =SUMIFS(交易记录!$D$6:$D$605,交易记录!$A$6:$A$605,">="&DATE(YEAR(A13),MONTH(A13),1),交易记录!$A$6:$A$605,"<"&DATE(YEAR(A13),MONTH(A13)+1,1),交易记录!$B$6:$B$605,"SMH",交易记录!$C$6:$C$605,"买入")+SUMIFS(交易记录!$E$6:$E$605,交易记录!$A$6:$A$605,">="&DATE(YEAR(A13),MONTH(A13),1),交易记录!$A$6:$A$605,"<"&DATE(YEAR(A13),MONTH(A13)+1,1),交易记录!$B$6:$B$605,"SMH",交易记录!$C$6:$C$605,"买入") -> 0 | I13: =SUM(F13:H13) -> 0 | J13: =IF(I13=0,"",I13-B13) | K13: =IF(I13=0,"尚未记录买入",IF(ABS(J13)<0.01,"已记录预算金额","已记录，金额有差额")) -> 尚未记录买入
A14: =DATE(2027,6,总览!$E$4) -> 46548 | B14: =回撤计划!J17 -> 500 | C14: =B14*总览!$B$8 -> 450 | D14: =B14*总览!$B$9 -> 50 | E14: =B14*总览!$B$10 -> 0 | F14: =SUMIFS(交易记录!$D$6:$D$605,交易记录!$A$6:$A$605,">="&DATE(YEAR(A14),MONTH(A14),1),交易记录!$A$6:$A$605,"<"&DATE(YEAR(A14),MONTH(A14)+1,1),交易记录!$B$6:$B$605,"VOO",交易记录!$C$6:$C$605,"买入")+SUMIFS(交易记录!$E$6:$E$605,交易记录!$A$6:$A$605,">="&DATE(YEAR(A14),MONTH(A14),1),交易记录!$A$6:$A$605,"<"&DATE(YEAR(A14),MONTH(A14)+1,1),交易记录!$B$6:$B$605,"VOO",交易记录!$C$6:$C$605,"买入") -> 0 | G14: =SUMIFS(交易记录!$D$6:$D$605,交易记录!$A$6:$A$605,">="&DATE(YEAR(A14),MONTH(A14),1),交易记录!$A$6:$A$605,"<"&DATE(YEAR(A14),MONTH(A14)+1,1),交易记录!$B$6:$B$605,"QQQM",交易记录!$C$6:$C$605,"买入")+SUMIFS(交易记录!$E$6:$E$605,交易记录!$A$6:$A$605,">="&DATE(YEAR(A14),MONTH(A14),1),交易记录!$A$6:$A$605,"<"&DATE(YEAR(A14),MONTH(A14)+1,1),交易记录!$B$6:$B$605,"QQQM",交易记录!$C$6:$C$605,"买入") -> 0 | H14: =SUMIFS(交易记录!$D$6:$D$605,交易记录!$A$6:$A$605,">="&DATE(YEAR(A14),MONTH(A14),1),交易记录!$A$6:$A$605,"<"&DATE(YEAR(A14),MONTH(A14)+1,1),交易记录!$B$6:$B$605,"SMH",交易记录!$C$6:$C$605,"买入")+SUMIFS(交易记录!$E$6:$E$605,交易记录!$A$6:$A$605,">="&DATE(YEAR(A14),MONTH(A14),1),交易记录!$A$6:$A$605,"<"&DATE(YEAR(A14),MONTH(A14)+1,1),交易记录!$B$6:$B$605,"SMH",交易记录!$C$6:$C$605,"买入") -> 0 | I14: =SUM(F14:H14) -> 0 | J14: =IF(I14=0,"",I14-B14) | K14: =IF(I14=0,"尚未记录买入",IF(ABS(J14)<0.01,"已记录预算金额","已记录，金额有差额")) -> 尚未记录买入
A15: =DATE(2027,7,总览!$E$4) -> 46578 | B15: =回撤计划!J18 -> 500 | C15: =B15*总览!$B$8 -> 450 | D15: =B15*总览!$B$9 -> 50 | E15: =B15*总览!$B$10 -> 0 | F15: =SUMIFS(交易记录!$D$6:$D$605,交易记录!$A$6:$A$605,">="&DATE(YEAR(A15),MONTH(A15),1),交易记录!$A$6:$A$605,"<"&DATE(YEAR(A15),MONTH(A15)+1,1),交易记录!$B$6:$B$605,"VOO",交易记录!$C$6:$C$605,"买入")+SUMIFS(交易记录!$E$6:$E$605,交易记录!$A$6:$A$605,">="&DATE(YEAR(A15),MONTH(A15),1),交易记录!$A$6:$A$605,"<"&DATE(YEAR(A15),MONTH(A15)+1,1),交易记录!$B$6:$B$605,"VOO",交易记录!$C$6:$C$605,"买入") -> 0 | G15: =SUMIFS(交易记录!$D$6:$D$605,交易记录!$A$6:$A$605,">="&DATE(YEAR(A15),MONTH(A15),1),交易记录!$A$6:$A$605,"<"&DATE(YEAR(A15),MONTH(A15)+1,1),交易记录!$B$6:$B$605,"QQQM",交易记录!$C$6:$C$605,"买入")+SUMIFS(交易记录!$E$6:$E$605,交易记录!$A$6:$A$605,">="&DATE(YEAR(A15),MONTH(A15),1),交易记录!$A$6:$A$605,"<"&DATE(YEAR(A15),MONTH(A15)+1,1),交易记录!$B$6:$B$605,"QQQM",交易记录!$C$6:$C$605,"买入") -> 0 | H15: =SUMIFS(交易记录!$D$6:$D$605,交易记录!$A$6:$A$605,">="&DATE(YEAR(A15),MONTH(A15),1),交易记录!$A$6:$A$605,"<"&DATE(YEAR(A15),MONTH(A15)+1,1),交易记录!$B$6:$B$605,"SMH",交易记录!$C$6:$C$605,"买入")+SUMIFS(交易记录!$E$6:$E$605,交易记录!$A$6:$A$605,">="&DATE(YEAR(A15),MONTH(A15),1),交易记录!$A$6:$A$605,"<"&DATE(YEAR(A15),MONTH(A15)+1,1),交易记录!$B$6:$B$605,"SMH",交易记录!$C$6:$C$605,"买入") -> 0 | I15: =SUM(F15:H15) -> 0 | J15: =IF(I15=0,"",I15-B15) | K15: =IF(I15=0,"尚未记录买入",IF(ABS(J15)<0.01,"已记录预算金额","已记录，金额有差额")) -> 尚未记录买入
A16: =DATE(2027,8,总览!$E$4) -> 46609 | B16: =回撤计划!J19 -> 500 | C16: =B16*总览!$B$8 -> 450 | D16: =B16*总览!$B$9 -> 50 | E16: =B16*总览!$B$10 -> 0 | F16: =SUMIFS(交易记录!$D$6:$D$605,交易记录!$A$6:$A$605,">="&DATE(YEAR(A16),MONTH(A16),1),交易记录!$A$6:$A$605,"<"&DATE(YEAR(A16),MONTH(A16)+1,1),交易记录!$B$6:$B$605,"VOO",交易记录!$C$6:$C$605,"买入")+SUMIFS(交易记录!$E$6:$E$605,交易记录!$A$6:$A$605,">="&DATE(YEAR(A16),MONTH(A16),1),交易记录!$A$6:$A$605,"<"&DATE(YEAR(A16),MONTH(A16)+1,1),交易记录!$B$6:$B$605,"VOO",交易记录!$C$6:$C$605,"买入") -> 0 | G16: =SUMIFS(交易记录!$D$6:$D$605,交易记录!$A$6:$A$605,">="&DATE(YEAR(A16),MONTH(A16),1),交易记录!$A$6:$A$605,"<"&DATE(YEAR(A16),MONTH(A16)+1,1),交易记录!$B$6:$B$605,"QQQM",交易记录!$C$6:$C$605,"买入")+SUMIFS(交易记录!$E$6:$E$605,交易记录!$A$6:$A$605,">="&DATE(YEAR(A16),MONTH(A16),1),交易记录!$A$6:$A$605,"<"&DATE(YEAR(A16),MONTH(A16)+1,1),交易记录!$B$6:$B$605,"QQQM",交易记录!$C$6:$C$605,"买入") -> 0 | H16: =SUMIFS(交易记录!$D$6:$D$605,交易记录!$A$6:$A$605,">="&DATE(YEAR(A16),MONTH(A16),1),交易记录!$A$6:$A$605,"<"&DATE(YEAR(A16),MONTH(A16)+1,1),交易记录!$B$6:$B$605,"SMH",交易记录!$C$6:$C$605,"买入")+SUMIFS(交易记录!$E$6:$E$605,交易记录!$A$6:$A$605,">="&DATE(YEAR(A16),MONTH(A16),1),交易记录!$A$6:$A$605,"<"&DATE(YEAR(A16),MONTH(A16)+1,1),交易记录!$B$6:$B$605,"SMH",交易记录!$C$6:$C$605,"买入") -> 0 | I16: =SUM(F16:H16) -> 0 | J16: =IF(I16=0,"",I16-B16) | K16: =IF(I16=0,"尚未记录买入",IF(ABS(J16)<0.01,"已记录预算金额","已记录，金额有差额")) -> 尚未记录买入
A17: =DATE(2027,9,总览!$E$4) -> 46640 | B17: =回撤计划!J20 -> 500 | C17: =B17*总览!$B$8 -> 450 | D17: =B17*总览!$B$9 -> 50 | E17: =B17*总览!$B$10 -> 0 | F17: =SUMIFS(交易记录!$D$6:$D$605,交易记录!$A$6:$A$605,">="&DATE(YEAR(A17),MONTH(A17),1),交易记录!$A$6:$A$605,"<"&DATE(YEAR(A17),MONTH(A17)+1,1),交易记录!$B$6:$B$605,"VOO",交易记录!$C$6:$C$605,"买入")+SUMIFS(交易记录!$E$6:$E$605,交易记录!$A$6:$A$605,">="&DATE(YEAR(A17),MONTH(A17),1),交易记录!$A$6:$A$605,"<"&DATE(YEAR(A17),MONTH(A17)+1,1),交易记录!$B$6:$B$605,"VOO",交易记录!$C$6:$C$605,"买入") -> 0 | G17: =SUMIFS(交易记录!$D$6:$D$605,交易记录!$A$6:$A$605,">="&DATE(YEAR(A17),MONTH(A17),1),交易记录!$A$6:$A$605,"<"&DATE(YEAR(A17),MONTH(A17)+1,1),交易记录!$B$6:$B$605,"QQQM",交易记录!$C$6:$C$605,"买入")+SUMIFS(交易记录!$E$6:$E$605,交易记录!$A$6:$A$605,">="&DATE(YEAR(A17),MONTH(A17),1),交易记录!$A$6:$A$605,"<"&DATE(YEAR(A17),MONTH(A17)+1,1),交易记录!$B$6:$B$605,"QQQM",交易记录!$C$6:$C$605,"买入") -> 0 | H17: =SUMIFS(交易记录!$D$6:$D$605,交易记录!$A$6:$A$605,">="&DATE(YEAR(A17),MONTH(A17),1),交易记录!$A$6:$A$605,"<"&DATE(YEAR(A17),MONTH(A17)+1,1),交易记录!$B$6:$B$605,"SMH",交易记录!$C$6:$C$605,"买入")+SUMIFS(交易记录!$E$6:$E$605,交易记录!$A$6:$A$605,">="&DATE(YEAR(A17),MONTH(A17),1),交易记录!$A$6:$A$605,"<"&DATE(YEAR(A17),MONTH(A17)+1,1),交易记录!$B$6:$B$605,"SMH",交易记录!$C$6:$C$605,"买入") -> 0 | I17: =SUM(F17:H17) -> 0 | J17: =IF(I17=0,"",I17-B17) | K17: =IF(I17=0,"尚未记录买入",IF(ABS(J17)<0.01,"已记录预算金额","已记录，金额有差额")) -> 尚未记录买入
A18: =DATE(2027,10,总览!$E$4) -> 46670 | B18: =回撤计划!J21 -> 500 | C18: =B18*总览!$B$8 -> 450 | D18: =B18*总览!$B$9 -> 50 | E18: =B18*总览!$B$10 -> 0 | F18: =SUMIFS(交易记录!$D$6:$D$605,交易记录!$A$6:$A$605,">="&DATE(YEAR(A18),MONTH(A18),1),交易记录!$A$6:$A$605,"<"&DATE(YEAR(A18),MONTH(A18)+1,1),交易记录!$B$6:$B$605,"VOO",交易记录!$C$6:$C$605,"买入")+SUMIFS(交易记录!$E$6:$E$605,交易记录!$A$6:$A$605,">="&DATE(YEAR(A18),MONTH(A18),1),交易记录!$A$6:$A$605,"<"&DATE(YEAR(A18),MONTH(A18)+1,1),交易记录!$B$6:$B$605,"VOO",交易记录!$C$6:$C$605,"买入") -> 0 | G18: =SUMIFS(交易记录!$D$6:$D$605,交易记录!$A$6:$A$605,">="&DATE(YEAR(A18),MONTH(A18),1),交易记录!$A$6:$A$605,"<"&DATE(YEAR(A18),MONTH(A18)+1,1),交易记录!$B$6:$B$605,"QQQM",交易记录!$C$6:$C$605,"买入")+SUMIFS(交易记录!$E$6:$E$605,交易记录!$A$6:$A$605,">="&DATE(YEAR(A18),MONTH(A18),1),交易记录!$A$6:$A$605,"<"&DATE(YEAR(A18),MONTH(A18)+1,1),交易记录!$B$6:$B$605,"QQQM",交易记录!$C$6:$C$605,"买入") -> 0 | H18: =SUMIFS(交易记录!$D$6:$D$605,交易记录!$A$6:$A$605,">="&DATE(YEAR(A18),MONTH(A18),1),交易记录!$A$6:$A$605,"<"&DATE(YEAR(A18),MONTH(A18)+1,1),交易记录!$B$6:$B$605,"SMH",交易记录!$C$6:$C$605,"买入")+SUMIFS(交易记录!$E$6:$E$605,交易记录!$A$6:$A$605,">="&DATE(YEAR(A18),MONTH(A18),1),交易记录!$A$6:$A$605,"<"&DATE(YEAR(A18),MONTH(A18)+1,1),交易记录!$B$6:$B$605,"SMH",交易记录!$C$6:$C$605,"买入") -> 0 | I18: =SUM(F18:H18) -> 0 | J18: =IF(I18=0,"",I18-B18) | K18: =IF(I18=0,"尚未记录买入",IF(ABS(J18)<0.01,"已记录预算金额","已记录，金额有差额")) -> 尚未记录买入
A19: =DATE(2027,11,总览!$E$4) -> 46701 | B19: =回撤计划!J22 -> 500 | C19: =B19*总览!$B$8 -> 450 | D19: =B19*总览!$B$9 -> 50 | E19: =B19*总览!$B$10 -> 0 | F19: =SUMIFS(交易记录!$D$6:$D$605,交易记录!$A$6:$A$605,">="&DATE(YEAR(A19),MONTH(A19),1),交易记录!$A$6:$A$605,"<"&DATE(YEAR(A19),MONTH(A19)+1,1),交易记录!$B$6:$B$605,"VOO",交易记录!$C$6:$C$605,"买入")+SUMIFS(交易记录!$E$6:$E$605,交易记录!$A$6:$A$605,">="&DATE(YEAR(A19),MONTH(A19),1),交易记录!$A$6:$A$605,"<"&DATE(YEAR(A19),MONTH(A19)+1,1),交易记录!$B$6:$B$605,"VOO",交易记录!$C$6:$C$605,"买入") -> 0 | G19: =SUMIFS(交易记录!$D$6:$D$605,交易记录!$A$6:$A$605,">="&DATE(YEAR(A19),MONTH(A19),1),交易记录!$A$6:$A$605,"<"&DATE(YEAR(A19),MONTH(A19)+1,1),交易记录!$B$6:$B$605,"QQQM",交易记录!$C$6:$C$605,"买入")+SUMIFS(交易记录!$E$6:$E$605,交易记录!$A$6:$A$605,">="&DATE(YEAR(A19),MONTH(A19),1),交易记录!$A$6:$A$605,"<"&DATE(YEAR(A19),MONTH(A19)+1,1),交易记录!$B$6:$B$605,"QQQM",交易记录!$C$6:$C$605,"买入") -> 0 | H19: =SUMIFS(交易记录!$D$6:$D$605,交易记录!$A$6:$A$605,">="&DATE(YEAR(A19),MONTH(A19),1),交易记录!$A$6:$A$605,"<"&DATE(YEAR(A19),MONTH(A19)+1,1),交易记录!$B$6:$B$605,"SMH",交易记录!$C$6:$C$605,"买入")+SUMIFS(交易记录!$E$6:$E$605,交易记录!$A$6:$A$605,">="&DATE(YEAR(A19),MONTH(A19),1),交易记录!$A$6:$A$605,"<"&DATE(YEAR(A19),MONTH(A19)+1,1),交易记录!$B$6:$B$605,"SMH",交易记录!$C$6:$C$605,"买入") -> 0 | I19: =SUM(F19:H19) -> 0 | J19: =IF(I19=0,"",I19-B19) | K19: =IF(I19=0,"尚未记录买入",IF(ABS(J19)<0.01,"已记录预算金额","已记录，金额有差额")) -> 尚未记录买入
A20: =DATE(2027,12,总览!$E$4) -> 46731 | B20: =回撤计划!J23 -> 500 | C20: =B20*总览!$B$8 -> 450 | D20: =B20*总览!$B$9 -> 50 | E20: =B20*总览!$B$10 -> 0 | F20: =SUMIFS(交易记录!$D$6:$D$605,交易记录!$A$6:$A$605,">="&DATE(YEAR(A20),MONTH(A20),1),交易记录!$A$6:$A$605,"<"&DATE(YEAR(A20),MONTH(A20)+1,1),交易记录!$B$6:$B$605,"VOO",交易记录!$C$6:$C$605,"买入")+SUMIFS(交易记录!$E$6:$E$605,交易记录!$A$6:$A$605,">="&DATE(YEAR(A20),MONTH(A20),1),交易记录!$A$6:$A$605,"<"&DATE(YEAR(A20),MONTH(A20)+1,1),交易记录!$B$6:$B$605,"VOO",交易记录!$C$6:$C$605,"买入") -> 0 | G20: =SUMIFS(交易记录!$D$6:$D$605,交易记录!$A$6:$A$605,">="&DATE(YEAR(A20),MONTH(A20),1),交易记录!$A$6:$A$605,"<"&DATE(YEAR(A20),MONTH(A20)+1,1),交易记录!$B$6:$B$605,"QQQM",交易记录!$C$6:$C$605,"买入")+SUMIFS(交易记录!$E$6:$E$605,交易记录!$A$6:$A$605,">="&DATE(YEAR(A20),MONTH(A20),1),交易记录!$A$6:$A$605,"<"&DATE(YEAR(A20),MONTH(A20)+1,1),交易记录!$B$6:$B$605,"QQQM",交易记录!$C$6:$C$605,"买入") -> 0 | H20: =SUMIFS(交易记录!$D$6:$D$605,交易记录!$A$6:$A$605,">="&DATE(YEAR(A20),MONTH(A20),1),交易记录!$A$6:$A$605,"<"&DATE(YEAR(A20),MONTH(A20)+1,1),交易记录!$B$6:$B$605,"SMH",交易记录!$C$6:$C$605,"买入")+SUMIFS(交易记录!$E$6:$E$605,交易记录!$A$6:$A$605,">="&DATE(YEAR(A20),MONTH(A20),1),交易记录!$A$6:$A$605,"<"&DATE(YEAR(A20),MONTH(A20)+1,1),交易记录!$B$6:$B$605,"SMH",交易记录!$C$6:$C$605,"买入") -> 0 | I20: =SUM(F20:H20) -> 0 | J20: =IF(I20=0,"",I20-B20) | K20: =IF(I20=0,"尚未记录买入",IF(ABS(J20)<0.01,"已记录预算金额","已记录，金额有差额")) -> 尚未记录买入
A21: =DATE(2028,1,总览!$E$4) -> 46762 | B21: =回撤计划!J24 -> 500 | C21: =B21*总览!$B$8 -> 450 | D21: =B21*总览!$B$9 -> 50 | E21: =B21*总览!$B$10 -> 0 | F21: =SUMIFS(交易记录!$D$6:$D$605,交易记录!$A$6:$A$605,">="&DATE(YEAR(A21),MONTH(A21),1),交易记录!$A$6:$A$605,"<"&DATE(YEAR(A21),MONTH(A21)+1,1),交易记录!$B$6:$B$605,"VOO",交易记录!$C$6:$C$605,"买入")+SUMIFS(交易记录!$E$6:$E$605,交易记录!$A$6:$A$605,">="&DATE(YEAR(A21),MONTH(A21),1),交易记录!$A$6:$A$605,"<"&DATE(YEAR(A21),MONTH(A21)+1,1),交易记录!$B$6:$B$605,"VOO",交易记录!$C$6:$C$605,"买入") -> 0 | G21: =SUMIFS(交易记录!$D$6:$D$605,交易记录!$A$6:$A$605,">="&DATE(YEAR(A21),MONTH(A21),1),交易记录!$A$6:$A$605,"<"&DATE(YEAR(A21),MONTH(A21)+1,1),交易记录!$B$6:$B$605,"QQQM",交易记录!$C$6:$C$605,"买入")+SUMIFS(交易记录!$E$6:$E$605,交易记录!$A$6:$A$605,">="&DATE(YEAR(A21),MONTH(A21),1),交易记录!$A$6:$A$605,"<"&DATE(YEAR(A21),MONTH(A21)+1,1),交易记录!$B$6:$B$605,"QQQM",交易记录!$C$6:$C$605,"买入") -> 0 | H21: =SUMIFS(交易记录!$D$6:$D$605,交易记录!$A$6:$A$605,">="&DATE(YEAR(A21),MONTH(A21),1),交易记录!$A$6:$A$605,"<"&DATE(YEAR(A21),MONTH(A21)+1,1),交易记录!$B$6:$B$605,"SMH",交易记录!$C$6:$C$605,"买入")+SUMIFS(交易记录!$E$6:$E$605,交易记录!$A$6:$A$605,">="&DATE(YEAR(A21),MONTH(A21),1),交易记录!$A$6:$A$605,"<"&DATE(YEAR(A21),MONTH(A21)+1,1),交易记录!$B$6:$B$605,"SMH",交易记录!$C$6:$C$605,"买入") -> 0 | I21: =SUM(F21:H21) -> 0 | J21: =IF(I21=0,"",I21-B21) | K21: =IF(I21=0,"尚未记录买入",IF(ABS(J21)<0.01,"已记录预算金额","已记录，金额有差额")) -> 尚未记录买入
A22: =DATE(2028,2,总览!$E$4) -> 46793 | B22: =回撤计划!J25 -> 500 | C22: =B22*总览!$B$8 -> 450 | D22: =B22*总览!$B$9 -> 50 | E22: =B22*总览!$B$10 -> 0 | F22: =SUMIFS(交易记录!$D$6:$D$605,交易记录!$A$6:$A$605,">="&DATE(YEAR(A22),MONTH(A22),1),交易记录!$A$6:$A$605,"<"&DATE(YEAR(A22),MONTH(A22)+1,1),交易记录!$B$6:$B$605,"VOO",交易记录!$C$6:$C$605,"买入")+SUMIFS(交易记录!$E$6:$E$605,交易记录!$A$6:$A$605,">="&DATE(YEAR(A22),MONTH(A22),1),交易记录!$A$6:$A$605,"<"&DATE(YEAR(A22),MONTH(A22)+1,1),交易记录!$B$6:$B$605,"VOO",交易记录!$C$6:$C$605,"买入") -> 0 | G22: =SUMIFS(交易记录!$D$6:$D$605,交易记录!$A$6:$A$605,">="&DATE(YEAR(A22),MONTH(A22),1),交易记录!$A$6:$A$605,"<"&DATE(YEAR(A22),MONTH(A22)+1,1),交易记录!$B$6:$B$605,"QQQM",交易记录!$C$6:$C$605,"买入")+SUMIFS(交易记录!$E$6:$E$605,交易记录!$A$6:$A$605,">="&DATE(YEAR(A22),MONTH(A22),1),交易记录!$A$6:$A$605,"<"&DATE(YEAR(A22),MONTH(A22)+1,1),交易记录!$B$6:$B$605,"QQQM",交易记录!$C$6:$C$605,"买入") -> 0 | H22: =SUMIFS(交易记录!$D$6:$D$605,交易记录!$A$6:$A$605,">="&DATE(YEAR(A22),MONTH(A22),1),交易记录!$A$6:$A$605,"<"&DATE(YEAR(A22),MONTH(A22)+1,1),交易记录!$B$6:$B$605,"SMH",交易记录!$C$6:$C$605,"买入")+SUMIFS(交易记录!$E$6:$E$605,交易记录!$A$6:$A$605,">="&DATE(YEAR(A22),MONTH(A22),1),交易记录!$A$6:$A$605,"<"&DATE(YEAR(A22),MONTH(A22)+1,1),交易记录!$B$6:$B$605,"SMH",交易记录!$C$6:$C$605,"买入") -> 0 | I22: =SUM(F22:H22) -> 0 | J22: =IF(I22=0,"",I22-B22) | K22: =IF(I22=0,"尚未记录买入",IF(ABS(J22)<0.01,"已记录预算金额","已记录，金额有差额")) -> 尚未记录买入
A23: =DATE(2028,3,总览!$E$4) -> 46822 | B23: =回撤计划!J26 -> 500 | C23: =B23*总览!$B$8 -> 450 | D23: =B23*总览!$B$9 -> 50 | E23: =B23*总览!$B$10 -> 0 | F23: =SUMIFS(交易记录!$D$6:$D$605,交易记录!$A$6:$A$605,">="&DATE(YEAR(A23),MONTH(A23),1),交易记录!$A$6:$A$605,"<"&DATE(YEAR(A23),MONTH(A23)+1,1),交易记录!$B$6:$B$605,"VOO",交易记录!$C$6:$C$605,"买入")+SUMIFS(交易记录!$E$6:$E$605,交易记录!$A$6:$A$605,">="&DATE(YEAR(A23),MONTH(A23),1),交易记录!$A$6:$A$605,"<"&DATE(YEAR(A23),MONTH(A23)+1,1),交易记录!$B$6:$B$605,"VOO",交易记录!$C$6:$C$605,"买入") -> 0 | G23: =SUMIFS(交易记录!$D$6:$D$605,交易记录!$A$6:$A$605,">="&DATE(YEAR(A23),MONTH(A23),1),交易记录!$A$6:$A$605,"<"&DATE(YEAR(A23),MONTH(A23)+1,1),交易记录!$B$6:$B$605,"QQQM",交易记录!$C$6:$C$605,"买入")+SUMIFS(交易记录!$E$6:$E$605,交易记录!$A$6:$A$605,">="&DATE(YEAR(A23),MONTH(A23),1),交易记录!$A$6:$A$605,"<"&DATE(YEAR(A23),MONTH(A23)+1,1),交易记录!$B$6:$B$605,"QQQM",交易记录!$C$6:$C$605,"买入") -> 0 | H23: =SUMIFS(交易记录!$D$6:$D$605,交易记录!$A$6:$A$605,">="&DATE(YEAR(A23),MONTH(A23),1),交易记录!$A$6:$A$605,"<"&DATE(YEAR(A23),MONTH(A23)+1,1),交易记录!$B$6:$B$605,"SMH",交易记录!$C$6:$C$605,"买入")+SUMIFS(交易记录!$E$6:$E$605,交易记录!$A$6:$A$605,">="&DATE(YEAR(A23),MONTH(A23),1),交易记录!$A$6:$A$605,"<"&DATE(YEAR(A23),MONTH(A23)+1,1),交易记录!$B$6:$B$605,"SMH",交易记录!$C$6:$C$605,"买入") -> 0 | I23: =SUM(F23:H23) -> 0 | J23: =IF(I23=0,"",I23-B23) | K23: =IF(I23=0,"尚未记录买入",IF(ABS(J23)<0.01,"已记录预算金额","已记录，金额有差额")) -> 尚未记录买入
A24: =DATE(2028,4,总览!$E$4) -> 46853 | B24: =回撤计划!J27 -> 500 | C24: =B24*总览!$B$8 -> 450 | D24: =B24*总览!$B$9 -> 50 | E24: =B24*总览!$B$10 -> 0 | F24: =SUMIFS(交易记录!$D$6:$D$605,交易记录!$A$6:$A$605,">="&DATE(YEAR(A24),MONTH(A24),1),交易记录!$A$6:$A$605,"<"&DATE(YEAR(A24),MONTH(A24)+1,1),交易记录!$B$6:$B$605,"VOO",交易记录!$C$6:$C$605,"买入")+SUMIFS(交易记录!$E$6:$E$605,交易记录!$A$6:$A$605,">="&DATE(YEAR(A24),MONTH(A24),1),交易记录!$A$6:$A$605,"<"&DATE(YEAR(A24),MONTH(A24)+1,1),交易记录!$B$6:$B$605,"VOO",交易记录!$C$6:$C$605,"买入") -> 0 | G24: =SUMIFS(交易记录!$D$6:$D$605,交易记录!$A$6:$A$605,">="&DATE(YEAR(A24),MONTH(A24),1),交易记录!$A$6:$A$605,"<"&DATE(YEAR(A24),MONTH(A24)+1,1),交易记录!$B$6:$B$605,"QQQM",交易记录!$C$6:$C$605,"买入")+SUMIFS(交易记录!$E$6:$E$605,交易记录!$A$6:$A$605,">="&DATE(YEAR(A24),MONTH(A24),1),交易记录!$A$6:$A$605,"<"&DATE(YEAR(A24),MONTH(A24)+1,1),交易记录!$B$6:$B$605,"QQQM",交易记录!$C$6:$C$605,"买入") -> 0 | H24: =SUMIFS(交易记录!$D$6:$D$605,交易记录!$A$6:$A$605,">="&DATE(YEAR(A24),MONTH(A24),1),交易记录!$A$6:$A$605,"<"&DATE(YEAR(A24),MONTH(A24)+1,1),交易记录!$B$6:$B$605,"SMH",交易记录!$C$6:$C$605,"买入")+SUMIFS(交易记录!$E$6:$E$605,交易记录!$A$6:$A$605,">="&DATE(YEAR(A24),MONTH(A24),1),交易记录!$A$6:$A$605,"<"&DATE(YEAR(A24),MONTH(A24)+1,1),交易记录!$B$6:$B$605,"SMH",交易记录!$C$6:$C$605,"买入") -> 0 | I24: =SUM(F24:H24) -> 0 | J24: =IF(I24=0,"",I24-B24) | K24: =IF(I24=0,"尚未记录买入",IF(ABS(J24)<0.01,"已记录预算金额","已记录，金额有差额")) -> 尚未记录买入
A25: =DATE(2028,5,总览!$E$4) -> 46883 | B25: =回撤计划!J28 -> 500 | C25: =B25*总览!$B$8 -> 450 | D25: =B25*总览!$B$9 -> 50 | E25: =B25*总览!$B$10 -> 0 | F25: =SUMIFS(交易记录!$D$6:$D$605,交易记录!$A$6:$A$605,">="&DATE(YEAR(A25),MONTH(A25),1),交易记录!$A$6:$A$605,"<"&DATE(YEAR(A25),MONTH(A25)+1,1),交易记录!$B$6:$B$605,"VOO",交易记录!$C$6:$C$605,"买入")+SUMIFS(交易记录!$E$6:$E$605,交易记录!$A$6:$A$605,">="&DATE(YEAR(A25),MONTH(A25),1),交易记录!$A$6:$A$605,"<"&DATE(YEAR(A25),MONTH(A25)+1,1),交易记录!$B$6:$B$605,"VOO",交易记录!$C$6:$C$605,"买入") -> 0 | G25: =SUMIFS(交易记录!$D$6:$D$605,交易记录!$A$6:$A$605,">="&DATE(YEAR(A25),MONTH(A25),1),交易记录!$A$6:$A$605,"<"&DATE(YEAR(A25),MONTH(A25)+1,1),交易记录!$B$6:$B$605,"QQQM",交易记录!$C$6:$C$605,"买入")+SUMIFS(交易记录!$E$6:$E$605,交易记录!$A$6:$A$605,">="&DATE(YEAR(A25),MONTH(A25),1),交易记录!$A$6:$A$605,"<"&DATE(YEAR(A25),MONTH(A25)+1,1),交易记录!$B$6:$B$605,"QQQM",交易记录!$C$6:$C$605,"买入") -> 0 | H25: =SUMIFS(交易记录!$D$6:$D$605,交易记录!$A$6:$A$605,">="&DATE(YEAR(A25),MONTH(A25),1),交易记录!$A$6:$A$605,"<"&DATE(YEAR(A25),MONTH(A25)+1,1),交易记录!$B$6:$B$605,"SMH",交易记录!$C$6:$C$605,"买入")+SUMIFS(交易记录!$E$6:$E$605,交易记录!$A$6:$A$605,">="&DATE(YEAR(A25),MONTH(A25),1),交易记录!$A$6:$A$605,"<"&DATE(YEAR(A25),MONTH(A25)+1,1),交易记录!$B$6:$B$605,"SMH",交易记录!$C$6:$C$605,"买入") -> 0 | I25: =SUM(F25:H25) -> 0 | J25: =IF(I25=0,"",I25-B25) | K25: =IF(I25=0,"尚未记录买入",IF(ABS(J25)<0.01,"已记录预算金额","已记录，金额有差额")) -> 尚未记录买入
A26: =DATE(2028,6,总览!$E$4) -> 46914 | B26: =回撤计划!J29 -> 500 | C26: =B26*总览!$B$8 -> 450 | D26: =B26*总览!$B$9 -> 50 | E26: =B26*总览!$B$10 -> 0 | F26: =SUMIFS(交易记录!$D$6:$D$605,交易记录!$A$6:$A$605,">="&DATE(YEAR(A26),MONTH(A26),1),交易记录!$A$6:$A$605,"<"&DATE(YEAR(A26),MONTH(A26)+1,1),交易记录!$B$6:$B$605,"VOO",交易记录!$C$6:$C$605,"买入")+SUMIFS(交易记录!$E$6:$E$605,交易记录!$A$6:$A$605,">="&DATE(YEAR(A26),MONTH(A26),1),交易记录!$A$6:$A$605,"<"&DATE(YEAR(A26),MONTH(A26)+1,1),交易记录!$B$6:$B$605,"VOO",交易记录!$C$6:$C$605,"买入") -> 0 | G26: =SUMIFS(交易记录!$D$6:$D$605,交易记录!$A$6:$A$605,">="&DATE(YEAR(A26),MONTH(A26),1),交易记录!$A$6:$A$605,"<"&DATE(YEAR(A26),MONTH(A26)+1,1),交易记录!$B$6:$B$605,"QQQM",交易记录!$C$6:$C$605,"买入")+SUMIFS(交易记录!$E$6:$E$605,交易记录!$A$6:$A$605,">="&DATE(YEAR(A26),MONTH(A26),1),交易记录!$A$6:$A$605,"<"&DATE(YEAR(A26),MONTH(A26)+1,1),交易记录!$B$6:$B$605,"QQQM",交易记录!$C$6:$C$605,"买入") -> 0 | H26: =SUMIFS(交易记录!$D$6:$D$605,交易记录!$A$6:$A$605,">="&DATE(YEAR(A26),MONTH(A26),1),交易记录!$A$6:$A$605,"<"&DATE(YEAR(A26),MONTH(A26)+1,1),交易记录!$B$6:$B$605,"SMH",交易记录!$C$6:$C$605,"买入")+SUMIFS(交易记录!$E$6:$E$605,交易记录!$A$6:$A$605,">="&DATE(YEAR(A26),MONTH(A26),1),交易记录!$A$6:$A$605,"<"&DATE(YEAR(A26),MONTH(A26)+1,1),交易记录!$B$6:$B$605,"SMH",交易记录!$C$6:$C$605,"买入") -> 0 | I26: =SUM(F26:H26) -> 0 | J26: =IF(I26=0,"",I26-B26) | K26: =IF(I26=0,"尚未记录买入",IF(ABS(J26)<0.01,"已记录预算金额","已记录，金额有差额")) -> 尚未记录买入
A27: =DATE(2028,7,总览!$E$4) -> 46944 | B27: =回撤计划!J30 -> 500 | C27: =B27*总览!$B$8 -> 450 | D27: =B27*总览!$B$9 -> 50 | E27: =B27*总览!$B$10 -> 0 | F27: =SUMIFS(交易记录!$D$6:$D$605,交易记录!$A$6:$A$605,">="&DATE(YEAR(A27),MONTH(A27),1),交易记录!$A$6:$A$605,"<"&DATE(YEAR(A27),MONTH(A27)+1,1),交易记录!$B$6:$B$605,"VOO",交易记录!$C$6:$C$605,"买入")+SUMIFS(交易记录!$E$6:$E$605,交易记录!$A$6:$A$605,">="&DATE(YEAR(A27),MONTH(A27),1),交易记录!$A$6:$A$605,"<"&DATE(YEAR(A27),MONTH(A27)+1,1),交易记录!$B$6:$B$605,"VOO",交易记录!$C$6:$C$605,"买入") -> 0 | G27: =SUMIFS(交易记录!$D$6:$D$605,交易记录!$A$6:$A$605,">="&DATE(YEAR(A27),MONTH(A27),1),交易记录!$A$6:$A$605,"<"&DATE(YEAR(A27),MONTH(A27)+1,1),交易记录!$B$6:$B$605,"QQQM",交易记录!$C$6:$C$605,"买入")+SUMIFS(交易记录!$E$6:$E$605,交易记录!$A$6:$A$605,">="&DATE(YEAR(A27),MONTH(A27),1),交易记录!$A$6:$A$605,"<"&DATE(YEAR(A27),MONTH(A27)+1,1),交易记录!$B$6:$B$605,"QQQM",交易记录!$C$6:$C$605,"买入") -> 0 | H27: =SUMIFS(交易记录!$D$6:$D$605,交易记录!$A$6:$A$605,">="&DATE(YEAR(A27),MONTH(A27),1),交易记录!$A$6:$A$605,"<"&DATE(YEAR(A27),MONTH(A27)+1,1),交易记录!$B$6:$B$605,"SMH",交易记录!$C$6:$C$605,"买入")+SUMIFS(交易记录!$E$6:$E$605,交易记录!$A$6:$A$605,">="&DATE(YEAR(A27),MONTH(A27),1),交易记录!$A$6:$A$605,"<"&DATE(YEAR(A27),MONTH(A27)+1,1),交易记录!$B$6:$B$605,"SMH",交易记录!$C$6:$C$605,"买入") -> 0 | I27: =SUM(F27:H27) -> 0 | J27: =IF(I27=0,"",I27-B27) | K27: =IF(I27=0,"尚未记录买入",IF(ABS(J27)<0.01,"已记录预算金额","已记录，金额有差额")) -> 尚未记录买入
A28: =DATE(2028,8,总览!$E$4) -> 46975 | B28: =回撤计划!J31 -> 500 | C28: =B28*总览!$B$8 -> 450 | D28: =B28*总览!$B$9 -> 50 | E28: =B28*总览!$B$10 -> 0 | F28: =SUMIFS(交易记录!$D$6:$D$605,交易记录!$A$6:$A$605,">="&DATE(YEAR(A28),MONTH(A28),1),交易记录!$A$6:$A$605,"<"&DATE(YEAR(A28),MONTH(A28)+1,1),交易记录!$B$6:$B$605,"VOO",交易记录!$C$6:$C$605,"买入")+SUMIFS(交易记录!$E$6:$E$605,交易记录!$A$6:$A$605,">="&DATE(YEAR(A28),MONTH(A28),1),交易记录!$A$6:$A$605,"<"&DATE(YEAR(A28),MONTH(A28)+1,1),交易记录!$B$6:$B$605,"VOO",交易记录!$C$6:$C$605,"买入") -> 0 | G28: =SUMIFS(交易记录!$D$6:$D$605,交易记录!$A$6:$A$605,">="&DATE(YEAR(A28),MONTH(A28),1),交易记录!$A$6:$A$605,"<"&DATE(YEAR(A28),MONTH(A28)+1,1),交易记录!$B$6:$B$605,"QQQM",交易记录!$C$6:$C$605,"买入")+SUMIFS(交易记录!$E$6:$E$605,交易记录!$A$6:$A$605,">="&DATE(YEAR(A28),MONTH(A28),1),交易记录!$A$6:$A$605,"<"&DATE(YEAR(A28),MONTH(A28)+1,1),交易记录!$B$6:$B$605,"QQQM",交易记录!$C$6:$C$605,"买入") -> 0 | H28: =SUMIFS(交易记录!$D$6:$D$605,交易记录!$A$6:$A$605,">="&DATE(YEAR(A28),MONTH(A28),1),交易记录!$A$6:$A$605,"<"&DATE(YEAR(A28),MONTH(A28)+1,1),交易记录!$B$6:$B$605,"SMH",交易记录!$C$6:$C$605,"买入")+SUMIFS(交易记录!$E$6:$E$605,交易记录!$A$6:$A$605,">="&DATE(YEAR(A28),MONTH(A28),1),交易记录!$A$6:$A$605,"<"&DATE(YEAR(A28),MONTH(A28)+1,1),交易记录!$B$6:$B$605,"SMH",交易记录!$C$6:$C$605,"买入") -> 0 | I28: =SUM(F28:H28) -> 0 | J28: =IF(I28=0,"",I28-B28) | K28: =IF(I28=0,"尚未记录买入",IF(ABS(J28)<0.01,"已记录预算金额","已记录，金额有差额")) -> 尚未记录买入
A29: =DATE(2028,9,总览!$E$4) -> 47006 | B29: =回撤计划!J32 -> 500 | C29: =B29*总览!$B$8 -> 450 | D29: =B29*总览!$B$9 -> 50 | E29: =B29*总览!$B$10 -> 0 | F29: =SUMIFS(交易记录!$D$6:$D$605,交易记录!$A$6:$A$605,">="&DATE(YEAR(A29),MONTH(A29),1),交易记录!$A$6:$A$605,"<"&DATE(YEAR(A29),MONTH(A29)+1,1),交易记录!$B$6:$B$605,"VOO",交易记录!$C$6:$C$605,"买入")+SUMIFS(交易记录!$E$6:$E$605,交易记录!$A$6:$A$605,">="&DATE(YEAR(A29),MONTH(A29),1),交易记录!$A$6:$A$605,"<"&DATE(YEAR(A29),MONTH(A29)+1,1),交易记录!$B$6:$B$605,"VOO",交易记录!$C$6:$C$605,"买入") -> 0 | G29: =SUMIFS(交易记录!$D$6:$D$605,交易记录!$A$6:$A$605,">="&DATE(YEAR(A29),MONTH(A29),1),交易记录!$A$6:$A$605,"<"&DATE(YEAR(A29),MONTH(A29)+1,1),交易记录!$B$6:$B$605,"QQQM",交易记录!$C$6:$C$605,"买入")+SUMIFS(交易记录!$E$6:$E$605,交易记录!$A$6:$A$605,">="&DATE(YEAR(A29),MONTH(A29),1),交易记录!$A$6:$A$605,"<"&DATE(YEAR(A29),MONTH(A29)+1,1),交易记录!$B$6:$B$605,"QQQM",交易记录!$C$6:$C$605,"买入") -> 0 | H29: =SUMIFS(交易记录!$D$6:$D$605,交易记录!$A$6:$A$605,">="&DATE(YEAR(A29),MONTH(A29),1),交易记录!$A$6:$A$605,"<"&DATE(YEAR(A29),MONTH(A29)+1,1),交易记录!$B$6:$B$605,"SMH",交易记录!$C$6:$C$605,"买入")+SUMIFS(交易记录!$E$6:$E$605,交易记录!$A$6:$A$605,">="&DATE(YEAR(A29),MONTH(A29),1),交易记录!$A$6:$A$605,"<"&DATE(YEAR(A29),MONTH(A29)+1,1),交易记录!$B$6:$B$605,"SMH",交易记录!$C$6:$C$605,"买入") -> 0 | I29: =SUM(F29:H29) -> 0 | J29: =IF(I29=0,"",I29-B29) | K29: =IF(I29=0,"尚未记录买入",IF(ABS(J29)<0.01,"已记录预算金额","已记录，金额有差额")) -> 尚未记录买入
A30: =DATE(2028,10,总览!$E$4) -> 47036 | B30: =回撤计划!J33 -> 500 | C30: =B30*总览!$B$8 -> 450 | D30: =B30*总览!$B$9 -> 50 | E30: =B30*总览!$B$10 -> 0 | F30: =SUMIFS(交易记录!$D$6:$D$605,交易记录!$A$6:$A$605,">="&DATE(YEAR(A30),MONTH(A30),1),交易记录!$A$6:$A$605,"<"&DATE(YEAR(A30),MONTH(A30)+1,1),交易记录!$B$6:$B$605,"VOO",交易记录!$C$6:$C$605,"买入")+SUMIFS(交易记录!$E$6:$E$605,交易记录!$A$6:$A$605,">="&DATE(YEAR(A30),MONTH(A30),1),交易记录!$A$6:$A$605,"<"&DATE(YEAR(A30),MONTH(A30)+1,1),交易记录!$B$6:$B$605,"VOO",交易记录!$C$6:$C$605,"买入") -> 0 | G30: =SUMIFS(交易记录!$D$6:$D$605,交易记录!$A$6:$A$605,">="&DATE(YEAR(A30),MONTH(A30),1),交易记录!$A$6:$A$605,"<"&DATE(YEAR(A30),MONTH(A30)+1,1),交易记录!$B$6:$B$605,"QQQM",交易记录!$C$6:$C$605,"买入")+SUMIFS(交易记录!$E$6:$E$605,交易记录!$A$6:$A$605,">="&DATE(YEAR(A30),MONTH(A30),1),交易记录!$A$6:$A$605,"<"&DATE(YEAR(A30),MONTH(A30)+1,1),交易记录!$B$6:$B$605,"QQQM",交易记录!$C$6:$C$605,"买入") -> 0 | H30: =SUMIFS(交易记录!$D$6:$D$605,交易记录!$A$6:$A$605,">="&DATE(YEAR(A30),MONTH(A30),1),交易记录!$A$6:$A$605,"<"&DATE(YEAR(A30),MONTH(A30)+1,1),交易记录!$B$6:$B$605,"SMH",交易记录!$C$6:$C$605,"买入")+SUMIFS(交易记录!$E$6:$E$605,交易记录!$A$6:$A$605,">="&DATE(YEAR(A30),MONTH(A30),1),交易记录!$A$6:$A$605,"<"&DATE(YEAR(A30),MONTH(A30)+1,1),交易记录!$B$6:$B$605,"SMH",交易记录!$C$6:$C$605,"买入") -> 0 | I30: =SUM(F30:H30) -> 0 | J30: =IF(I30=0,"",I30-B30) | K30: =IF(I30=0,"尚未记录买入",IF(ABS(J30)<0.01,"已记录预算金额","已记录，金额有差额")) -> 尚未记录买入
A31: =DATE(2028,11,总览!$E$4) -> 47067 | B31: =回撤计划!J34 -> 500 | C31: =B31*总览!$B$8 -> 450 | D31: =B31*总览!$B$9 -> 50 | E31: =B31*总览!$B$10 -> 0 | F31: =SUMIFS(交易记录!$D$6:$D$605,交易记录!$A$6:$A$605,">="&DATE(YEAR(A31),MONTH(A31),1),交易记录!$A$6:$A$605,"<"&DATE(YEAR(A31),MONTH(A31)+1,1),交易记录!$B$6:$B$605,"VOO",交易记录!$C$6:$C$605,"买入")+SUMIFS(交易记录!$E$6:$E$605,交易记录!$A$6:$A$605,">="&DATE(YEAR(A31),MONTH(A31),1),交易记录!$A$6:$A$605,"<"&DATE(YEAR(A31),MONTH(A31)+1,1),交易记录!$B$6:$B$605,"VOO",交易记录!$C$6:$C$605,"买入") -> 0 | G31: =SUMIFS(交易记录!$D$6:$D$605,交易记录!$A$6:$A$605,">="&DATE(YEAR(A31),MONTH(A31),1),交易记录!$A$6:$A$605,"<"&DATE(YEAR(A31),MONTH(A31)+1,1),交易记录!$B$6:$B$605,"QQQM",交易记录!$C$6:$C$605,"买入")+SUMIFS(交易记录!$E$6:$E$605,交易记录!$A$6:$A$605,">="&DATE(YEAR(A31),MONTH(A31),1),交易记录!$A$6:$A$605,"<"&DATE(YEAR(A31),MONTH(A31)+1,1),交易记录!$B$6:$B$605,"QQQM",交易记录!$C$6:$C$605,"买入") -> 0 | H31: =SUMIFS(交易记录!$D$6:$D$605,交易记录!$A$6:$A$605,">="&DATE(YEAR(A31),MONTH(A31),1),交易记录!$A$6:$A$605,"<"&DATE(YEAR(A31),MONTH(A31)+1,1),交易记录!$B$6:$B$605,"SMH",交易记录!$C$6:$C$605,"买入")+SUMIFS(交易记录!$E$6:$E$605,交易记录!$A$6:$A$605,">="&DATE(YEAR(A31),MONTH(A31),1),交易记录!$A$6:$A$605,"<"&DATE(YEAR(A31),MONTH(A31)+1,1),交易记录!$B$6:$B$605,"SMH",交易记录!$C$6:$C$605,"买入") -> 0 | I31: =SUM(F31:H31) -> 0 | J31: =IF(I31=0,"",I31-B31) | K31: =IF(I31=0,"尚未记录买入",IF(ABS(J31)<0.01,"已记录预算金额","已记录，金额有差额")) -> 尚未记录买入
A32: =DATE(2028,12,总览!$E$4) -> 47097 | B32: =回撤计划!J35 -> 500 | C32: =B32*总览!$B$8 -> 450 | D32: =B32*总览!$B$9 -> 50 | E32: =B32*总览!$B$10 -> 0 | F32: =SUMIFS(交易记录!$D$6:$D$605,交易记录!$A$6:$A$605,">="&DATE(YEAR(A32),MONTH(A32),1),交易记录!$A$6:$A$605,"<"&DATE(YEAR(A32),MONTH(A32)+1,1),交易记录!$B$6:$B$605,"VOO",交易记录!$C$6:$C$605,"买入")+SUMIFS(交易记录!$E$6:$E$605,交易记录!$A$6:$A$605,">="&DATE(YEAR(A32),MONTH(A32),1),交易记录!$A$6:$A$605,"<"&DATE(YEAR(A32),MONTH(A32)+1,1),交易记录!$B$6:$B$605,"VOO",交易记录!$C$6:$C$605,"买入") -> 0 | G32: =SUMIFS(交易记录!$D$6:$D$605,交易记录!$A$6:$A$605,">="&DATE(YEAR(A32),MONTH(A32),1),交易记录!$A$6:$A$605,"<"&DATE(YEAR(A32),MONTH(A32)+1,1),交易记录!$B$6:$B$605,"QQQM",交易记录!$C$6:$C$605,"买入")+SUMIFS(交易记录!$E$6:$E$605,交易记录!$A$6:$A$605,">="&DATE(YEAR(A32),MONTH(A32),1),交易记录!$A$6:$A$605,"<"&DATE(YEAR(A32),MONTH(A32)+1,1),交易记录!$B$6:$B$605,"QQQM",交易记录!$C$6:$C$605,"买入") -> 0 | H32: =SUMIFS(交易记录!$D$6:$D$605,交易记录!$A$6:$A$605,">="&DATE(YEAR(A32),MONTH(A32),1),交易记录!$A$6:$A$605,"<"&DATE(YEAR(A32),MONTH(A32)+1,1),交易记录!$B$6:$B$605,"SMH",交易记录!$C$6:$C$605,"买入")+SUMIFS(交易记录!$E$6:$E$605,交易记录!$A$6:$A$605,">="&DATE(YEAR(A32),MONTH(A32),1),交易记录!$A$6:$A$605,"<"&DATE(YEAR(A32),MONTH(A32)+1,1),交易记录!$B$6:$B$605,"SMH",交易记录!$C$6:$C$605,"买入") -> 0 | I32: =SUM(F32:H32) -> 0 | J32: =IF(I32=0,"",I32-B32) | K32: =IF(I32=0,"尚未记录买入",IF(ABS(J32)<0.01,"已记录预算金额","已记录，金额有差额")) -> 尚未记录买入
A33: =DATE(2029,1,总览!$E$4) -> 47128 | B33: =回撤计划!J36 -> 500 | C33: =B33*总览!$B$8 -> 450 | D33: =B33*总览!$B$9 -> 50 | E33: =B33*总览!$B$10 -> 0 | F33: =SUMIFS(交易记录!$D$6:$D$605,交易记录!$A$6:$A$605,">="&DATE(YEAR(A33),MONTH(A33),1),交易记录!$A$6:$A$605,"<"&DATE(YEAR(A33),MONTH(A33)+1,1),交易记录!$B$6:$B$605,"VOO",交易记录!$C$6:$C$605,"买入")+SUMIFS(交易记录!$E$6:$E$605,交易记录!$A$6:$A$605,">="&DATE(YEAR(A33),MONTH(A33),1),交易记录!$A$6:$A$605,"<"&DATE(YEAR(A33),MONTH(A33)+1,1),交易记录!$B$6:$B$605,"VOO",交易记录!$C$6:$C$605,"买入") -> 0 | G33: =SUMIFS(交易记录!$D$6:$D$605,交易记录!$A$6:$A$605,">="&DATE(YEAR(A33),MONTH(A33),1),交易记录!$A$6:$A$605,"<"&DATE(YEAR(A33),MONTH(A33)+1,1),交易记录!$B$6:$B$605,"QQQM",交易记录!$C$6:$C$605,"买入")+SUMIFS(交易记录!$E$6:$E$605,交易记录!$A$6:$A$605,">="&DATE(YEAR(A33),MONTH(A33),1),交易记录!$A$6:$A$605,"<"&DATE(YEAR(A33),MONTH(A33)+1,1),交易记录!$B$6:$B$605,"QQQM",交易记录!$C$6:$C$605,"买入") -> 0 | H33: =SUMIFS(交易记录!$D$6:$D$605,交易记录!$A$6:$A$605,">="&DATE(YEAR(A33),MONTH(A33),1),交易记录!$A$6:$A$605,"<"&DATE(YEAR(A33),MONTH(A33)+1,1),交易记录!$B$6:$B$605,"SMH",交易记录!$C$6:$C$605,"买入")+SUMIFS(交易记录!$E$6:$E$605,交易记录!$A$6:$A$605,">="&DATE(YEAR(A33),MONTH(A33),1),交易记录!$A$6:$A$605,"<"&DATE(YEAR(A33),MONTH(A33)+1,1),交易记录!$B$6:$B$605,"SMH",交易记录!$C$6:$C$605,"买入") -> 0 | I33: =SUM(F33:H33) -> 0 | J33: =IF(I33=0,"",I33-B33) | K33: =IF(I33=0,"尚未记录买入",IF(ABS(J33)<0.01,"已记录预算金额","已记录，金额有差额")) -> 尚未记录买入
A34: =DATE(2029,2,总览!$E$4) -> 47159 | B34: =回撤计划!J37 -> 500 | C34: =B34*总览!$B$8 -> 450 | D34: =B34*总览!$B$9 -> 50 | E34: =B34*总览!$B$10 -> 0 | F34: =SUMIFS(交易记录!$D$6:$D$605,交易记录!$A$6:$A$605,">="&DATE(YEAR(A34),MONTH(A34),1),交易记录!$A$6:$A$605,"<"&DATE(YEAR(A34),MONTH(A34)+1,1),交易记录!$B$6:$B$605,"VOO",交易记录!$C$6:$C$605,"买入")+SUMIFS(交易记录!$E$6:$E$605,交易记录!$A$6:$A$605,">="&DATE(YEAR(A34),MONTH(A34),1),交易记录!$A$6:$A$605,"<"&DATE(YEAR(A34),MONTH(A34)+1,1),交易记录!$B$6:$B$605,"VOO",交易记录!$C$6:$C$605,"买入") -> 0 | G34: =SUMIFS(交易记录!$D$6:$D$605,交易记录!$A$6:$A$605,">="&DATE(YEAR(A34),MONTH(A34),1),交易记录!$A$6:$A$605,"<"&DATE(YEAR(A34),MONTH(A34)+1,1),交易记录!$B$6:$B$605,"QQQM",交易记录!$C$6:$C$605,"买入")+SUMIFS(交易记录!$E$6:$E$605,交易记录!$A$6:$A$605,">="&DATE(YEAR(A34),MONTH(A34),1),交易记录!$A$6:$A$605,"<"&DATE(YEAR(A34),MONTH(A34)+1,1),交易记录!$B$6:$B$605,"QQQM",交易记录!$C$6:$C$605,"买入") -> 0 | H34: =SUMIFS(交易记录!$D$6:$D$605,交易记录!$A$6:$A$605,">="&DATE(YEAR(A34),MONTH(A34),1),交易记录!$A$6:$A$605,"<"&DATE(YEAR(A34),MONTH(A34)+1,1),交易记录!$B$6:$B$605,"SMH",交易记录!$C$6:$C$605,"买入")+SUMIFS(交易记录!$E$6:$E$605,交易记录!$A$6:$A$605,">="&DATE(YEAR(A34),MONTH(A34),1),交易记录!$A$6:$A$605,"<"&DATE(YEAR(A34),MONTH(A34)+1,1),交易记录!$B$6:$B$605,"SMH",交易记录!$C$6:$C$605,"买入") -> 0 | I34: =SUM(F34:H34) -> 0 | J34: =IF(I34=0,"",I34-B34) | K34: =IF(I34=0,"尚未记录买入",IF(ABS(J34)<0.01,"已记录预算金额","已记录，金额有差额")) -> 尚未记录买入
A35: =DATE(2029,3,总览!$E$4) -> 47187 | B35: =回撤计划!J38 -> 500 | C35: =B35*总览!$B$8 -> 450 | D35: =B35*总览!$B$9 -> 50 | E35: =B35*总览!$B$10 -> 0 | F35: =SUMIFS(交易记录!$D$6:$D$605,交易记录!$A$6:$A$605,">="&DATE(YEAR(A35),MONTH(A35),1),交易记录!$A$6:$A$605,"<"&DATE(YEAR(A35),MONTH(A35)+1,1),交易记录!$B$6:$B$605,"VOO",交易记录!$C$6:$C$605,"买入")+SUMIFS(交易记录!$E$6:$E$605,交易记录!$A$6:$A$605,">="&DATE(YEAR(A35),MONTH(A35),1),交易记录!$A$6:$A$605,"<"&DATE(YEAR(A35),MONTH(A35)+1,1),交易记录!$B$6:$B$605,"VOO",交易记录!$C$6:$C$605,"买入") -> 0 | G35: =SUMIFS(交易记录!$D$6:$D$605,交易记录!$A$6:$A$605,">="&DATE(YEAR(A35),MONTH(A35),1),交易记录!$A$6:$A$605,"<"&DATE(YEAR(A35),MONTH(A35)+1,1),交易记录!$B$6:$B$605,"QQQM",交易记录!$C$6:$C$605,"买入")+SUMIFS(交易记录!$E$6:$E$605,交易记录!$A$6:$A$605,">="&DATE(YEAR(A35),MONTH(A35),1),交易记录!$A$6:$A$605,"<"&DATE(YEAR(A35),MONTH(A35)+1,1),交易记录!$B$6:$B$605,"QQQM",交易记录!$C$6:$C$605,"买入") -> 0 | H35: =SUMIFS(交易记录!$D$6:$D$605,交易记录!$A$6:$A$605,">="&DATE(YEAR(A35),MONTH(A35),1),交易记录!$A$6:$A$605,"<"&DATE(YEAR(A35),MONTH(A35)+1,1),交易记录!$B$6:$B$605,"SMH",交易记录!$C$6:$C$605,"买入")+SUMIFS(交易记录!$E$6:$E$605,交易记录!$A$6:$A$605,">="&DATE(YEAR(A35),MONTH(A35),1),交易记录!$A$6:$A$605,"<"&DATE(YEAR(A35),MONTH(A35)+1,1),交易记录!$B$6:$B$605,"SMH",交易记录!$C$6:$C$605,"买入") -> 0 | I35: =SUM(F35:H35) -> 0 | J35: =IF(I35=0,"",I35-B35) | K35: =IF(I35=0,"尚未记录买入",IF(ABS(J35)<0.01,"已记录预算金额","已记录，金额有差额")) -> 尚未记录买入
A36: =DATE(2029,4,总览!$E$4) -> 47218 | B36: =回撤计划!J39 -> 500 | C36: =B36*总览!$B$8 -> 450 | D36: =B36*总览!$B$9 -> 50 | E36: =B36*总览!$B$10 -> 0 | F36: =SUMIFS(交易记录!$D$6:$D$605,交易记录!$A$6:$A$605,">="&DATE(YEAR(A36),MONTH(A36),1),交易记录!$A$6:$A$605,"<"&DATE(YEAR(A36),MONTH(A36)+1,1),交易记录!$B$6:$B$605,"VOO",交易记录!$C$6:$C$605,"买入")+SUMIFS(交易记录!$E$6:$E$605,交易记录!$A$6:$A$605,">="&DATE(YEAR(A36),MONTH(A36),1),交易记录!$A$6:$A$605,"<"&DATE(YEAR(A36),MONTH(A36)+1,1),交易记录!$B$6:$B$605,"VOO",交易记录!$C$6:$C$605,"买入") -> 0 | G36: =SUMIFS(交易记录!$D$6:$D$605,交易记录!$A$6:$A$605,">="&DATE(YEAR(A36),MONTH(A36),1),交易记录!$A$6:$A$605,"<"&DATE(YEAR(A36),MONTH(A36)+1,1),交易记录!$B$6:$B$605,"QQQM",交易记录!$C$6:$C$605,"买入")+SUMIFS(交易记录!$E$6:$E$605,交易记录!$A$6:$A$605,">="&DATE(YEAR(A36),MONTH(A36),1),交易记录!$A$6:$A$605,"<"&DATE(YEAR(A36),MONTH(A36)+1,1),交易记录!$B$6:$B$605,"QQQM",交易记录!$C$6:$C$605,"买入") -> 0 | H36: =SUMIFS(交易记录!$D$6:$D$605,交易记录!$A$6:$A$605,">="&DATE(YEAR(A36),MONTH(A36),1),交易记录!$A$6:$A$605,"<"&DATE(YEAR(A36),MONTH(A36)+1,1),交易记录!$B$6:$B$605,"SMH",交易记录!$C$6:$C$605,"买入")+SUMIFS(交易记录!$E$6:$E$605,交易记录!$A$6:$A$605,">="&DATE(YEAR(A36),MONTH(A36),1),交易记录!$A$6:$A$605,"<"&DATE(YEAR(A36),MONTH(A36)+1,1),交易记录!$B$6:$B$605,"SMH",交易记录!$C$6:$C$605,"买入") -> 0 | I36: =SUM(F36:H36) -> 0 | J36: =IF(I36=0,"",I36-B36) | K36: =IF(I36=0,"尚未记录买入",IF(ABS(J36)<0.01,"已记录预算金额","已记录，金额有差额")) -> 尚未记录买入
A37: =DATE(2029,5,总览!$E$4) -> 47248 | B37: =回撤计划!J40 -> 500 | C37: =B37*总览!$B$8 -> 450 | D37: =B37*总览!$B$9 -> 50 | E37: =B37*总览!$B$10 -> 0 | F37: =SUMIFS(交易记录!$D$6:$D$605,交易记录!$A$6:$A$605,">="&DATE(YEAR(A37),MONTH(A37),1),交易记录!$A$6:$A$605,"<"&DATE(YEAR(A37),MONTH(A37)+1,1),交易记录!$B$6:$B$605,"VOO",交易记录!$C$6:$C$605,"买入")+SUMIFS(交易记录!$E$6:$E$605,交易记录!$A$6:$A$605,">="&DATE(YEAR(A37),MONTH(A37),1),交易记录!$A$6:$A$605,"<"&DATE(YEAR(A37),MONTH(A37)+1,1),交易记录!$B$6:$B$605,"VOO",交易记录!$C$6:$C$605,"买入") -> 0 | G37: =SUMIFS(交易记录!$D$6:$D$605,交易记录!$A$6:$A$605,">="&DATE(YEAR(A37),MONTH(A37),1),交易记录!$A$6:$A$605,"<"&DATE(YEAR(A37),MONTH(A37)+1,1),交易记录!$B$6:$B$605,"QQQM",交易记录!$C$6:$C$605,"买入")+SUMIFS(交易记录!$E$6:$E$605,交易记录!$A$6:$A$605,">="&DATE(YEAR(A37),MONTH(A37),1),交易记录!$A$6:$A$605,"<"&DATE(YEAR(A37),MONTH(A37)+1,1),交易记录!$B$6:$B$605,"QQQM",交易记录!$C$6:$C$605,"买入") -> 0 | H37: =SUMIFS(交易记录!$D$6:$D$605,交易记录!$A$6:$A$605,">="&DATE(YEAR(A37),MONTH(A37),1),交易记录!$A$6:$A$605,"<"&DATE(YEAR(A37),MONTH(A37)+1,1),交易记录!$B$6:$B$605,"SMH",交易记录!$C$6:$C$605,"买入")+SUMIFS(交易记录!$E$6:$E$605,交易记录!$A$6:$A$605,">="&DATE(YEAR(A37),MONTH(A37),1),交易记录!$A$6:$A$605,"<"&DATE(YEAR(A37),MONTH(A37)+1,1),交易记录!$B$6:$B$605,"SMH",交易记录!$C$6:$C$605,"买入") -> 0 | I37: =SUM(F37:H37) -> 0 | J37: =IF(I37=0,"",I37-B37) | K37: =IF(I37=0,"尚未记录买入",IF(ABS(J37)<0.01,"已记录预算金额","已记录，金额有差额")) -> 尚未记录买入
A38: =DATE(2029,6,总览!$E$4) -> 47279 | B38: =回撤计划!J41 -> 500 | C38: =B38*总览!$B$8 -> 450 | D38: =B38*总览!$B$9 -> 50 | E38: =B38*总览!$B$10 -> 0 | F38: =SUMIFS(交易记录!$D$6:$D$605,交易记录!$A$6:$A$605,">="&DATE(YEAR(A38),MONTH(A38),1),交易记录!$A$6:$A$605,"<"&DATE(YEAR(A38),MONTH(A38)+1,1),交易记录!$B$6:$B$605,"VOO",交易记录!$C$6:$C$605,"买入")+SUMIFS(交易记录!$E$6:$E$605,交易记录!$A$6:$A$605,">="&DATE(YEAR(A38),MONTH(A38),1),交易记录!$A$6:$A$605,"<"&DATE(YEAR(A38),MONTH(A38)+1,1),交易记录!$B$6:$B$605,"VOO",交易记录!$C$6:$C$605,"买入") -> 0 | G38: =SUMIFS(交易记录!$D$6:$D$605,交易记录!$A$6:$A$605,">="&DATE(YEAR(A38),MONTH(A38),1),交易记录!$A$6:$A$605,"<"&DATE(YEAR(A38),MONTH(A38)+1,1),交易记录!$B$6:$B$605,"QQQM",交易记录!$C$6:$C$605,"买入")+SUMIFS(交易记录!$E$6:$E$605,交易记录!$A$6:$A$605,">="&DATE(YEAR(A38),MONTH(A38),1),交易记录!$A$6:$A$605,"<"&DATE(YEAR(A38),MONTH(A38)+1,1),交易记录!$B$6:$B$605,"QQQM",交易记录!$C$6:$C$605,"买入") -> 0 | H38: =SUMIFS(交易记录!$D$6:$D$605,交易记录!$A$6:$A$605,">="&DATE(YEAR(A38),MONTH(A38),1),交易记录!$A$6:$A$605,"<"&DATE(YEAR(A38),MONTH(A38)+1,1),交易记录!$B$6:$B$605,"SMH",交易记录!$C$6:$C$605,"买入")+SUMIFS(交易记录!$E$6:$E$605,交易记录!$A$6:$A$605,">="&DATE(YEAR(A38),MONTH(A38),1),交易记录!$A$6:$A$605,"<"&DATE(YEAR(A38),MONTH(A38)+1,1),交易记录!$B$6:$B$605,"SMH",交易记录!$C$6:$C$605,"买入") -> 0 | I38: =SUM(F38:H38) -> 0 | J38: =IF(I38=0,"",I38-B38) | K38: =IF(I38=0,"尚未记录买入",IF(ABS(J38)<0.01,"已记录预算金额","已记录，金额有差额")) -> 尚未记录买入
A39: =DATE(2029,7,总览!$E$4) -> 47309 | B39: =回撤计划!J42 -> 500 | C39: =B39*总览!$B$8 -> 450 | D39: =B39*总览!$B$9 -> 50 | E39: =B39*总览!$B$10 -> 0 | F39: =SUMIFS(交易记录!$D$6:$D$605,交易记录!$A$6:$A$605,">="&DATE(YEAR(A39),MONTH(A39),1),交易记录!$A$6:$A$605,"<"&DATE(YEAR(A39),MONTH(A39)+1,1),交易记录!$B$6:$B$605,"VOO",交易记录!$C$6:$C$605,"买入")+SUMIFS(交易记录!$E$6:$E$605,交易记录!$A$6:$A$605,">="&DATE(YEAR(A39),MONTH(A39),1),交易记录!$A$6:$A$605,"<"&DATE(YEAR(A39),MONTH(A39)+1,1),交易记录!$B$6:$B$605,"VOO",交易记录!$C$6:$C$605,"买入") -> 0 | G39: =SUMIFS(交易记录!$D$6:$D$605,交易记录!$A$6:$A$605,">="&DATE(YEAR(A39),MONTH(A39),1),交易记录!$A$6:$A$605,"<"&DATE(YEAR(A39),MONTH(A39)+1,1),交易记录!$B$6:$B$605,"QQQM",交易记录!$C$6:$C$605,"买入")+SUMIFS(交易记录!$E$6:$E$605,交易记录!$A$6:$A$605,">="&DATE(YEAR(A39),MONTH(A39),1),交易记录!$A$6:$A$605,"<"&DATE(YEAR(A39),MONTH(A39)+1,1),交易记录!$B$6:$B$605,"QQQM",交易记录!$C$6:$C$605,"买入") -> 0 | H39: =SUMIFS(交易记录!$D$6:$D$605,交易记录!$A$6:$A$605,">="&DATE(YEAR(A39),MONTH(A39),1),交易记录!$A$6:$A$605,"<"&DATE(YEAR(A39),MONTH(A39)+1,1),交易记录!$B$6:$B$605,"SMH",交易记录!$C$6:$C$605,"买入")+SUMIFS(交易记录!$E$6:$E$605,交易记录!$A$6:$A$605,">="&DATE(YEAR(A39),MONTH(A39),1),交易记录!$A$6:$A$605,"<"&DATE(YEAR(A39),MONTH(A39)+1,1),交易记录!$B$6:$B$605,"SMH",交易记录!$C$6:$C$605,"买入") -> 0 | I39: =SUM(F39:H39) -> 0 | J39: =IF(I39=0,"",I39-B39) | K39: =IF(I39=0,"尚未记录买入",IF(ABS(J39)<0.01,"已记录预算金额","已记录，金额有差额")) -> 尚未记录买入
A40: =DATE(2029,8,总览!$E$4) -> 47340 | B40: =回撤计划!J43 -> 500 | C40: =B40*总览!$B$8 -> 450 | D40: =B40*总览!$B$9 -> 50 | E40: =B40*总览!$B$10 -> 0 | F40: =SUMIFS(交易记录!$D$6:$D$605,交易记录!$A$6:$A$605,">="&DATE(YEAR(A40),MONTH(A40),1),交易记录!$A$6:$A$605,"<"&DATE(YEAR(A40),MONTH(A40)+1,1),交易记录!$B$6:$B$605,"VOO",交易记录!$C$6:$C$605,"买入")+SUMIFS(交易记录!$E$6:$E$605,交易记录!$A$6:$A$605,">="&DATE(YEAR(A40),MONTH(A40),1),交易记录!$A$6:$A$605,"<"&DATE(YEAR(A40),MONTH(A40)+1,1),交易记录!$B$6:$B$605,"VOO",交易记录!$C$6:$C$605,"买入") -> 0 | G40: =SUMIFS(交易记录!$D$6:$D$605,交易记录!$A$6:$A$605,">="&DATE(YEAR(A40),MONTH(A40),1),交易记录!$A$6:$A$605,"<"&DATE(YEAR(A40),MONTH(A40)+1,1),交易记录!$B$6:$B$605,"QQQM",交易记录!$C$6:$C$605,"买入")+SUMIFS(交易记录!$E$6:$E$605,交易记录!$A$6:$A$605,">="&DATE(YEAR(A40),MONTH(A40),1),交易记录!$A$6:$A$605,"<"&DATE(YEAR(A40),MONTH(A40)+1,1),交易记录!$B$6:$B$605,"QQQM",交易记录!$C$6:$C$605,"买入") -> 0 | H40: =SUMIFS(交易记录!$D$6:$D$605,交易记录!$A$6:$A$605,">="&DATE(YEAR(A40),MONTH(A40),1),交易记录!$A$6:$A$605,"<"&DATE(YEAR(A40),MONTH(A40)+1,1),交易记录!$B$6:$B$605,"SMH",交易记录!$C$6:$C$605,"买入")+SUMIFS(交易记录!$E$6:$E$605,交易记录!$A$6:$A$605,">="&DATE(YEAR(A40),MONTH(A40),1),交易记录!$A$6:$A$605,"<"&DATE(YEAR(A40),MONTH(A40)+1,1),交易记录!$B$6:$B$605,"SMH",交易记录!$C$6:$C$605,"买入") -> 0 | I40: =SUM(F40:H40) -> 0 | J40: =IF(I40=0,"",I40-B40) | K40: =IF(I40=0,"尚未记录买入",IF(ABS(J40)<0.01,"已记录预算金额","已记录，金额有差额")) -> 尚未记录买入
A41: =DATE(2029,9,总览!$E$4) -> 47371 | B41: =回撤计划!J44 -> 500 | C41: =B41*总览!$B$8 -> 450 | D41: =B41*总览!$B$9 -> 50 | E41: =B41*总览!$B$10 -> 0 | F41: =SUMIFS(交易记录!$D$6:$D$605,交易记录!$A$6:$A$605,">="&DATE(YEAR(A41),MONTH(A41),1),交易记录!$A$6:$A$605,"<"&DATE(YEAR(A41),MONTH(A41)+1,1),交易记录!$B$6:$B$605,"VOO",交易记录!$C$6:$C$605,"买入")+SUMIFS(交易记录!$E$6:$E$605,交易记录!$A$6:$A$605,">="&DATE(YEAR(A41),MONTH(A41),1),交易记录!$A$6:$A$605,"<"&DATE(YEAR(A41),MONTH(A41)+1,1),交易记录!$B$6:$B$605,"VOO",交易记录!$C$6:$C$605,"买入") -> 0 | G41: =SUMIFS(交易记录!$D$6:$D$605,交易记录!$A$6:$A$605,">="&DATE(YEAR(A41),MONTH(A41),1),交易记录!$A$6:$A$605,"<"&DATE(YEAR(A41),MONTH(A41)+1,1),交易记录!$B$6:$B$605,"QQQM",交易记录!$C$6:$C$605,"买入")+SUMIFS(交易记录!$E$6:$E$605,交易记录!$A$6:$A$605,">="&DATE(YEAR(A41),MONTH(A41),1),交易记录!$A$6:$A$605,"<"&DATE(YEAR(A41),MONTH(A41)+1,1),交易记录!$B$6:$B$605,"QQQM",交易记录!$C$6:$C$605,"买入") -> 0 | H41: =SUMIFS(交易记录!$D$6:$D$605,交易记录!$A$6:$A$605,">="&DATE(YEAR(A41),MONTH(A41),1),交易记录!$A$6:$A$605,"<"&DATE(YEAR(A41),MONTH(A41)+1,1),交易记录!$B$6:$B$605,"SMH",交易记录!$C$6:$C$605,"买入")+SUMIFS(交易记录!$E$6:$E$605,交易记录!$A$6:$A$605,">="&DATE(YEAR(A41),MONTH(A41),1),交易记录!$A$6:$A$605,"<"&DATE(YEAR(A41),MONTH(A41)+1,1),交易记录!$B$6:$B$605,"SMH",交易记录!$C$6:$C$605,"买入") -> 0 | I41: =SUM(F41:H41) -> 0 | J41: =IF(I41=0,"",I41-B41) | K41: =IF(I41=0,"尚未记录买入",IF(ABS(J41)<0.01,"已记录预算金额","已记录，金额有差额")) -> 尚未记录买入
A42: =DATE(2029,10,总览!$E$4) -> 47401 | B42: =回撤计划!J45 -> 500 | C42: =B42*总览!$B$8 -> 450 | D42: =B42*总览!$B$9 -> 50 | E42: =B42*总览!$B$10 -> 0 | F42: =SUMIFS(交易记录!$D$6:$D$605,交易记录!$A$6:$A$605,">="&DATE(YEAR(A42),MONTH(A42),1),交易记录!$A$6:$A$605,"<"&DATE(YEAR(A42),MONTH(A42)+1,1),交易记录!$B$6:$B$605,"VOO",交易记录!$C$6:$C$605,"买入")+SUMIFS(交易记录!$E$6:$E$605,交易记录!$A$6:$A$605,">="&DATE(YEAR(A42),MONTH(A42),1),交易记录!$A$6:$A$605,"<"&DATE(YEAR(A42),MONTH(A42)+1,1),交易记录!$B$6:$B$605,"VOO",交易记录!$C$6:$C$605,"买入") -> 0 | G42: =SUMIFS(交易记录!$D$6:$D$605,交易记录!$A$6:$A$605,">="&DATE(YEAR(A42),MONTH(A42),1),交易记录!$A$6:$A$605,"<"&DATE(YEAR(A42),MONTH(A42)+1,1),交易记录!$B$6:$B$605,"QQQM",交易记录!$C$6:$C$605,"买入")+SUMIFS(交易记录!$E$6:$E$605,交易记录!$A$6:$A$605,">="&DATE(YEAR(A42),MONTH(A42),1),交易记录!$A$6:$A$605,"<"&DATE(YEAR(A42),MONTH(A42)+1,1),交易记录!$B$6:$B$605,"QQQM",交易记录!$C$6:$C$605,"买入") -> 0 | H42: =SUMIFS(交易记录!$D$6:$D$605,交易记录!$A$6:$A$605,">="&DATE(YEAR(A42),MONTH(A42),1),交易记录!$A$6:$A$605,"<"&DATE(YEAR(A42),MONTH(A42)+1,1),交易记录!$B$6:$B$605,"SMH",交易记录!$C$6:$C$605,"买入")+SUMIFS(交易记录!$E$6:$E$605,交易记录!$A$6:$A$605,">="&DATE(YEAR(A42),MONTH(A42),1),交易记录!$A$6:$A$605,"<"&DATE(YEAR(A42),MONTH(A42)+1,1),交易记录!$B$6:$B$605,"SMH",交易记录!$C$6:$C$605,"买入") -> 0 | I42: =SUM(F42:H42) -> 0 | J42: =IF(I42=0,"",I42-B42) | K42: =IF(I42=0,"尚未记录买入",IF(ABS(J42)<0.01,"已记录预算金额","已记录，金额有差额")) -> 尚未记录买入
A43: =DATE(2029,11,总览!$E$4) -> 47432 | B43: =回撤计划!J46 -> 500 | C43: =B43*总览!$B$8 -> 450 | D43: =B43*总览!$B$9 -> 50 | E43: =B43*总览!$B$10 -> 0 | F43: =SUMIFS(交易记录!$D$6:$D$605,交易记录!$A$6:$A$605,">="&DATE(YEAR(A43),MONTH(A43),1),交易记录!$A$6:$A$605,"<"&DATE(YEAR(A43),MONTH(A43)+1,1),交易记录!$B$6:$B$605,"VOO",交易记录!$C$6:$C$605,"买入")+SUMIFS(交易记录!$E$6:$E$605,交易记录!$A$6:$A$605,">="&DATE(YEAR(A43),MONTH(A43),1),交易记录!$A$6:$A$605,"<"&DATE(YEAR(A43),MONTH(A43)+1,1),交易记录!$B$6:$B$605,"VOO",交易记录!$C$6:$C$605,"买入") -> 0 | G43: =SUMIFS(交易记录!$D$6:$D$605,交易记录!$A$6:$A$605,">="&DATE(YEAR(A43),MONTH(A43),1),交易记录!$A$6:$A$605,"<"&DATE(YEAR(A43),MONTH(A43)+1,1),交易记录!$B$6:$B$605,"QQQM",交易记录!$C$6:$C$605,"买入")+SUMIFS(交易记录!$E$6:$E$605,交易记录!$A$6:$A$605,">="&DATE(YEAR(A43),MONTH(A43),1),交易记录!$A$6:$A$605,"<"&DATE(YEAR(A43),MONTH(A43)+1,1),交易记录!$B$6:$B$605,"QQQM",交易记录!$C$6:$C$605,"买入") -> 0 | H43: =SUMIFS(交易记录!$D$6:$D$605,交易记录!$A$6:$A$605,">="&DATE(YEAR(A43),MONTH(A43),1),交易记录!$A$6:$A$605,"<"&DATE(YEAR(A43),MONTH(A43)+1,1),交易记录!$B$6:$B$605,"SMH",交易记录!$C$6:$C$605,"买入")+SUMIFS(交易记录!$E$6:$E$605,交易记录!$A$6:$A$605,">="&DATE(YEAR(A43),MONTH(A43),1),交易记录!$A$6:$A$605,"<"&DATE(YEAR(A43),MONTH(A43)+1,1),交易记录!$B$6:$B$605,"SMH",交易记录!$C$6:$C$605,"买入") -> 0 | I43: =SUM(F43:H43) -> 0 | J43: =IF(I43=0,"",I43-B43) | K43: =IF(I43=0,"尚未记录买入",IF(ABS(J43)<0.01,"已记录预算金额","已记录，金额有差额")) -> 尚未记录买入
A44: =DATE(2029,12,总览!$E$4) -> 47462 | B44: =回撤计划!J47 -> 500 | C44: =B44*总览!$B$8 -> 450 | D44: =B44*总览!$B$9 -> 50 | E44: =B44*总览!$B$10 -> 0 | F44: =SUMIFS(交易记录!$D$6:$D$605,交易记录!$A$6:$A$605,">="&DATE(YEAR(A44),MONTH(A44),1),交易记录!$A$6:$A$605,"<"&DATE(YEAR(A44),MONTH(A44)+1,1),交易记录!$B$6:$B$605,"VOO",交易记录!$C$6:$C$605,"买入")+SUMIFS(交易记录!$E$6:$E$605,交易记录!$A$6:$A$605,">="&DATE(YEAR(A44),MONTH(A44),1),交易记录!$A$6:$A$605,"<"&DATE(YEAR(A44),MONTH(A44)+1,1),交易记录!$B$6:$B$605,"VOO",交易记录!$C$6:$C$605,"买入") -> 0 | G44: =SUMIFS(交易记录!$D$6:$D$605,交易记录!$A$6:$A$605,">="&DATE(YEAR(A44),MONTH(A44),1),交易记录!$A$6:$A$605,"<"&DATE(YEAR(A44),MONTH(A44)+1,1),交易记录!$B$6:$B$605,"QQQM",交易记录!$C$6:$C$605,"买入")+SUMIFS(交易记录!$E$6:$E$605,交易记录!$A$6:$A$605,">="&DATE(YEAR(A44),MONTH(A44),1),交易记录!$A$6:$A$605,"<"&DATE(YEAR(A44),MONTH(A44)+1,1),交易记录!$B$6:$B$605,"QQQM",交易记录!$C$6:$C$605,"买入") -> 0 | H44: =SUMIFS(交易记录!$D$6:$D$605,交易记录!$A$6:$A$605,">="&DATE(YEAR(A44),MONTH(A44),1),交易记录!$A$6:$A$605,"<"&DATE(YEAR(A44),MONTH(A44)+1,1),交易记录!$B$6:$B$605,"SMH",交易记录!$C$6:$C$605,"买入")+SUMIFS(交易记录!$E$6:$E$605,交易记录!$A$6:$A$605,">="&DATE(YEAR(A44),MONTH(A44),1),交易记录!$A$6:$A$605,"<"&DATE(YEAR(A44),MONTH(A44)+1,1),交易记录!$B$6:$B$605,"SMH",交易记录!$C$6:$C$605,"买入") -> 0 | I44: =SUM(F44:H44) -> 0 | J44: =IF(I44=0,"",I44-B44) | K44: =IF(I44=0,"尚未记录买入",IF(ABS(J44)<0.01,"已记录预算金额","已记录，金额有差额")) -> 尚未记录买入
A45: =DATE(2030,1,总览!$E$4) -> 47493 | B45: =回撤计划!J48 -> 500 | C45: =B45*总览!$B$8 -> 450 | D45: =B45*总览!$B$9 -> 50 | E45: =B45*总览!$B$10 -> 0 | F45: =SUMIFS(交易记录!$D$6:$D$605,交易记录!$A$6:$A$605,">="&DATE(YEAR(A45),MONTH(A45),1),交易记录!$A$6:$A$605,"<"&DATE(YEAR(A45),MONTH(A45)+1,1),交易记录!$B$6:$B$605,"VOO",交易记录!$C$6:$C$605,"买入")+SUMIFS(交易记录!$E$6:$E$605,交易记录!$A$6:$A$605,">="&DATE(YEAR(A45),MONTH(A45),1),交易记录!$A$6:$A$605,"<"&DATE(YEAR(A45),MONTH(A45)+1,1),交易记录!$B$6:$B$605,"VOO",交易记录!$C$6:$C$605,"买入") -> 0 | G45: =SUMIFS(交易记录!$D$6:$D$605,交易记录!$A$6:$A$605,">="&DATE(YEAR(A45),MONTH(A45),1),交易记录!$A$6:$A$605,"<"&DATE(YEAR(A45),MONTH(A45)+1,1),交易记录!$B$6:$B$605,"QQQM",交易记录!$C$6:$C$605,"买入")+SUMIFS(交易记录!$E$6:$E$605,交易记录!$A$6:$A$605,">="&DATE(YEAR(A45),MONTH(A45),1),交易记录!$A$6:$A$605,"<"&DATE(YEAR(A45),MONTH(A45)+1,1),交易记录!$B$6:$B$605,"QQQM",交易记录!$C$6:$C$605,"买入") -> 0 | H45: =SUMIFS(交易记录!$D$6:$D$605,交易记录!$A$6:$A$605,">="&DATE(YEAR(A45),MONTH(A45),1),交易记录!$A$6:$A$605,"<"&DATE(YEAR(A45),MONTH(A45)+1,1),交易记录!$B$6:$B$605,"SMH",交易记录!$C$6:$C$605,"买入")+SUMIFS(交易记录!$E$6:$E$605,交易记录!$A$6:$A$605,">="&DATE(YEAR(A45),MONTH(A45),1),交易记录!$A$6:$A$605,"<"&DATE(YEAR(A45),MONTH(A45)+1,1),交易记录!$B$6:$B$605,"SMH",交易记录!$C$6:$C$605,"买入") -> 0 | I45: =SUM(F45:H45) -> 0 | J45: =IF(I45=0,"",I45-B45) | K45: =IF(I45=0,"尚未记录买入",IF(ABS(J45)<0.01,"已记录预算金额","已记录，金额有差额")) -> 尚未记录买入
A46: =DATE(2030,2,总览!$E$4) -> 47524 | B46: =回撤计划!J49 -> 500 | C46: =B46*总览!$B$8 -> 450 | D46: =B46*总览!$B$9 -> 50 | E46: =B46*总览!$B$10 -> 0 | F46: =SUMIFS(交易记录!$D$6:$D$605,交易记录!$A$6:$A$605,">="&DATE(YEAR(A46),MONTH(A46),1),交易记录!$A$6:$A$605,"<"&DATE(YEAR(A46),MONTH(A46)+1,1),交易记录!$B$6:$B$605,"VOO",交易记录!$C$6:$C$605,"买入")+SUMIFS(交易记录!$E$6:$E$605,交易记录!$A$6:$A$605,">="&DATE(YEAR(A46),MONTH(A46),1),交易记录!$A$6:$A$605,"<"&DATE(YEAR(A46),MONTH(A46)+1,1),交易记录!$B$6:$B$605,"VOO",交易记录!$C$6:$C$605,"买入") -> 0 | G46: =SUMIFS(交易记录!$D$6:$D$605,交易记录!$A$6:$A$605,">="&DATE(YEAR(A46),MONTH(A46),1),交易记录!$A$6:$A$605,"<"&DATE(YEAR(A46),MONTH(A46)+1,1),交易记录!$B$6:$B$605,"QQQM",交易记录!$C$6:$C$605,"买入")+SUMIFS(交易记录!$E$6:$E$605,交易记录!$A$6:$A$605,">="&DATE(YEAR(A46),MONTH(A46),1),交易记录!$A$6:$A$605,"<"&DATE(YEAR(A46),MONTH(A46)+1,1),交易记录!$B$6:$B$605,"QQQM",交易记录!$C$6:$C$605,"买入") -> 0 | H46: =SUMIFS(交易记录!$D$6:$D$605,交易记录!$A$6:$A$605,">="&DATE(YEAR(A46),MONTH(A46),1),交易记录!$A$6:$A$605,"<"&DATE(YEAR(A46),MONTH(A46)+1,1),交易记录!$B$6:$B$605,"SMH",交易记录!$C$6:$C$605,"买入")+SUMIFS(交易记录!$E$6:$E$605,交易记录!$A$6:$A$605,">="&DATE(YEAR(A46),MONTH(A46),1),交易记录!$A$6:$A$605,"<"&DATE(YEAR(A46),MONTH(A46)+1,1),交易记录!$B$6:$B$605,"SMH",交易记录!$C$6:$C$605,"买入") -> 0 | I46: =SUM(F46:H46) -> 0 | J46: =IF(I46=0,"",I46-B46) | K46: =IF(I46=0,"尚未记录买入",IF(ABS(J46)<0.01,"已记录预算金额","已记录，金额有差额")) -> 尚未记录买入
A47: =DATE(2030,3,总览!$E$4) -> 47552 | B47: =回撤计划!J50 -> 500 | C47: =B47*总览!$B$8 -> 450 | D47: =B47*总览!$B$9 -> 50 | E47: =B47*总览!$B$10 -> 0 | F47: =SUMIFS(交易记录!$D$6:$D$605,交易记录!$A$6:$A$605,">="&DATE(YEAR(A47),MONTH(A47),1),交易记录!$A$6:$A$605,"<"&DATE(YEAR(A47),MONTH(A47)+1,1),交易记录!$B$6:$B$605,"VOO",交易记录!$C$6:$C$605,"买入")+SUMIFS(交易记录!$E$6:$E$605,交易记录!$A$6:$A$605,">="&DATE(YEAR(A47),MONTH(A47),1),交易记录!$A$6:$A$605,"<"&DATE(YEAR(A47),MONTH(A47)+1,1),交易记录!$B$6:$B$605,"VOO",交易记录!$C$6:$C$605,"买入") -> 0 | G47: =SUMIFS(交易记录!$D$6:$D$605,交易记录!$A$6:$A$605,">="&DATE(YEAR(A47),MONTH(A47),1),交易记录!$A$6:$A$605,"<"&DATE(YEAR(A47),MONTH(A47)+1,1),交易记录!$B$6:$B$605,"QQQM",交易记录!$C$6:$C$605,"买入")+SUMIFS(交易记录!$E$6:$E$605,交易记录!$A$6:$A$605,">="&DATE(YEAR(A47),MONTH(A47),1),交易记录!$A$6:$A$605,"<"&DATE(YEAR(A47),MONTH(A47)+1,1),交易记录!$B$6:$B$605,"QQQM",交易记录!$C$6:$C$605,"买入") -> 0 | H47: =SUMIFS(交易记录!$D$6:$D$605,交易记录!$A$6:$A$605,">="&DATE(YEAR(A47),MONTH(A47),1),交易记录!$A$6:$A$605,"<"&DATE(YEAR(A47),MONTH(A47)+1,1),交易记录!$B$6:$B$605,"SMH",交易记录!$C$6:$C$605,"买入")+SUMIFS(交易记录!$E$6:$E$605,交易记录!$A$6:$A$605,">="&DATE(YEAR(A47),MONTH(A47),1),交易记录!$A$6:$A$605,"<"&DATE(YEAR(A47),MONTH(A47)+1,1),交易记录!$B$6:$B$605,"SMH",交易记录!$C$6:$C$605,"买入") -> 0 | I47: =SUM(F47:H47) -> 0 | J47: =IF(I47=0,"",I47-B47) | K47: =IF(I47=0,"尚未记录买入",IF(ABS(J47)<0.01,"已记录预算金额","已记录，金额有差额")) -> 尚未记录买入
A48: =DATE(2030,4,总览!$E$4) -> 47583 | B48: =回撤计划!J51 -> 500 | C48: =B48*总览!$B$8 -> 450 | D48: =B48*总览!$B$9 -> 50 | E48: =B48*总览!$B$10 -> 0 | F48: =SUMIFS(交易记录!$D$6:$D$605,交易记录!$A$6:$A$605,">="&DATE(YEAR(A48),MONTH(A48),1),交易记录!$A$6:$A$605,"<"&DATE(YEAR(A48),MONTH(A48)+1,1),交易记录!$B$6:$B$605,"VOO",交易记录!$C$6:$C$605,"买入")+SUMIFS(交易记录!$E$6:$E$605,交易记录!$A$6:$A$605,">="&DATE(YEAR(A48),MONTH(A48),1),交易记录!$A$6:$A$605,"<"&DATE(YEAR(A48),MONTH(A48)+1,1),交易记录!$B$6:$B$605,"VOO",交易记录!$C$6:$C$605,"买入") -> 0 | G48: =SUMIFS(交易记录!$D$6:$D$605,交易记录!$A$6:$A$605,">="&DATE(YEAR(A48),MONTH(A48),1),交易记录!$A$6:$A$605,"<"&DATE(YEAR(A48),MONTH(A48)+1,1),交易记录!$B$6:$B$605,"QQQM",交易记录!$C$6:$C$605,"买入")+SUMIFS(交易记录!$E$6:$E$605,交易记录!$A$6:$A$605,">="&DATE(YEAR(A48),MONTH(A48),1),交易记录!$A$6:$A$605,"<"&DATE(YEAR(A48),MONTH(A48)+1,1),交易记录!$B$6:$B$605,"QQQM",交易记录!$C$6:$C$605,"买入") -> 0 | H48: =SUMIFS(交易记录!$D$6:$D$605,交易记录!$A$6:$A$605,">="&DATE(YEAR(A48),MONTH(A48),1),交易记录!$A$6:$A$605,"<"&DATE(YEAR(A48),MONTH(A48)+1,1),交易记录!$B$6:$B$605,"SMH",交易记录!$C$6:$C$605,"买入")+SUMIFS(交易记录!$E$6:$E$605,交易记录!$A$6:$A$605,">="&DATE(YEAR(A48),MONTH(A48),1),交易记录!$A$6:$A$605,"<"&DATE(YEAR(A48),MONTH(A48)+1,1),交易记录!$B$6:$B$605,"SMH",交易记录!$C$6:$C$605,"买入") -> 0 | I48: =SUM(F48:H48) -> 0 | J48: =IF(I48=0,"",I48-B48) | K48: =IF(I48=0,"尚未记录买入",IF(ABS(J48)<0.01,"已记录预算金额","已记录，金额有差额")) -> 尚未记录买入
A49: =DATE(2030,5,总览!$E$4) -> 47613 | B49: =回撤计划!J52 -> 500 | C49: =B49*总览!$B$8 -> 450 | D49: =B49*总览!$B$9 -> 50 | E49: =B49*总览!$B$10 -> 0 | F49: =SUMIFS(交易记录!$D$6:$D$605,交易记录!$A$6:$A$605,">="&DATE(YEAR(A49),MONTH(A49),1),交易记录!$A$6:$A$605,"<"&DATE(YEAR(A49),MONTH(A49)+1,1),交易记录!$B$6:$B$605,"VOO",交易记录!$C$6:$C$605,"买入")+SUMIFS(交易记录!$E$6:$E$605,交易记录!$A$6:$A$605,">="&DATE(YEAR(A49),MONTH(A49),1),交易记录!$A$6:$A$605,"<"&DATE(YEAR(A49),MONTH(A49)+1,1),交易记录!$B$6:$B$605,"VOO",交易记录!$C$6:$C$605,"买入") -> 0 | G49: =SUMIFS(交易记录!$D$6:$D$605,交易记录!$A$6:$A$605,">="&DATE(YEAR(A49),MONTH(A49),1),交易记录!$A$6:$A$605,"<"&DATE(YEAR(A49),MONTH(A49)+1,1),交易记录!$B$6:$B$605,"QQQM",交易记录!$C$6:$C$605,"买入")+SUMIFS(交易记录!$E$6:$E$605,交易记录!$A$6:$A$605,">="&DATE(YEAR(A49),MONTH(A49),1),交易记录!$A$6:$A$605,"<"&DATE(YEAR(A49),MONTH(A49)+1,1),交易记录!$B$6:$B$605,"QQQM",交易记录!$C$6:$C$605,"买入") -> 0 | H49: =SUMIFS(交易记录!$D$6:$D$605,交易记录!$A$6:$A$605,">="&DATE(YEAR(A49),MONTH(A49),1),交易记录!$A$6:$A$605,"<"&DATE(YEAR(A49),MONTH(A49)+1,1),交易记录!$B$6:$B$605,"SMH",交易记录!$C$6:$C$605,"买入")+SUMIFS(交易记录!$E$6:$E$605,交易记录!$A$6:$A$605,">="&DATE(YEAR(A49),MONTH(A49),1),交易记录!$A$6:$A$605,"<"&DATE(YEAR(A49),MONTH(A49)+1,1),交易记录!$B$6:$B$605,"SMH",交易记录!$C$6:$C$605,"买入") -> 0 | I49: =SUM(F49:H49) -> 0 | J49: =IF(I49=0,"",I49-B49) | K49: =IF(I49=0,"尚未记录买入",IF(ABS(J49)<0.01,"已记录预算金额","已记录，金额有差额")) -> 尚未记录买入
A50: =DATE(2030,6,总览!$E$4) -> 47644 | B50: =回撤计划!J53 -> 500 | C50: =B50*总览!$B$8 -> 450 | D50: =B50*总览!$B$9 -> 50 | E50: =B50*总览!$B$10 -> 0 | F50: =SUMIFS(交易记录!$D$6:$D$605,交易记录!$A$6:$A$605,">="&DATE(YEAR(A50),MONTH(A50),1),交易记录!$A$6:$A$605,"<"&DATE(YEAR(A50),MONTH(A50)+1,1),交易记录!$B$6:$B$605,"VOO",交易记录!$C$6:$C$605,"买入")+SUMIFS(交易记录!$E$6:$E$605,交易记录!$A$6:$A$605,">="&DATE(YEAR(A50),MONTH(A50),1),交易记录!$A$6:$A$605,"<"&DATE(YEAR(A50),MONTH(A50)+1,1),交易记录!$B$6:$B$605,"VOO",交易记录!$C$6:$C$605,"买入") -> 0 | G50: =SUMIFS(交易记录!$D$6:$D$605,交易记录!$A$6:$A$605,">="&DATE(YEAR(A50),MONTH(A50),1),交易记录!$A$6:$A$605,"<"&DATE(YEAR(A50),MONTH(A50)+1,1),交易记录!$B$6:$B$605,"QQQM",交易记录!$C$6:$C$605,"买入")+SUMIFS(交易记录!$E$6:$E$605,交易记录!$A$6:$A$605,">="&DATE(YEAR(A50),MONTH(A50),1),交易记录!$A$6:$A$605,"<"&DATE(YEAR(A50),MONTH(A50)+1,1),交易记录!$B$6:$B$605,"QQQM",交易记录!$C$6:$C$605,"买入") -> 0 | H50: =SUMIFS(交易记录!$D$6:$D$605,交易记录!$A$6:$A$605,">="&DATE(YEAR(A50),MONTH(A50),1),交易记录!$A$6:$A$605,"<"&DATE(YEAR(A50),MONTH(A50)+1,1),交易记录!$B$6:$B$605,"SMH",交易记录!$C$6:$C$605,"买入")+SUMIFS(交易记录!$E$6:$E$605,交易记录!$A$6:$A$605,">="&DATE(YEAR(A50),MONTH(A50),1),交易记录!$A$6:$A$605,"<"&DATE(YEAR(A50),MONTH(A50)+1,1),交易记录!$B$6:$B$605,"SMH",交易记录!$C$6:$C$605,"买入") -> 0 | I50: =SUM(F50:H50) -> 0 | J50: =IF(I50=0,"",I50-B50) | K50: =IF(I50=0,"尚未记录买入",IF(ABS(J50)<0.01,"已记录预算金额","已记录，金额有差额")) -> 尚未记录买入
A51: =DATE(2030,7,总览!$E$4) -> 47674 | B51: =回撤计划!J54 -> 500 | C51: =B51*总览!$B$8 -> 450 | D51: =B51*总览!$B$9 -> 50 | E51: =B51*总览!$B$10 -> 0 | F51: =SUMIFS(交易记录!$D$6:$D$605,交易记录!$A$6:$A$605,">="&DATE(YEAR(A51),MONTH(A51),1),交易记录!$A$6:$A$605,"<"&DATE(YEAR(A51),MONTH(A51)+1,1),交易记录!$B$6:$B$605,"VOO",交易记录!$C$6:$C$605,"买入")+SUMIFS(交易记录!$E$6:$E$605,交易记录!$A$6:$A$605,">="&DATE(YEAR(A51),MONTH(A51),1),交易记录!$A$6:$A$605,"<"&DATE(YEAR(A51),MONTH(A51)+1,1),交易记录!$B$6:$B$605,"VOO",交易记录!$C$6:$C$605,"买入") -> 0 | G51: =SUMIFS(交易记录!$D$6:$D$605,交易记录!$A$6:$A$605,">="&DATE(YEAR(A51),MONTH(A51),1),交易记录!$A$6:$A$605,"<"&DATE(YEAR(A51),MONTH(A51)+1,1),交易记录!$B$6:$B$605,"QQQM",交易记录!$C$6:$C$605,"买入")+SUMIFS(交易记录!$E$6:$E$605,交易记录!$A$6:$A$605,">="&DATE(YEAR(A51),MONTH(A51),1),交易记录!$A$6:$A$605,"<"&DATE(YEAR(A51),MONTH(A51)+1,1),交易记录!$B$6:$B$605,"QQQM",交易记录!$C$6:$C$605,"买入") -> 0 | H51: =SUMIFS(交易记录!$D$6:$D$605,交易记录!$A$6:$A$605,">="&DATE(YEAR(A51),MONTH(A51),1),交易记录!$A$6:$A$605,"<"&DATE(YEAR(A51),MONTH(A51)+1,1),交易记录!$B$6:$B$605,"SMH",交易记录!$C$6:$C$605,"买入")+SUMIFS(交易记录!$E$6:$E$605,交易记录!$A$6:$A$605,">="&DATE(YEAR(A51),MONTH(A51),1),交易记录!$A$6:$A$605,"<"&DATE(YEAR(A51),MONTH(A51)+1,1),交易记录!$B$6:$B$605,"SMH",交易记录!$C$6:$C$605,"买入") -> 0 | I51: =SUM(F51:H51) -> 0 | J51: =IF(I51=0,"",I51-B51) | K51: =IF(I51=0,"尚未记录买入",IF(ABS(J51)<0.01,"已记录预算金额","已记录，金额有差额")) -> 尚未记录买入
A52: =DATE(2030,8,总览!$E$4) -> 47705 | B52: =回撤计划!J55 -> 500 | C52: =B52*总览!$B$8 -> 450 | D52: =B52*总览!$B$9 -> 50 | E52: =B52*总览!$B$10 -> 0 | F52: =SUMIFS(交易记录!$D$6:$D$605,交易记录!$A$6:$A$605,">="&DATE(YEAR(A52),MONTH(A52),1),交易记录!$A$6:$A$605,"<"&DATE(YEAR(A52),MONTH(A52)+1,1),交易记录!$B$6:$B$605,"VOO",交易记录!$C$6:$C$605,"买入")+SUMIFS(交易记录!$E$6:$E$605,交易记录!$A$6:$A$605,">="&DATE(YEAR(A52),MONTH(A52),1),交易记录!$A$6:$A$605,"<"&DATE(YEAR(A52),MONTH(A52)+1,1),交易记录!$B$6:$B$605,"VOO",交易记录!$C$6:$C$605,"买入") -> 0 | G52: =SUMIFS(交易记录!$D$6:$D$605,交易记录!$A$6:$A$605,">="&DATE(YEAR(A52),MONTH(A52),1),交易记录!$A$6:$A$605,"<"&DATE(YEAR(A52),MONTH(A52)+1,1),交易记录!$B$6:$B$605,"QQQM",交易记录!$C$6:$C$605,"买入")+SUMIFS(交易记录!$E$6:$E$605,交易记录!$A$6:$A$605,">="&DATE(YEAR(A52),MONTH(A52),1),交易记录!$A$6:$A$605,"<"&DATE(YEAR(A52),MONTH(A52)+1,1),交易记录!$B$6:$B$605,"QQQM",交易记录!$C$6:$C$605,"买入") -> 0 | H52: =SUMIFS(交易记录!$D$6:$D$605,交易记录!$A$6:$A$605,">="&DATE(YEAR(A52),MONTH(A52),1),交易记录!$A$6:$A$605,"<"&DATE(YEAR(A52),MONTH(A52)+1,1),交易记录!$B$6:$B$605,"SMH",交易记录!$C$6:$C$605,"买入")+SUMIFS(交易记录!$E$6:$E$605,交易记录!$A$6:$A$605,">="&DATE(YEAR(A52),MONTH(A52),1),交易记录!$A$6:$A$605,"<"&DATE(YEAR(A52),MONTH(A52)+1,1),交易记录!$B$6:$B$605,"SMH",交易记录!$C$6:$C$605,"买入") -> 0 | I52: =SUM(F52:H52) -> 0 | J52: =IF(I52=0,"",I52-B52) | K52: =IF(I52=0,"尚未记录买入",IF(ABS(J52)<0.01,"已记录预算金额","已记录，金额有差额")) -> 尚未记录买入
A53: =DATE(2030,9,总览!$E$4) -> 47736 | B53: =回撤计划!J56 -> 500 | C53: =B53*总览!$B$8 -> 450 | D53: =B53*总览!$B$9 -> 50 | E53: =B53*总览!$B$10 -> 0 | F53: =SUMIFS(交易记录!$D$6:$D$605,交易记录!$A$6:$A$605,">="&DATE(YEAR(A53),MONTH(A53),1),交易记录!$A$6:$A$605,"<"&DATE(YEAR(A53),MONTH(A53)+1,1),交易记录!$B$6:$B$605,"VOO",交易记录!$C$6:$C$605,"买入")+SUMIFS(交易记录!$E$6:$E$605,交易记录!$A$6:$A$605,">="&DATE(YEAR(A53),MONTH(A53),1),交易记录!$A$6:$A$605,"<"&DATE(YEAR(A53),MONTH(A53)+1,1),交易记录!$B$6:$B$605,"VOO",交易记录!$C$6:$C$605,"买入") -> 0 | G53: =SUMIFS(交易记录!$D$6:$D$605,交易记录!$A$6:$A$605,">="&DATE(YEAR(A53),MONTH(A53),1),交易记录!$A$6:$A$605,"<"&DATE(YEAR(A53),MONTH(A53)+1,1),交易记录!$B$6:$B$605,"QQQM",交易记录!$C$6:$C$605,"买入")+SUMIFS(交易记录!$E$6:$E$605,交易记录!$A$6:$A$605,">="&DATE(YEAR(A53),MONTH(A53),1),交易记录!$A$6:$A$605,"<"&DATE(YEAR(A53),MONTH(A53)+1,1),交易记录!$B$6:$B$605,"QQQM",交易记录!$C$6:$C$605,"买入") -> 0 | H53: =SUMIFS(交易记录!$D$6:$D$605,交易记录!$A$6:$A$605,">="&DATE(YEAR(A53),MONTH(A53),1),交易记录!$A$6:$A$605,"<"&DATE(YEAR(A53),MONTH(A53)+1,1),交易记录!$B$6:$B$605,"SMH",交易记录!$C$6:$C$605,"买入")+SUMIFS(交易记录!$E$6:$E$605,交易记录!$A$6:$A$605,">="&DATE(YEAR(A53),MONTH(A53),1),交易记录!$A$6:$A$605,"<"&DATE(YEAR(A53),MONTH(A53)+1,1),交易记录!$B$6:$B$605,"SMH",交易记录!$C$6:$C$605,"买入") -> 0 | I53: =SUM(F53:H53) -> 0 | J53: =IF(I53=0,"",I53-B53) | K53: =IF(I53=0,"尚未记录买入",IF(ABS(J53)<0.01,"已记录预算金额","已记录，金额有差额")) -> 尚未记录买入
A54: =DATE(2030,10,总览!$E$4) -> 47766 | B54: =回撤计划!J57 -> 500 | C54: =B54*总览!$B$8 -> 450 | D54: =B54*总览!$B$9 -> 50 | E54: =B54*总览!$B$10 -> 0 | F54: =SUMIFS(交易记录!$D$6:$D$605,交易记录!$A$6:$A$605,">="&DATE(YEAR(A54),MONTH(A54),1),交易记录!$A$6:$A$605,"<"&DATE(YEAR(A54),MONTH(A54)+1,1),交易记录!$B$6:$B$605,"VOO",交易记录!$C$6:$C$605,"买入")+SUMIFS(交易记录!$E$6:$E$605,交易记录!$A$6:$A$605,">="&DATE(YEAR(A54),MONTH(A54),1),交易记录!$A$6:$A$605,"<"&DATE(YEAR(A54),MONTH(A54)+1,1),交易记录!$B$6:$B$605,"VOO",交易记录!$C$6:$C$605,"买入") -> 0 | G54: =SUMIFS(交易记录!$D$6:$D$605,交易记录!$A$6:$A$605,">="&DATE(YEAR(A54),MONTH(A54),1),交易记录!$A$6:$A$605,"<"&DATE(YEAR(A54),MONTH(A54)+1,1),交易记录!$B$6:$B$605,"QQQM",交易记录!$C$6:$C$605,"买入")+SUMIFS(交易记录!$E$6:$E$605,交易记录!$A$6:$A$605,">="&DATE(YEAR(A54),MONTH(A54),1),交易记录!$A$6:$A$605,"<"&DATE(YEAR(A54),MONTH(A54)+1,1),交易记录!$B$6:$B$605,"QQQM",交易记录!$C$6:$C$605,"买入") -> 0 | H54: =SUMIFS(交易记录!$D$6:$D$605,交易记录!$A$6:$A$605,">="&DATE(YEAR(A54),MONTH(A54),1),交易记录!$A$6:$A$605,"<"&DATE(YEAR(A54),MONTH(A54)+1,1),交易记录!$B$6:$B$605,"SMH",交易记录!$C$6:$C$605,"买入")+SUMIFS(交易记录!$E$6:$E$605,交易记录!$A$6:$A$605,">="&DATE(YEAR(A54),MONTH(A54),1),交易记录!$A$6:$A$605,"<"&DATE(YEAR(A54),MONTH(A54)+1,1),交易记录!$B$6:$B$605,"SMH",交易记录!$C$6:$C$605,"买入") -> 0 | I54: =SUM(F54:H54) -> 0 | J54: =IF(I54=0,"",I54-B54) | K54: =IF(I54=0,"尚未记录买入",IF(ABS(J54)<0.01,"已记录预算金额","已记录，金额有差额")) -> 尚未记录买入
A55: =DATE(2030,11,总览!$E$4) -> 47797 | B55: =回撤计划!J58 -> 500 | C55: =B55*总览!$B$8 -> 450 | D55: =B55*总览!$B$9 -> 50 | E55: =B55*总览!$B$10 -> 0 | F55: =SUMIFS(交易记录!$D$6:$D$605,交易记录!$A$6:$A$605,">="&DATE(YEAR(A55),MONTH(A55),1),交易记录!$A$6:$A$605,"<"&DATE(YEAR(A55),MONTH(A55)+1,1),交易记录!$B$6:$B$605,"VOO",交易记录!$C$6:$C$605,"买入")+SUMIFS(交易记录!$E$6:$E$605,交易记录!$A$6:$A$605,">="&DATE(YEAR(A55),MONTH(A55),1),交易记录!$A$6:$A$605,"<"&DATE(YEAR(A55),MONTH(A55)+1,1),交易记录!$B$6:$B$605,"VOO",交易记录!$C$6:$C$605,"买入") -> 0 | G55: =SUMIFS(交易记录!$D$6:$D$605,交易记录!$A$6:$A$605,">="&DATE(YEAR(A55),MONTH(A55),1),交易记录!$A$6:$A$605,"<"&DATE(YEAR(A55),MONTH(A55)+1,1),交易记录!$B$6:$B$605,"QQQM",交易记录!$C$6:$C$605,"买入")+SUMIFS(交易记录!$E$6:$E$605,交易记录!$A$6:$A$605,">="&DATE(YEAR(A55),MONTH(A55),1),交易记录!$A$6:$A$605,"<"&DATE(YEAR(A55),MONTH(A55)+1,1),交易记录!$B$6:$B$605,"QQQM",交易记录!$C$6:$C$605,"买入") -> 0 | H55: =SUMIFS(交易记录!$D$6:$D$605,交易记录!$A$6:$A$605,">="&DATE(YEAR(A55),MONTH(A55),1),交易记录!$A$6:$A$605,"<"&DATE(YEAR(A55),MONTH(A55)+1,1),交易记录!$B$6:$B$605,"SMH",交易记录!$C$6:$C$605,"买入")+SUMIFS(交易记录!$E$6:$E$605,交易记录!$A$6:$A$605,">="&DATE(YEAR(A55),MONTH(A55),1),交易记录!$A$6:$A$605,"<"&DATE(YEAR(A55),MONTH(A55)+1,1),交易记录!$B$6:$B$605,"SMH",交易记录!$C$6:$C$605,"买入") -> 0 | I55: =SUM(F55:H55) -> 0 | J55: =IF(I55=0,"",I55-B55) | K55: =IF(I55=0,"尚未记录买入",IF(ABS(J55)<0.01,"已记录预算金额","已记录，金额有差额")) -> 尚未记录买入
A56: =DATE(2030,12,总览!$E$4) -> 47827 | B56: =回撤计划!J59 -> 500 | C56: =B56*总览!$B$8 -> 450 | D56: =B56*总览!$B$9 -> 50 | E56: =B56*总览!$B$10 -> 0 | F56: =SUMIFS(交易记录!$D$6:$D$605,交易记录!$A$6:$A$605,">="&DATE(YEAR(A56),MONTH(A56),1),交易记录!$A$6:$A$605,"<"&DATE(YEAR(A56),MONTH(A56)+1,1),交易记录!$B$6:$B$605,"VOO",交易记录!$C$6:$C$605,"买入")+SUMIFS(交易记录!$E$6:$E$605,交易记录!$A$6:$A$605,">="&DATE(YEAR(A56),MONTH(A56),1),交易记录!$A$6:$A$605,"<"&DATE(YEAR(A56),MONTH(A56)+1,1),交易记录!$B$6:$B$605,"VOO",交易记录!$C$6:$C$605,"买入") -> 0 | G56: =SUMIFS(交易记录!$D$6:$D$605,交易记录!$A$6:$A$605,">="&DATE(YEAR(A56),MONTH(A56),1),交易记录!$A$6:$A$605,"<"&DATE(YEAR(A56),MONTH(A56)+1,1),交易记录!$B$6:$B$605,"QQQM",交易记录!$C$6:$C$605,"买入")+SUMIFS(交易记录!$E$6:$E$605,交易记录!$A$6:$A$605,">="&DATE(YEAR(A56),MONTH(A56),1),交易记录!$A$6:$A$605,"<"&DATE(YEAR(A56),MONTH(A56)+1,1),交易记录!$B$6:$B$605,"QQQM",交易记录!$C$6:$C$605,"买入") -> 0 | H56: =SUMIFS(交易记录!$D$6:$D$605,交易记录!$A$6:$A$605,">="&DATE(YEAR(A56),MONTH(A56),1),交易记录!$A$6:$A$605,"<"&DATE(YEAR(A56),MONTH(A56)+1,1),交易记录!$B$6:$B$605,"SMH",交易记录!$C$6:$C$605,"买入")+SUMIFS(交易记录!$E$6:$E$605,交易记录!$A$6:$A$605,">="&DATE(YEAR(A56),MONTH(A56),1),交易记录!$A$6:$A$605,"<"&DATE(YEAR(A56),MONTH(A56)+1,1),交易记录!$B$6:$B$605,"SMH",交易记录!$C$6:$C$605,"买入") -> 0 | I56: =SUM(F56:H56) -> 0 | J56: =IF(I56=0,"",I56-B56) | K56: =IF(I56=0,"尚未记录买入",IF(ABS(J56)<0.01,"已记录预算金额","已记录，金额有差额")) -> 尚未记录买入
A57: =DATE(2031,1,总览!$E$4) -> 47858 | B57: =回撤计划!J60 -> 500 | C57: =B57*总览!$B$8 -> 450 | D57: =B57*总览!$B$9 -> 50 | E57: =B57*总览!$B$10 -> 0 | F57: =SUMIFS(交易记录!$D$6:$D$605,交易记录!$A$6:$A$605,">="&DATE(YEAR(A57),MONTH(A57),1),交易记录!$A$6:$A$605,"<"&DATE(YEAR(A57),MONTH(A57)+1,1),交易记录!$B$6:$B$605,"VOO",交易记录!$C$6:$C$605,"买入")+SUMIFS(交易记录!$E$6:$E$605,交易记录!$A$6:$A$605,">="&DATE(YEAR(A57),MONTH(A57),1),交易记录!$A$6:$A$605,"<"&DATE(YEAR(A57),MONTH(A57)+1,1),交易记录!$B$6:$B$605,"VOO",交易记录!$C$6:$C$605,"买入") -> 0 | G57: =SUMIFS(交易记录!$D$6:$D$605,交易记录!$A$6:$A$605,">="&DATE(YEAR(A57),MONTH(A57),1),交易记录!$A$6:$A$605,"<"&DATE(YEAR(A57),MONTH(A57)+1,1),交易记录!$B$6:$B$605,"QQQM",交易记录!$C$6:$C$605,"买入")+SUMIFS(交易记录!$E$6:$E$605,交易记录!$A$6:$A$605,">="&DATE(YEAR(A57),MONTH(A57),1),交易记录!$A$6:$A$605,"<"&DATE(YEAR(A57),MONTH(A57)+1,1),交易记录!$B$6:$B$605,"QQQM",交易记录!$C$6:$C$605,"买入") -> 0 | H57: =SUMIFS(交易记录!$D$6:$D$605,交易记录!$A$6:$A$605,">="&DATE(YEAR(A57),MONTH(A57),1),交易记录!$A$6:$A$605,"<"&DATE(YEAR(A57),MONTH(A57)+1,1),交易记录!$B$6:$B$605,"SMH",交易记录!$C$6:$C$605,"买入")+SUMIFS(交易记录!$E$6:$E$605,交易记录!$A$6:$A$605,">="&DATE(YEAR(A57),MONTH(A57),1),交易记录!$A$6:$A$605,"<"&DATE(YEAR(A57),MONTH(A57)+1,1),交易记录!$B$6:$B$605,"SMH",交易记录!$C$6:$C$605,"买入") -> 0 | I57: =SUM(F57:H57) -> 0 | J57: =IF(I57=0,"",I57-B57) | K57: =IF(I57=0,"尚未记录买入",IF(ABS(J57)<0.01,"已记录预算金额","已记录，金额有差额")) -> 尚未记录买入
A58: =DATE(2031,2,总览!$E$4) -> 47889 | B58: =回撤计划!J61 -> 500 | C58: =B58*总览!$B$8 -> 450 | D58: =B58*总览!$B$9 -> 50 | E58: =B58*总览!$B$10 -> 0 | F58: =SUMIFS(交易记录!$D$6:$D$605,交易记录!$A$6:$A$605,">="&DATE(YEAR(A58),MONTH(A58),1),交易记录!$A$6:$A$605,"<"&DATE(YEAR(A58),MONTH(A58)+1,1),交易记录!$B$6:$B$605,"VOO",交易记录!$C$6:$C$605,"买入")+SUMIFS(交易记录!$E$6:$E$605,交易记录!$A$6:$A$605,">="&DATE(YEAR(A58),MONTH(A58),1),交易记录!$A$6:$A$605,"<"&DATE(YEAR(A58),MONTH(A58)+1,1),交易记录!$B$6:$B$605,"VOO",交易记录!$C$6:$C$605,"买入") -> 0 | G58: =SUMIFS(交易记录!$D$6:$D$605,交易记录!$A$6:$A$605,">="&DATE(YEAR(A58),MONTH(A58),1),交易记录!$A$6:$A$605,"<"&DATE(YEAR(A58),MONTH(A58)+1,1),交易记录!$B$6:$B$605,"QQQM",交易记录!$C$6:$C$605,"买入")+SUMIFS(交易记录!$E$6:$E$605,交易记录!$A$6:$A$605,">="&DATE(YEAR(A58),MONTH(A58),1),交易记录!$A$6:$A$605,"<"&DATE(YEAR(A58),MONTH(A58)+1,1),交易记录!$B$6:$B$605,"QQQM",交易记录!$C$6:$C$605,"买入") -> 0 | H58: =SUMIFS(交易记录!$D$6:$D$605,交易记录!$A$6:$A$605,">="&DATE(YEAR(A58),MONTH(A58),1),交易记录!$A$6:$A$605,"<"&DATE(YEAR(A58),MONTH(A58)+1,1),交易记录!$B$6:$B$605,"SMH",交易记录!$C$6:$C$605,"买入")+SUMIFS(交易记录!$E$6:$E$605,交易记录!$A$6:$A$605,">="&DATE(YEAR(A58),MONTH(A58),1),交易记录!$A$6:$A$605,"<"&DATE(YEAR(A58),MONTH(A58)+1,1),交易记录!$B$6:$B$605,"SMH",交易记录!$C$6:$C$605,"买入") -> 0 | I58: =SUM(F58:H58) -> 0 | J58: =IF(I58=0,"",I58-B58) | K58: =IF(I58=0,"尚未记录买入",IF(ABS(J58)<0.01,"已记录预算金额","已记录，金额有差额")) -> 尚未记录买入
A59: =DATE(2031,3,总览!$E$4) -> 47917 | B59: =回撤计划!J62 -> 500 | C59: =B59*总览!$B$8 -> 450 | D59: =B59*总览!$B$9 -> 50 | E59: =B59*总览!$B$10 -> 0 | F59: =SUMIFS(交易记录!$D$6:$D$605,交易记录!$A$6:$A$605,">="&DATE(YEAR(A59),MONTH(A59),1),交易记录!$A$6:$A$605,"<"&DATE(YEAR(A59),MONTH(A59)+1,1),交易记录!$B$6:$B$605,"VOO",交易记录!$C$6:$C$605,"买入")+SUMIFS(交易记录!$E$6:$E$605,交易记录!$A$6:$A$605,">="&DATE(YEAR(A59),MONTH(A59),1),交易记录!$A$6:$A$605,"<"&DATE(YEAR(A59),MONTH(A59)+1,1),交易记录!$B$6:$B$605,"VOO",交易记录!$C$6:$C$605,"买入") -> 0 | G59: =SUMIFS(交易记录!$D$6:$D$605,交易记录!$A$6:$A$605,">="&DATE(YEAR(A59),MONTH(A59),1),交易记录!$A$6:$A$605,"<"&DATE(YEAR(A59),MONTH(A59)+1,1),交易记录!$B$6:$B$605,"QQQM",交易记录!$C$6:$C$605,"买入")+SUMIFS(交易记录!$E$6:$E$605,交易记录!$A$6:$A$605,">="&DATE(YEAR(A59),MONTH(A59),1),交易记录!$A$6:$A$605,"<"&DATE(YEAR(A59),MONTH(A59)+1,1),交易记录!$B$6:$B$605,"QQQM",交易记录!$C$6:$C$605,"买入") -> 0 | H59: =SUMIFS(交易记录!$D$6:$D$605,交易记录!$A$6:$A$605,">="&DATE(YEAR(A59),MONTH(A59),1),交易记录!$A$6:$A$605,"<"&DATE(YEAR(A59),MONTH(A59)+1,1),交易记录!$B$6:$B$605,"SMH",交易记录!$C$6:$C$605,"买入")+SUMIFS(交易记录!$E$6:$E$605,交易记录!$A$6:$A$605,">="&DATE(YEAR(A59),MONTH(A59),1),交易记录!$A$6:$A$605,"<"&DATE(YEAR(A59),MONTH(A59)+1,1),交易记录!$B$6:$B$605,"SMH",交易记录!$C$6:$C$605,"买入") -> 0 | I59: =SUM(F59:H59) -> 0 | J59: =IF(I59=0,"",I59-B59) | K59: =IF(I59=0,"尚未记录买入",IF(ABS(J59)<0.01,"已记录预算金额","已记录，金额有差额")) -> 尚未记录买入
A60: =DATE(2031,4,总览!$E$4) -> 47948 | B60: =回撤计划!J63 -> 500 | C60: =B60*总览!$B$8 -> 450 | D60: =B60*总览!$B$9 -> 50 | E60: =B60*总览!$B$10 -> 0 | F60: =SUMIFS(交易记录!$D$6:$D$605,交易记录!$A$6:$A$605,">="&DATE(YEAR(A60),MONTH(A60),1),交易记录!$A$6:$A$605,"<"&DATE(YEAR(A60),MONTH(A60)+1,1),交易记录!$B$6:$B$605,"VOO",交易记录!$C$6:$C$605,"买入")+SUMIFS(交易记录!$E$6:$E$605,交易记录!$A$6:$A$605,">="&DATE(YEAR(A60),MONTH(A60),1),交易记录!$A$6:$A$605,"<"&DATE(YEAR(A60),MONTH(A60)+1,1),交易记录!$B$6:$B$605,"VOO",交易记录!$C$6:$C$605,"买入") -> 0 | G60: =SUMIFS(交易记录!$D$6:$D$605,交易记录!$A$6:$A$605,">="&DATE(YEAR(A60),MONTH(A60),1),交易记录!$A$6:$A$605,"<"&DATE(YEAR(A60),MONTH(A60)+1,1),交易记录!$B$6:$B$605,"QQQM",交易记录!$C$6:$C$605,"买入")+SUMIFS(交易记录!$E$6:$E$605,交易记录!$A$6:$A$605,">="&DATE(YEAR(A60),MONTH(A60),1),交易记录!$A$6:$A$605,"<"&DATE(YEAR(A60),MONTH(A60)+1,1),交易记录!$B$6:$B$605,"QQQM",交易记录!$C$6:$C$605,"买入") -> 0 | H60: =SUMIFS(交易记录!$D$6:$D$605,交易记录!$A$6:$A$605,">="&DATE(YEAR(A60),MONTH(A60),1),交易记录!$A$6:$A$605,"<"&DATE(YEAR(A60),MONTH(A60)+1,1),交易记录!$B$6:$B$605,"SMH",交易记录!$C$6:$C$605,"买入")+SUMIFS(交易记录!$E$6:$E$605,交易记录!$A$6:$A$605,">="&DATE(YEAR(A60),MONTH(A60),1),交易记录!$A$6:$A$605,"<"&DATE(YEAR(A60),MONTH(A60)+1,1),交易记录!$B$6:$B$605,"SMH",交易记录!$C$6:$C$605,"买入") -> 0 | I60: =SUM(F60:H60) -> 0 | J60: =IF(I60=0,"",I60-B60) | K60: =IF(I60=0,"尚未记录买入",IF(ABS(J60)<0.01,"已记录预算金额","已记录，金额有差额")) -> 尚未记录买入
A61: =DATE(2031,5,总览!$E$4) -> 47978 | B61: =回撤计划!J64 -> 500 | C61: =B61*总览!$B$8 -> 450 | D61: =B61*总览!$B$9 -> 50 | E61: =B61*总览!$B$10 -> 0 | F61: =SUMIFS(交易记录!$D$6:$D$605,交易记录!$A$6:$A$605,">="&DATE(YEAR(A61),MONTH(A61),1),交易记录!$A$6:$A$605,"<"&DATE(YEAR(A61),MONTH(A61)+1,1),交易记录!$B$6:$B$605,"VOO",交易记录!$C$6:$C$605,"买入")+SUMIFS(交易记录!$E$6:$E$605,交易记录!$A$6:$A$605,">="&DATE(YEAR(A61),MONTH(A61),1),交易记录!$A$6:$A$605,"<"&DATE(YEAR(A61),MONTH(A61)+1,1),交易记录!$B$6:$B$605,"VOO",交易记录!$C$6:$C$605,"买入") -> 0 | G61: =SUMIFS(交易记录!$D$6:$D$605,交易记录!$A$6:$A$605,">="&DATE(YEAR(A61),MONTH(A61),1),交易记录!$A$6:$A$605,"<"&DATE(YEAR(A61),MONTH(A61)+1,1),交易记录!$B$6:$B$605,"QQQM",交易记录!$C$6:$C$605,"买入")+SUMIFS(交易记录!$E$6:$E$605,交易记录!$A$6:$A$605,">="&DATE(YEAR(A61),MONTH(A61),1),交易记录!$A$6:$A$605,"<"&DATE(YEAR(A61),MONTH(A61)+1,1),交易记录!$B$6:$B$605,"QQQM",交易记录!$C$6:$C$605,"买入") -> 0 | H61: =SUMIFS(交易记录!$D$6:$D$605,交易记录!$A$6:$A$605,">="&DATE(YEAR(A61),MONTH(A61),1),交易记录!$A$6:$A$605,"<"&DATE(YEAR(A61),MONTH(A61)+1,1),交易记录!$B$6:$B$605,"SMH",交易记录!$C$6:$C$605,"买入")+SUMIFS(交易记录!$E$6:$E$605,交易记录!$A$6:$A$605,">="&DATE(YEAR(A61),MONTH(A61),1),交易记录!$A$6:$A$605,"<"&DATE(YEAR(A61),MONTH(A61)+1,1),交易记录!$B$6:$B$605,"SMH",交易记录!$C$6:$C$605,"买入") -> 0 | I61: =SUM(F61:H61) -> 0 | J61: =IF(I61=0,"",I61-B61) | K61: =IF(I61=0,"尚未记录买入",IF(ABS(J61)<0.01,"已记录预算金额","已记录，金额有差额")) -> 尚未记录买入
A62: =DATE(2031,6,总览!$E$4) -> 48009 | B62: =回撤计划!J65 -> 500 | C62: =B62*总览!$B$8 -> 450 | D62: =B62*总览!$B$9 -> 50 | E62: =B62*总览!$B$10 -> 0 | F62: =SUMIFS(交易记录!$D$6:$D$605,交易记录!$A$6:$A$605,">="&DATE(YEAR(A62),MONTH(A62),1),交易记录!$A$6:$A$605,"<"&DATE(YEAR(A62),MONTH(A62)+1,1),交易记录!$B$6:$B$605,"VOO",交易记录!$C$6:$C$605,"买入")+SUMIFS(交易记录!$E$6:$E$605,交易记录!$A$6:$A$605,">="&DATE(YEAR(A62),MONTH(A62),1),交易记录!$A$6:$A$605,"<"&DATE(YEAR(A62),MONTH(A62)+1,1),交易记录!$B$6:$B$605,"VOO",交易记录!$C$6:$C$605,"买入") -> 0 | G62: =SUMIFS(交易记录!$D$6:$D$605,交易记录!$A$6:$A$605,">="&DATE(YEAR(A62),MONTH(A62),1),交易记录!$A$6:$A$605,"<"&DATE(YEAR(A62),MONTH(A62)+1,1),交易记录!$B$6:$B$605,"QQQM",交易记录!$C$6:$C$605,"买入")+SUMIFS(交易记录!$E$6:$E$605,交易记录!$A$6:$A$605,">="&DATE(YEAR(A62),MONTH(A62),1),交易记录!$A$6:$A$605,"<"&DATE(YEAR(A62),MONTH(A62)+1,1),交易记录!$B$6:$B$605,"QQQM",交易记录!$C$6:$C$605,"买入") -> 0 | H62: =SUMIFS(交易记录!$D$6:$D$605,交易记录!$A$6:$A$605,">="&DATE(YEAR(A62),MONTH(A62),1),交易记录!$A$6:$A$605,"<"&DATE(YEAR(A62),MONTH(A62)+1,1),交易记录!$B$6:$B$605,"SMH",交易记录!$C$6:$C$605,"买入")+SUMIFS(交易记录!$E$6:$E$605,交易记录!$A$6:$A$605,">="&DATE(YEAR(A62),MONTH(A62),1),交易记录!$A$6:$A$605,"<"&DATE(YEAR(A62),MONTH(A62)+1,1),交易记录!$B$6:$B$605,"SMH",交易记录!$C$6:$C$605,"买入") -> 0 | I62: =SUM(F62:H62) -> 0 | J62: =IF(I62=0,"",I62-B62) | K62: =IF(I62=0,"尚未记录买入",IF(ABS(J62)<0.01,"已记录预算金额","已记录，金额有差额")) -> 尚未记录买入
A63: =DATE(2031,7,总览!$E$4) -> 48039 | B63: =回撤计划!J66 -> 500 | C63: =B63*总览!$B$8 -> 450 | D63: =B63*总览!$B$9 -> 50 | E63: =B63*总览!$B$10 -> 0 | F63: =SUMIFS(交易记录!$D$6:$D$605,交易记录!$A$6:$A$605,">="&DATE(YEAR(A63),MONTH(A63),1),交易记录!$A$6:$A$605,"<"&DATE(YEAR(A63),MONTH(A63)+1,1),交易记录!$B$6:$B$605,"VOO",交易记录!$C$6:$C$605,"买入")+SUMIFS(交易记录!$E$6:$E$605,交易记录!$A$6:$A$605,">="&DATE(YEAR(A63),MONTH(A63),1),交易记录!$A$6:$A$605,"<"&DATE(YEAR(A63),MONTH(A63)+1,1),交易记录!$B$6:$B$605,"VOO",交易记录!$C$6:$C$605,"买入") -> 0 | G63: =SUMIFS(交易记录!$D$6:$D$605,交易记录!$A$6:$A$605,">="&DATE(YEAR(A63),MONTH(A63),1),交易记录!$A$6:$A$605,"<"&DATE(YEAR(A63),MONTH(A63)+1,1),交易记录!$B$6:$B$605,"QQQM",交易记录!$C$6:$C$605,"买入")+SUMIFS(交易记录!$E$6:$E$605,交易记录!$A$6:$A$605,">="&DATE(YEAR(A63),MONTH(A63),1),交易记录!$A$6:$A$605,"<"&DATE(YEAR(A63),MONTH(A63)+1,1),交易记录!$B$6:$B$605,"QQQM",交易记录!$C$6:$C$605,"买入") -> 0 | H63: =SUMIFS(交易记录!$D$6:$D$605,交易记录!$A$6:$A$605,">="&DATE(YEAR(A63),MONTH(A63),1),交易记录!$A$6:$A$605,"<"&DATE(YEAR(A63),MONTH(A63)+1,1),交易记录!$B$6:$B$605,"SMH",交易记录!$C$6:$C$605,"买入")+SUMIFS(交易记录!$E$6:$E$605,交易记录!$A$6:$A$605,">="&DATE(YEAR(A63),MONTH(A63),1),交易记录!$A$6:$A$605,"<"&DATE(YEAR(A63),MONTH(A63)+1,1),交易记录!$B$6:$B$605,"SMH",交易记录!$C$6:$C$605,"买入") -> 0 | I63: =SUM(F63:H63) -> 0 | J63: =IF(I63=0,"",I63-B63) | K63: =IF(I63=0,"尚未记录买入",IF(ABS(J63)<0.01,"已记录预算金额","已记录，金额有差额")) -> 尚未记录买入
A64: =DATE(2031,8,总览!$E$4) -> 48070 | B64: =回撤计划!J67 -> 500 | C64: =B64*总览!$B$8 -> 450 | D64: =B64*总览!$B$9 -> 50 | E64: =B64*总览!$B$10 -> 0 | F64: =SUMIFS(交易记录!$D$6:$D$605,交易记录!$A$6:$A$605,">="&DATE(YEAR(A64),MONTH(A64),1),交易记录!$A$6:$A$605,"<"&DATE(YEAR(A64),MONTH(A64)+1,1),交易记录!$B$6:$B$605,"VOO",交易记录!$C$6:$C$605,"买入")+SUMIFS(交易记录!$E$6:$E$605,交易记录!$A$6:$A$605,">="&DATE(YEAR(A64),MONTH(A64),1),交易记录!$A$6:$A$605,"<"&DATE(YEAR(A64),MONTH(A64)+1,1),交易记录!$B$6:$B$605,"VOO",交易记录!$C$6:$C$605,"买入") -> 0 | G64: =SUMIFS(交易记录!$D$6:$D$605,交易记录!$A$6:$A$605,">="&DATE(YEAR(A64),MONTH(A64),1),交易记录!$A$6:$A$605,"<"&DATE(YEAR(A64),MONTH(A64)+1,1),交易记录!$B$6:$B$605,"QQQM",交易记录!$C$6:$C$605,"买入")+SUMIFS(交易记录!$E$6:$E$605,交易记录!$A$6:$A$605,">="&DATE(YEAR(A64),MONTH(A64),1),交易记录!$A$6:$A$605,"<"&DATE(YEAR(A64),MONTH(A64)+1,1),交易记录!$B$6:$B$605,"QQQM",交易记录!$C$6:$C$605,"买入") -> 0 | H64: =SUMIFS(交易记录!$D$6:$D$605,交易记录!$A$6:$A$605,">="&DATE(YEAR(A64),MONTH(A64),1),交易记录!$A$6:$A$605,"<"&DATE(YEAR(A64),MONTH(A64)+1,1),交易记录!$B$6:$B$605,"SMH",交易记录!$C$6:$C$605,"买入")+SUMIFS(交易记录!$E$6:$E$605,交易记录!$A$6:$A$605,">="&DATE(YEAR(A64),MONTH(A64),1),交易记录!$A$6:$A$605,"<"&DATE(YEAR(A64),MONTH(A64)+1,1),交易记录!$B$6:$B$605,"SMH",交易记录!$C$6:$C$605,"买入") -> 0 | I64: =SUM(F64:H64) -> 0 | J64: =IF(I64=0,"",I64-B64) | K64: =IF(I64=0,"尚未记录买入",IF(ABS(J64)<0.01,"已记录预算金额","已记录，金额有差额")) -> 尚未记录买入
A65: =DATE(2031,9,总览!$E$4) -> 48101 | B65: =回撤计划!J68 -> 500 | C65: =B65*总览!$B$8 -> 450 | D65: =B65*总览!$B$9 -> 50 | E65: =B65*总览!$B$10 -> 0 | F65: =SUMIFS(交易记录!$D$6:$D$605,交易记录!$A$6:$A$605,">="&DATE(YEAR(A65),MONTH(A65),1),交易记录!$A$6:$A$605,"<"&DATE(YEAR(A65),MONTH(A65)+1,1),交易记录!$B$6:$B$605,"VOO",交易记录!$C$6:$C$605,"买入")+SUMIFS(交易记录!$E$6:$E$605,交易记录!$A$6:$A$605,">="&DATE(YEAR(A65),MONTH(A65),1),交易记录!$A$6:$A$605,"<"&DATE(YEAR(A65),MONTH(A65)+1,1),交易记录!$B$6:$B$605,"VOO",交易记录!$C$6:$C$605,"买入") -> 0 | G65: =SUMIFS(交易记录!$D$6:$D$605,交易记录!$A$6:$A$605,">="&DATE(YEAR(A65),MONTH(A65),1),交易记录!$A$6:$A$605,"<"&DATE(YEAR(A65),MONTH(A65)+1,1),交易记录!$B$6:$B$605,"QQQM",交易记录!$C$6:$C$605,"买入")+SUMIFS(交易记录!$E$6:$E$605,交易记录!$A$6:$A$605,">="&DATE(YEAR(A65),MONTH(A65),1),交易记录!$A$6:$A$605,"<"&DATE(YEAR(A65),MONTH(A65)+1,1),交易记录!$B$6:$B$605,"QQQM",交易记录!$C$6:$C$605,"买入") -> 0 | H65: =SUMIFS(交易记录!$D$6:$D$605,交易记录!$A$6:$A$605,">="&DATE(YEAR(A65),MONTH(A65),1),交易记录!$A$6:$A$605,"<"&DATE(YEAR(A65),MONTH(A65)+1,1),交易记录!$B$6:$B$605,"SMH",交易记录!$C$6:$C$605,"买入")+SUMIFS(交易记录!$E$6:$E$605,交易记录!$A$6:$A$605,">="&DATE(YEAR(A65),MONTH(A65),1),交易记录!$A$6:$A$605,"<"&DATE(YEAR(A65),MONTH(A65)+1,1),交易记录!$B$6:$B$605,"SMH",交易记录!$C$6:$C$605,"买入") -> 0 | I65: =SUM(F65:H65) -> 0 | J65: =IF(I65=0,"",I65-B65) | K65: =IF(I65=0,"尚未记录买入",IF(ABS(J65)<0.01,"已记录预算金额","已记录，金额有差额")) -> 尚未记录买入
A66: =DATE(2031,10,总览!$E$4) -> 48131 | B66: =回撤计划!J69 -> 500 | C66: =B66*总览!$B$8 -> 450 | D66: =B66*总览!$B$9 -> 50 | E66: =B66*总览!$B$10 -> 0 | F66: =SUMIFS(交易记录!$D$6:$D$605,交易记录!$A$6:$A$605,">="&DATE(YEAR(A66),MONTH(A66),1),交易记录!$A$6:$A$605,"<"&DATE(YEAR(A66),MONTH(A66)+1,1),交易记录!$B$6:$B$605,"VOO",交易记录!$C$6:$C$605,"买入")+SUMIFS(交易记录!$E$6:$E$605,交易记录!$A$6:$A$605,">="&DATE(YEAR(A66),MONTH(A66),1),交易记录!$A$6:$A$605,"<"&DATE(YEAR(A66),MONTH(A66)+1,1),交易记录!$B$6:$B$605,"VOO",交易记录!$C$6:$C$605,"买入") -> 0 | G66: =SUMIFS(交易记录!$D$6:$D$605,交易记录!$A$6:$A$605,">="&DATE(YEAR(A66),MONTH(A66),1),交易记录!$A$6:$A$605,"<"&DATE(YEAR(A66),MONTH(A66)+1,1),交易记录!$B$6:$B$605,"QQQM",交易记录!$C$6:$C$605,"买入")+SUMIFS(交易记录!$E$6:$E$605,交易记录!$A$6:$A$605,">="&DATE(YEAR(A66),MONTH(A66),1),交易记录!$A$6:$A$605,"<"&DATE(YEAR(A66),MONTH(A66)+1,1),交易记录!$B$6:$B$605,"QQQM",交易记录!$C$6:$C$605,"买入") -> 0 | H66: =SUMIFS(交易记录!$D$6:$D$605,交易记录!$A$6:$A$605,">="&DATE(YEAR(A66),MONTH(A66),1),交易记录!$A$6:$A$605,"<"&DATE(YEAR(A66),MONTH(A66)+1,1),交易记录!$B$6:$B$605,"SMH",交易记录!$C$6:$C$605,"买入")+SUMIFS(交易记录!$E$6:$E$605,交易记录!$A$6:$A$605,">="&DATE(YEAR(A66),MONTH(A66),1),交易记录!$A$6:$A$605,"<"&DATE(YEAR(A66),MONTH(A66)+1,1),交易记录!$B$6:$B$605,"SMH",交易记录!$C$6:$C$605,"买入") -> 0 | I66: =SUM(F66:H66) -> 0 | J66: =IF(I66=0,"",I66-B66) | K66: =IF(I66=0,"尚未记录买入",IF(ABS(J66)<0.01,"已记录预算金额","已记录，金额有差额")) -> 尚未记录买入
A67: =DATE(2031,11,总览!$E$4) -> 48162 | B67: =回撤计划!J70 -> 500 | C67: =B67*总览!$B$8 -> 450 | D67: =B67*总览!$B$9 -> 50 | E67: =B67*总览!$B$10 -> 0 | F67: =SUMIFS(交易记录!$D$6:$D$605,交易记录!$A$6:$A$605,">="&DATE(YEAR(A67),MONTH(A67),1),交易记录!$A$6:$A$605,"<"&DATE(YEAR(A67),MONTH(A67)+1,1),交易记录!$B$6:$B$605,"VOO",交易记录!$C$6:$C$605,"买入")+SUMIFS(交易记录!$E$6:$E$605,交易记录!$A$6:$A$605,">="&DATE(YEAR(A67),MONTH(A67),1),交易记录!$A$6:$A$605,"<"&DATE(YEAR(A67),MONTH(A67)+1,1),交易记录!$B$6:$B$605,"VOO",交易记录!$C$6:$C$605,"买入") -> 0 | G67: =SUMIFS(交易记录!$D$6:$D$605,交易记录!$A$6:$A$605,">="&DATE(YEAR(A67),MONTH(A67),1),交易记录!$A$6:$A$605,"<"&DATE(YEAR(A67),MONTH(A67)+1,1),交易记录!$B$6:$B$605,"QQQM",交易记录!$C$6:$C$605,"买入")+SUMIFS(交易记录!$E$6:$E$605,交易记录!$A$6:$A$605,">="&DATE(YEAR(A67),MONTH(A67),1),交易记录!$A$6:$A$605,"<"&DATE(YEAR(A67),MONTH(A67)+1,1),交易记录!$B$6:$B$605,"QQQM",交易记录!$C$6:$C$605,"买入") -> 0 | H67: =SUMIFS(交易记录!$D$6:$D$605,交易记录!$A$6:$A$605,">="&DATE(YEAR(A67),MONTH(A67),1),交易记录!$A$6:$A$605,"<"&DATE(YEAR(A67),MONTH(A67)+1,1),交易记录!$B$6:$B$605,"SMH",交易记录!$C$6:$C$605,"买入")+SUMIFS(交易记录!$E$6:$E$605,交易记录!$A$6:$A$605,">="&DATE(YEAR(A67),MONTH(A67),1),交易记录!$A$6:$A$605,"<"&DATE(YEAR(A67),MONTH(A67)+1,1),交易记录!$B$6:$B$605,"SMH",交易记录!$C$6:$C$605,"买入") -> 0 | I67: =SUM(F67:H67) -> 0 | J67: =IF(I67=0,"",I67-B67) | K67: =IF(I67=0,"尚未记录买入",IF(ABS(J67)<0.01,"已记录预算金额","已记录，金额有差额")) -> 尚未记录买入
A68: =DATE(2031,12,总览!$E$4) -> 48192 | B68: =回撤计划!J71 -> 500 | C68: =B68*总览!$B$8 -> 450 | D68: =B68*总览!$B$9 -> 50 | E68: =B68*总览!$B$10 -> 0 | F68: =SUMIFS(交易记录!$D$6:$D$605,交易记录!$A$6:$A$605,">="&DATE(YEAR(A68),MONTH(A68),1),交易记录!$A$6:$A$605,"<"&DATE(YEAR(A68),MONTH(A68)+1,1),交易记录!$B$6:$B$605,"VOO",交易记录!$C$6:$C$605,"买入")+SUMIFS(交易记录!$E$6:$E$605,交易记录!$A$6:$A$605,">="&DATE(YEAR(A68),MONTH(A68),1),交易记录!$A$6:$A$605,"<"&DATE(YEAR(A68),MONTH(A68)+1,1),交易记录!$B$6:$B$605,"VOO",交易记录!$C$6:$C$605,"买入") -> 0 | G68: =SUMIFS(交易记录!$D$6:$D$605,交易记录!$A$6:$A$605,">="&DATE(YEAR(A68),MONTH(A68),1),交易记录!$A$6:$A$605,"<"&DATE(YEAR(A68),MONTH(A68)+1,1),交易记录!$B$6:$B$605,"QQQM",交易记录!$C$6:$C$605,"买入")+SUMIFS(交易记录!$E$6:$E$605,交易记录!$A$6:$A$605,">="&DATE(YEAR(A68),MONTH(A68),1),交易记录!$A$6:$A$605,"<"&DATE(YEAR(A68),MONTH(A68)+1,1),交易记录!$B$6:$B$605,"QQQM",交易记录!$C$6:$C$605,"买入") -> 0 | H68: =SUMIFS(交易记录!$D$6:$D$605,交易记录!$A$6:$A$605,">="&DATE(YEAR(A68),MONTH(A68),1),交易记录!$A$6:$A$605,"<"&DATE(YEAR(A68),MONTH(A68)+1,1),交易记录!$B$6:$B$605,"SMH",交易记录!$C$6:$C$605,"买入")+SUMIFS(交易记录!$E$6:$E$605,交易记录!$A$6:$A$605,">="&DATE(YEAR(A68),MONTH(A68),1),交易记录!$A$6:$A$605,"<"&DATE(YEAR(A68),MONTH(A68)+1,1),交易记录!$B$6:$B$605,"SMH",交易记录!$C$6:$C$605,"买入") -> 0 | I68: =SUM(F68:H68) -> 0 | J68: =IF(I68=0,"",I68-B68) | K68: =IF(I68=0,"尚未记录买入",IF(ABS(J68)<0.01,"已记录预算金额","已记录，金额有差额")) -> 尚未记录买入
A69: =DATE(2032,1,总览!$E$4) -> 48223 | B69: =回撤计划!J72 -> 500 | C69: =B69*总览!$B$8 -> 450 | D69: =B69*总览!$B$9 -> 50 | E69: =B69*总览!$B$10 -> 0 | F69: =SUMIFS(交易记录!$D$6:$D$605,交易记录!$A$6:$A$605,">="&DATE(YEAR(A69),MONTH(A69),1),交易记录!$A$6:$A$605,"<"&DATE(YEAR(A69),MONTH(A69)+1,1),交易记录!$B$6:$B$605,"VOO",交易记录!$C$6:$C$605,"买入")+SUMIFS(交易记录!$E$6:$E$605,交易记录!$A$6:$A$605,">="&DATE(YEAR(A69),MONTH(A69),1),交易记录!$A$6:$A$605,"<"&DATE(YEAR(A69),MONTH(A69)+1,1),交易记录!$B$6:$B$605,"VOO",交易记录!$C$6:$C$605,"买入") -> 0 | G69: =SUMIFS(交易记录!$D$6:$D$605,交易记录!$A$6:$A$605,">="&DATE(YEAR(A69),MONTH(A69),1),交易记录!$A$6:$A$605,"<"&DATE(YEAR(A69),MONTH(A69)+1,1),交易记录!$B$6:$B$605,"QQQM",交易记录!$C$6:$C$605,"买入")+SUMIFS(交易记录!$E$6:$E$605,交易记录!$A$6:$A$605,">="&DATE(YEAR(A69),MONTH(A69),1),交易记录!$A$6:$A$605,"<"&DATE(YEAR(A69),MONTH(A69)+1,1),交易记录!$B$6:$B$605,"QQQM",交易记录!$C$6:$C$605,"买入") -> 0 | H69: =SUMIFS(交易记录!$D$6:$D$605,交易记录!$A$6:$A$605,">="&DATE(YEAR(A69),MONTH(A69),1),交易记录!$A$6:$A$605,"<"&DATE(YEAR(A69),MONTH(A69)+1,1),交易记录!$B$6:$B$605,"SMH",交易记录!$C$6:$C$605,"买入")+SUMIFS(交易记录!$E$6:$E$605,交易记录!$A$6:$A$605,">="&DATE(YEAR(A69),MONTH(A69),1),交易记录!$A$6:$A$605,"<"&DATE(YEAR(A69),MONTH(A69)+1,1),交易记录!$B$6:$B$605,"SMH",交易记录!$C$6:$C$605,"买入") -> 0 | I69: =SUM(F69:H69) -> 0 | J69: =IF(I69=0,"",I69-B69) | K69: =IF(I69=0,"尚未记录买入",IF(ABS(J69)<0.01,"已记录预算金额","已记录，金额有差额")) -> 尚未记录买入
A70: =DATE(2032,2,总览!$E$4) -> 48254 | B70: =回撤计划!J73 -> 500 | C70: =B70*总览!$B$8 -> 450 | D70: =B70*总览!$B$9 -> 50 | E70: =B70*总览!$B$10 -> 0 | F70: =SUMIFS(交易记录!$D$6:$D$605,交易记录!$A$6:$A$605,">="&DATE(YEAR(A70),MONTH(A70),1),交易记录!$A$6:$A$605,"<"&DATE(YEAR(A70),MONTH(A70)+1,1),交易记录!$B$6:$B$605,"VOO",交易记录!$C$6:$C$605,"买入")+SUMIFS(交易记录!$E$6:$E$605,交易记录!$A$6:$A$605,">="&DATE(YEAR(A70),MONTH(A70),1),交易记录!$A$6:$A$605,"<"&DATE(YEAR(A70),MONTH(A70)+1,1),交易记录!$B$6:$B$605,"VOO",交易记录!$C$6:$C$605,"买入") -> 0 | G70: =SUMIFS(交易记录!$D$6:$D$605,交易记录!$A$6:$A$605,">="&DATE(YEAR(A70),MONTH(A70),1),交易记录!$A$6:$A$605,"<"&DATE(YEAR(A70),MONTH(A70)+1,1),交易记录!$B$6:$B$605,"QQQM",交易记录!$C$6:$C$605,"买入")+SUMIFS(交易记录!$E$6:$E$605,交易记录!$A$6:$A$605,">="&DATE(YEAR(A70),MONTH(A70),1),交易记录!$A$6:$A$605,"<"&DATE(YEAR(A70),MONTH(A70)+1,1),交易记录!$B$6:$B$605,"QQQM",交易记录!$C$6:$C$605,"买入") -> 0 | H70: =SUMIFS(交易记录!$D$6:$D$605,交易记录!$A$6:$A$605,">="&DATE(YEAR(A70),MONTH(A70),1),交易记录!$A$6:$A$605,"<"&DATE(YEAR(A70),MONTH(A70)+1,1),交易记录!$B$6:$B$605,"SMH",交易记录!$C$6:$C$605,"买入")+SUMIFS(交易记录!$E$6:$E$605,交易记录!$A$6:$A$605,">="&DATE(YEAR(A70),MONTH(A70),1),交易记录!$A$6:$A$605,"<"&DATE(YEAR(A70),MONTH(A70)+1,1),交易记录!$B$6:$B$605,"SMH",交易记录!$C$6:$C$605,"买入") -> 0 | I70: =SUM(F70:H70) -> 0 | J70: =IF(I70=0,"",I70-B70) | K70: =IF(I70=0,"尚未记录买入",IF(ABS(J70)<0.01,"已记录预算金额","已记录，金额有差额")) -> 尚未记录买入
A71: =DATE(2032,3,总览!$E$4) -> 48283 | B71: =回撤计划!J74 -> 500 | C71: =B71*总览!$B$8 -> 450 | D71: =B71*总览!$B$9 -> 50 | E71: =B71*总览!$B$10 -> 0 | F71: =SUMIFS(交易记录!$D$6:$D$605,交易记录!$A$6:$A$605,">="&DATE(YEAR(A71),MONTH(A71),1),交易记录!$A$6:$A$605,"<"&DATE(YEAR(A71),MONTH(A71)+1,1),交易记录!$B$6:$B$605,"VOO",交易记录!$C$6:$C$605,"买入")+SUMIFS(交易记录!$E$6:$E$605,交易记录!$A$6:$A$605,">="&DATE(YEAR(A71),MONTH(A71),1),交易记录!$A$6:$A$605,"<"&DATE(YEAR(A71),MONTH(A71)+1,1),交易记录!$B$6:$B$605,"VOO",交易记录!$C$6:$C$605,"买入") -> 0 | G71: =SUMIFS(交易记录!$D$6:$D$605,交易记录!$A$6:$A$605,">="&DATE(YEAR(A71),MONTH(A71),1),交易记录!$A$6:$A$605,"<"&DATE(YEAR(A71),MONTH(A71)+1,1),交易记录!$B$6:$B$605,"QQQM",交易记录!$C$6:$C$605,"买入")+SUMIFS(交易记录!$E$6:$E$605,交易记录!$A$6:$A$605,">="&DATE(YEAR(A71),MONTH(A71),1),交易记录!$A$6:$A$605,"<"&DATE(YEAR(A71),MONTH(A71)+1,1),交易记录!$B$6:$B$605,"QQQM",交易记录!$C$6:$C$605,"买入") -> 0 | H71: =SUMIFS(交易记录!$D$6:$D$605,交易记录!$A$6:$A$605,">="&DATE(YEAR(A71),MONTH(A71),1),交易记录!$A$6:$A$605,"<"&DATE(YEAR(A71),MONTH(A71)+1,1),交易记录!$B$6:$B$605,"SMH",交易记录!$C$6:$C$605,"买入")+SUMIFS(交易记录!$E$6:$E$605,交易记录!$A$6:$A$605,">="&DATE(YEAR(A71),MONTH(A71),1),交易记录!$A$6:$A$605,"<"&DATE(YEAR(A71),MONTH(A71)+1,1),交易记录!$B$6:$B$605,"SMH",交易记录!$C$6:$C$605,"买入") -> 0 | I71: =SUM(F71:H71) -> 0 | J71: =IF(I71=0,"",I71-B71) | K71: =IF(I71=0,"尚未记录买入",IF(ABS(J71)<0.01,"已记录预算金额","已记录，金额有差额")) -> 尚未记录买入
A72: =DATE(2032,4,总览!$E$4) -> 48314 | B72: =回撤计划!J75 -> 500 | C72: =B72*总览!$B$8 -> 450 | D72: =B72*总览!$B$9 -> 50 | E72: =B72*总览!$B$10 -> 0 | F72: =SUMIFS(交易记录!$D$6:$D$605,交易记录!$A$6:$A$605,">="&DATE(YEAR(A72),MONTH(A72),1),交易记录!$A$6:$A$605,"<"&DATE(YEAR(A72),MONTH(A72)+1,1),交易记录!$B$6:$B$605,"VOO",交易记录!$C$6:$C$605,"买入")+SUMIFS(交易记录!$E$6:$E$605,交易记录!$A$6:$A$605,">="&DATE(YEAR(A72),MONTH(A72),1),交易记录!$A$6:$A$605,"<"&DATE(YEAR(A72),MONTH(A72)+1,1),交易记录!$B$6:$B$605,"VOO",交易记录!$C$6:$C$605,"买入") -> 0 | G72: =SUMIFS(交易记录!$D$6:$D$605,交易记录!$A$6:$A$605,">="&DATE(YEAR(A72),MONTH(A72),1),交易记录!$A$6:$A$605,"<"&DATE(YEAR(A72),MONTH(A72)+1,1),交易记录!$B$6:$B$605,"QQQM",交易记录!$C$6:$C$605,"买入")+SUMIFS(交易记录!$E$6:$E$605,交易记录!$A$6:$A$605,">="&DATE(YEAR(A72),MONTH(A72),1),交易记录!$A$6:$A$605,"<"&DATE(YEAR(A72),MONTH(A72)+1,1),交易记录!$B$6:$B$605,"QQQM",交易记录!$C$6:$C$605,"买入") -> 0 | H72: =SUMIFS(交易记录!$D$6:$D$605,交易记录!$A$6:$A$605,">="&DATE(YEAR(A72),MONTH(A72),1),交易记录!$A$6:$A$605,"<"&DATE(YEAR(A72),MONTH(A72)+1,1),交易记录!$B$6:$B$605,"SMH",交易记录!$C$6:$C$605,"买入")+SUMIFS(交易记录!$E$6:$E$605,交易记录!$A$6:$A$605,">="&DATE(YEAR(A72),MONTH(A72),1),交易记录!$A$6:$A$605,"<"&DATE(YEAR(A72),MONTH(A72)+1,1),交易记录!$B$6:$B$605,"SMH",交易记录!$C$6:$C$605,"买入") -> 0 | I72: =SUM(F72:H72) -> 0 | J72: =IF(I72=0,"",I72-B72) | K72: =IF(I72=0,"尚未记录买入",IF(ABS(J72)<0.01,"已记录预算金额","已记录，金额有差额")) -> 尚未记录买入
A73: =DATE(2032,5,总览!$E$4) -> 48344 | B73: =回撤计划!J76 -> 500 | C73: =B73*总览!$B$8 -> 450 | D73: =B73*总览!$B$9 -> 50 | E73: =B73*总览!$B$10 -> 0 | F73: =SUMIFS(交易记录!$D$6:$D$605,交易记录!$A$6:$A$605,">="&DATE(YEAR(A73),MONTH(A73),1),交易记录!$A$6:$A$605,"<"&DATE(YEAR(A73),MONTH(A73)+1,1),交易记录!$B$6:$B$605,"VOO",交易记录!$C$6:$C$605,"买入")+SUMIFS(交易记录!$E$6:$E$605,交易记录!$A$6:$A$605,">="&DATE(YEAR(A73),MONTH(A73),1),交易记录!$A$6:$A$605,"<"&DATE(YEAR(A73),MONTH(A73)+1,1),交易记录!$B$6:$B$605,"VOO",交易记录!$C$6:$C$605,"买入") -> 0 | G73: =SUMIFS(交易记录!$D$6:$D$605,交易记录!$A$6:$A$605,">="&DATE(YEAR(A73),MONTH(A73),1),交易记录!$A$6:$A$605,"<"&DATE(YEAR(A73),MONTH(A73)+1,1),交易记录!$B$6:$B$605,"QQQM",交易记录!$C$6:$C$605,"买入")+SUMIFS(交易记录!$E$6:$E$605,交易记录!$A$6:$A$605,">="&DATE(YEAR(A73),MONTH(A73),1),交易记录!$A$6:$A$605,"<"&DATE(YEAR(A73),MONTH(A73)+1,1),交易记录!$B$6:$B$605,"QQQM",交易记录!$C$6:$C$605,"买入") -> 0 | H73: =SUMIFS(交易记录!$D$6:$D$605,交易记录!$A$6:$A$605,">="&DATE(YEAR(A73),MONTH(A73),1),交易记录!$A$6:$A$605,"<"&DATE(YEAR(A73),MONTH(A73)+1,1),交易记录!$B$6:$B$605,"SMH",交易记录!$C$6:$C$605,"买入")+SUMIFS(交易记录!$E$6:$E$605,交易记录!$A$6:$A$605,">="&DATE(YEAR(A73),MONTH(A73),1),交易记录!$A$6:$A$605,"<"&DATE(YEAR(A73),MONTH(A73)+1,1),交易记录!$B$6:$B$605,"SMH",交易记录!$C$6:$C$605,"买入") -> 0 | I73: =SUM(F73:H73) -> 0 | J73: =IF(I73=0,"",I73-B73) | K73: =IF(I73=0,"尚未记录买入",IF(ABS(J73)<0.01,"已记录预算金额","已记录，金额有差额")) -> 尚未记录买入
A74: =DATE(2032,6,总览!$E$4) -> 48375 | B74: =回撤计划!J77 -> 500 | C74: =B74*总览!$B$8 -> 450 | D74: =B74*总览!$B$9 -> 50 | E74: =B74*总览!$B$10 -> 0 | F74: =SUMIFS(交易记录!$D$6:$D$605,交易记录!$A$6:$A$605,">="&DATE(YEAR(A74),MONTH(A74),1),交易记录!$A$6:$A$605,"<"&DATE(YEAR(A74),MONTH(A74)+1,1),交易记录!$B$6:$B$605,"VOO",交易记录!$C$6:$C$605,"买入")+SUMIFS(交易记录!$E$6:$E$605,交易记录!$A$6:$A$605,">="&DATE(YEAR(A74),MONTH(A74),1),交易记录!$A$6:$A$605,"<"&DATE(YEAR(A74),MONTH(A74)+1,1),交易记录!$B$6:$B$605,"VOO",交易记录!$C$6:$C$605,"买入") -> 0 | G74: =SUMIFS(交易记录!$D$6:$D$605,交易记录!$A$6:$A$605,">="&DATE(YEAR(A74),MONTH(A74),1),交易记录!$A$6:$A$605,"<"&DATE(YEAR(A74),MONTH(A74)+1,1),交易记录!$B$6:$B$605,"QQQM",交易记录!$C$6:$C$605,"买入")+SUMIFS(交易记录!$E$6:$E$605,交易记录!$A$6:$A$605,">="&DATE(YEAR(A74),MONTH(A74),1),交易记录!$A$6:$A$605,"<"&DATE(YEAR(A74),MONTH(A74)+1,1),交易记录!$B$6:$B$605,"QQQM",交易记录!$C$6:$C$605,"买入") -> 0 | H74: =SUMIFS(交易记录!$D$6:$D$605,交易记录!$A$6:$A$605,">="&DATE(YEAR(A74),MONTH(A74),1),交易记录!$A$6:$A$605,"<"&DATE(YEAR(A74),MONTH(A74)+1,1),交易记录!$B$6:$B$605,"SMH",交易记录!$C$6:$C$605,"买入")+SUMIFS(交易记录!$E$6:$E$605,交易记录!$A$6:$A$605,">="&DATE(YEAR(A74),MONTH(A74),1),交易记录!$A$6:$A$605,"<"&DATE(YEAR(A74),MONTH(A74)+1,1),交易记录!$B$6:$B$605,"SMH",交易记录!$C$6:$C$605,"买入") -> 0 | I74: =SUM(F74:H74) -> 0 | J74: =IF(I74=0,"",I74-B74) | K74: =IF(I74=0,"尚未记录买入",IF(ABS(J74)<0.01,"已记录预算金额","已记录，金额有差额")) -> 尚未记录买入
A75: =DATE(2032,7,总览!$E$4) -> 48405 | B75: =回撤计划!J78 -> 500 | C75: =B75*总览!$B$8 -> 450 | D75: =B75*总览!$B$9 -> 50 | E75: =B75*总览!$B$10 -> 0 | F75: =SUMIFS(交易记录!$D$6:$D$605,交易记录!$A$6:$A$605,">="&DATE(YEAR(A75),MONTH(A75),1),交易记录!$A$6:$A$605,"<"&DATE(YEAR(A75),MONTH(A75)+1,1),交易记录!$B$6:$B$605,"VOO",交易记录!$C$6:$C$605,"买入")+SUMIFS(交易记录!$E$6:$E$605,交易记录!$A$6:$A$605,">="&DATE(YEAR(A75),MONTH(A75),1),交易记录!$A$6:$A$605,"<"&DATE(YEAR(A75),MONTH(A75)+1,1),交易记录!$B$6:$B$605,"VOO",交易记录!$C$6:$C$605,"买入") -> 0 | G75: =SUMIFS(交易记录!$D$6:$D$605,交易记录!$A$6:$A$605,">="&DATE(YEAR(A75),MONTH(A75),1),交易记录!$A$6:$A$605,"<"&DATE(YEAR(A75),MONTH(A75)+1,1),交易记录!$B$6:$B$605,"QQQM",交易记录!$C$6:$C$605,"买入")+SUMIFS(交易记录!$E$6:$E$605,交易记录!$A$6:$A$605,">="&DATE(YEAR(A75),MONTH(A75),1),交易记录!$A$6:$A$605,"<"&DATE(YEAR(A75),MONTH(A75)+1,1),交易记录!$B$6:$B$605,"QQQM",交易记录!$C$6:$C$605,"买入") -> 0 | H75: =SUMIFS(交易记录!$D$6:$D$605,交易记录!$A$6:$A$605,">="&DATE(YEAR(A75),MONTH(A75),1),交易记录!$A$6:$A$605,"<"&DATE(YEAR(A75),MONTH(A75)+1,1),交易记录!$B$6:$B$605,"SMH",交易记录!$C$6:$C$605,"买入")+SUMIFS(交易记录!$E$6:$E$605,交易记录!$A$6:$A$605,">="&DATE(YEAR(A75),MONTH(A75),1),交易记录!$A$6:$A$605,"<"&DATE(YEAR(A75),MONTH(A75)+1,1),交易记录!$B$6:$B$605,"SMH",交易记录!$C$6:$C$605,"买入") -> 0 | I75: =SUM(F75:H75) -> 0 | J75: =IF(I75=0,"",I75-B75) | K75: =IF(I75=0,"尚未记录买入",IF(ABS(J75)<0.01,"已记录预算金额","已记录，金额有差额")) -> 尚未记录买入
A76: =DATE(2032,8,总览!$E$4) -> 48436 | B76: =回撤计划!J79 -> 500 | C76: =B76*总览!$B$8 -> 450 | D76: =B76*总览!$B$9 -> 50 | E76: =B76*总览!$B$10 -> 0 | F76: =SUMIFS(交易记录!$D$6:$D$605,交易记录!$A$6:$A$605,">="&DATE(YEAR(A76),MONTH(A76),1),交易记录!$A$6:$A$605,"<"&DATE(YEAR(A76),MONTH(A76)+1,1),交易记录!$B$6:$B$605,"VOO",交易记录!$C$6:$C$605,"买入")+SUMIFS(交易记录!$E$6:$E$605,交易记录!$A$6:$A$605,">="&DATE(YEAR(A76),MONTH(A76),1),交易记录!$A$6:$A$605,"<"&DATE(YEAR(A76),MONTH(A76)+1,1),交易记录!$B$6:$B$605,"VOO",交易记录!$C$6:$C$605,"买入") -> 0 | G76: =SUMIFS(交易记录!$D$6:$D$605,交易记录!$A$6:$A$605,">="&DATE(YEAR(A76),MONTH(A76),1),交易记录!$A$6:$A$605,"<"&DATE(YEAR(A76),MONTH(A76)+1,1),交易记录!$B$6:$B$605,"QQQM",交易记录!$C$6:$C$605,"买入")+SUMIFS(交易记录!$E$6:$E$605,交易记录!$A$6:$A$605,">="&DATE(YEAR(A76),MONTH(A76),1),交易记录!$A$6:$A$605,"<"&DATE(YEAR(A76),MONTH(A76)+1,1),交易记录!$B$6:$B$605,"QQQM",交易记录!$C$6:$C$605,"买入") -> 0 | H76: =SUMIFS(交易记录!$D$6:$D$605,交易记录!$A$6:$A$605,">="&DATE(YEAR(A76),MONTH(A76),1),交易记录!$A$6:$A$605,"<"&DATE(YEAR(A76),MONTH(A76)+1,1),交易记录!$B$6:$B$605,"SMH",交易记录!$C$6:$C$605,"买入")+SUMIFS(交易记录!$E$6:$E$605,交易记录!$A$6:$A$605,">="&DATE(YEAR(A76),MONTH(A76),1),交易记录!$A$6:$A$605,"<"&DATE(YEAR(A76),MONTH(A76)+1,1),交易记录!$B$6:$B$605,"SMH",交易记录!$C$6:$C$605,"买入") -> 0 | I76: =SUM(F76:H76) -> 0 | J76: =IF(I76=0,"",I76-B76) | K76: =IF(I76=0,"尚未记录买入",IF(ABS(J76)<0.01,"已记录预算金额","已记录，金额有差额")) -> 尚未记录买入
A77: =DATE(2032,9,总览!$E$4) -> 48467 | B77: =回撤计划!J80 -> 500 | C77: =B77*总览!$B$8 -> 450 | D77: =B77*总览!$B$9 -> 50 | E77: =B77*总览!$B$10 -> 0 | F77: =SUMIFS(交易记录!$D$6:$D$605,交易记录!$A$6:$A$605,">="&DATE(YEAR(A77),MONTH(A77),1),交易记录!$A$6:$A$605,"<"&DATE(YEAR(A77),MONTH(A77)+1,1),交易记录!$B$6:$B$605,"VOO",交易记录!$C$6:$C$605,"买入")+SUMIFS(交易记录!$E$6:$E$605,交易记录!$A$6:$A$605,">="&DATE(YEAR(A77),MONTH(A77),1),交易记录!$A$6:$A$605,"<"&DATE(YEAR(A77),MONTH(A77)+1,1),交易记录!$B$6:$B$605,"VOO",交易记录!$C$6:$C$605,"买入") -> 0 | G77: =SUMIFS(交易记录!$D$6:$D$605,交易记录!$A$6:$A$605,">="&DATE(YEAR(A77),MONTH(A77),1),交易记录!$A$6:$A$605,"<"&DATE(YEAR(A77),MONTH(A77)+1,1),交易记录!$B$6:$B$605,"QQQM",交易记录!$C$6:$C$605,"买入")+SUMIFS(交易记录!$E$6:$E$605,交易记录!$A$6:$A$605,">="&DATE(YEAR(A77),MONTH(A77),1),交易记录!$A$6:$A$605,"<"&DATE(YEAR(A77),MONTH(A77)+1,1),交易记录!$B$6:$B$605,"QQQM",交易记录!$C$6:$C$605,"买入") -> 0 | H77: =SUMIFS(交易记录!$D$6:$D$605,交易记录!$A$6:$A$605,">="&DATE(YEAR(A77),MONTH(A77),1),交易记录!$A$6:$A$605,"<"&DATE(YEAR(A77),MONTH(A77)+1,1),交易记录!$B$6:$B$605,"SMH",交易记录!$C$6:$C$605,"买入")+SUMIFS(交易记录!$E$6:$E$605,交易记录!$A$6:$A$605,">="&DATE(YEAR(A77),MONTH(A77),1),交易记录!$A$6:$A$605,"<"&DATE(YEAR(A77),MONTH(A77)+1,1),交易记录!$B$6:$B$605,"SMH",交易记录!$C$6:$C$605,"买入") -> 0 | I77: =SUM(F77:H77) -> 0 | J77: =IF(I77=0,"",I77-B77) | K77: =IF(I77=0,"尚未记录买入",IF(ABS(J77)<0.01,"已记录预算金额","已记录，金额有差额")) -> 尚未记录买入
A78: =DATE(2032,10,总览!$E$4) -> 48497 | B78: =回撤计划!J81 -> 500 | C78: =B78*总览!$B$8 -> 450 | D78: =B78*总览!$B$9 -> 50 | E78: =B78*总览!$B$10 -> 0 | F78: =SUMIFS(交易记录!$D$6:$D$605,交易记录!$A$6:$A$605,">="&DATE(YEAR(A78),MONTH(A78),1),交易记录!$A$6:$A$605,"<"&DATE(YEAR(A78),MONTH(A78)+1,1),交易记录!$B$6:$B$605,"VOO",交易记录!$C$6:$C$605,"买入")+SUMIFS(交易记录!$E$6:$E$605,交易记录!$A$6:$A$605,">="&DATE(YEAR(A78),MONTH(A78),1),交易记录!$A$6:$A$605,"<"&DATE(YEAR(A78),MONTH(A78)+1,1),交易记录!$B$6:$B$605,"VOO",交易记录!$C$6:$C$605,"买入") -> 0 | G78: =SUMIFS(交易记录!$D$6:$D$605,交易记录!$A$6:$A$605,">="&DATE(YEAR(A78),MONTH(A78),1),交易记录!$A$6:$A$605,"<"&DATE(YEAR(A78),MONTH(A78)+1,1),交易记录!$B$6:$B$605,"QQQM",交易记录!$C$6:$C$605,"买入")+SUMIFS(交易记录!$E$6:$E$605,交易记录!$A$6:$A$605,">="&DATE(YEAR(A78),MONTH(A78),1),交易记录!$A$6:$A$605,"<"&DATE(YEAR(A78),MONTH(A78)+1,1),交易记录!$B$6:$B$605,"QQQM",交易记录!$C$6:$C$605,"买入") -> 0 | H78: =SUMIFS(交易记录!$D$6:$D$605,交易记录!$A$6:$A$605,">="&DATE(YEAR(A78),MONTH(A78),1),交易记录!$A$6:$A$605,"<"&DATE(YEAR(A78),MONTH(A78)+1,1),交易记录!$B$6:$B$605,"SMH",交易记录!$C$6:$C$605,"买入")+SUMIFS(交易记录!$E$6:$E$605,交易记录!$A$6:$A$605,">="&DATE(YEAR(A78),MONTH(A78),1),交易记录!$A$6:$A$605,"<"&DATE(YEAR(A78),MONTH(A78)+1,1),交易记录!$B$6:$B$605,"SMH",交易记录!$C$6:$C$605,"买入") -> 0 | I78: =SUM(F78:H78) -> 0 | J78: =IF(I78=0,"",I78-B78) | K78: =IF(I78=0,"尚未记录买入",IF(ABS(J78)<0.01,"已记录预算金额","已记录，金额有差额")) -> 尚未记录买入
A79: =DATE(2032,11,总览!$E$4) -> 48528 | B79: =回撤计划!J82 -> 500 | C79: =B79*总览!$B$8 -> 450 | D79: =B79*总览!$B$9 -> 50 | E79: =B79*总览!$B$10 -> 0 | F79: =SUMIFS(交易记录!$D$6:$D$605,交易记录!$A$6:$A$605,">="&DATE(YEAR(A79),MONTH(A79),1),交易记录!$A$6:$A$605,"<"&DATE(YEAR(A79),MONTH(A79)+1,1),交易记录!$B$6:$B$605,"VOO",交易记录!$C$6:$C$605,"买入")+SUMIFS(交易记录!$E$6:$E$605,交易记录!$A$6:$A$605,">="&DATE(YEAR(A79),MONTH(A79),1),交易记录!$A$6:$A$605,"<"&DATE(YEAR(A79),MONTH(A79)+1,1),交易记录!$B$6:$B$605,"VOO",交易记录!$C$6:$C$605,"买入") -> 0 | G79: =SUMIFS(交易记录!$D$6:$D$605,交易记录!$A$6:$A$605,">="&DATE(YEAR(A79),MONTH(A79),1),交易记录!$A$6:$A$605,"<"&DATE(YEAR(A79),MONTH(A79)+1,1),交易记录!$B$6:$B$605,"QQQM",交易记录!$C$6:$C$605,"买入")+SUMIFS(交易记录!$E$6:$E$605,交易记录!$A$6:$A$605,">="&DATE(YEAR(A79),MONTH(A79),1),交易记录!$A$6:$A$605,"<"&DATE(YEAR(A79),MONTH(A79)+1,1),交易记录!$B$6:$B$605,"QQQM",交易记录!$C$6:$C$605,"买入") -> 0 | H79: =SUMIFS(交易记录!$D$6:$D$605,交易记录!$A$6:$A$605,">="&DATE(YEAR(A79),MONTH(A79),1),交易记录!$A$6:$A$605,"<"&DATE(YEAR(A79),MONTH(A79)+1,1),交易记录!$B$6:$B$605,"SMH",交易记录!$C$6:$C$605,"买入")+SUMIFS(交易记录!$E$6:$E$605,交易记录!$A$6:$A$605,">="&DATE(YEAR(A79),MONTH(A79),1),交易记录!$A$6:$A$605,"<"&DATE(YEAR(A79),MONTH(A79)+1,1),交易记录!$B$6:$B$605,"SMH",交易记录!$C$6:$C$605,"买入") -> 0 | I79: =SUM(F79:H79) -> 0 | J79: =IF(I79=0,"",I79-B79) | K79: =IF(I79=0,"尚未记录买入",IF(ABS(J79)<0.01,"已记录预算金额","已记录，金额有差额")) -> 尚未记录买入
A80: =DATE(2032,12,总览!$E$4) -> 48558 | B80: =回撤计划!J83 -> 500 | C80: =B80*总览!$B$8 -> 450 | D80: =B80*总览!$B$9 -> 50 | E80: =B80*总览!$B$10 -> 0 | F80: =SUMIFS(交易记录!$D$6:$D$605,交易记录!$A$6:$A$605,">="&DATE(YEAR(A80),MONTH(A80),1),交易记录!$A$6:$A$605,"<"&DATE(YEAR(A80),MONTH(A80)+1,1),交易记录!$B$6:$B$605,"VOO",交易记录!$C$6:$C$605,"买入")+SUMIFS(交易记录!$E$6:$E$605,交易记录!$A$6:$A$605,">="&DATE(YEAR(A80),MONTH(A80),1),交易记录!$A$6:$A$605,"<"&DATE(YEAR(A80),MONTH(A80)+1,1),交易记录!$B$6:$B$605,"VOO",交易记录!$C$6:$C$605,"买入") -> 0 | G80: =SUMIFS(交易记录!$D$6:$D$605,交易记录!$A$6:$A$605,">="&DATE(YEAR(A80),MONTH(A80),1),交易记录!$A$6:$A$605,"<"&DATE(YEAR(A80),MONTH(A80)+1,1),交易记录!$B$6:$B$605,"QQQM",交易记录!$C$6:$C$605,"买入")+SUMIFS(交易记录!$E$6:$E$605,交易记录!$A$6:$A$605,">="&DATE(YEAR(A80),MONTH(A80),1),交易记录!$A$6:$A$605,"<"&DATE(YEAR(A80),MONTH(A80)+1,1),交易记录!$B$6:$B$605,"QQQM",交易记录!$C$6:$C$605,"买入") -> 0 | H80: =SUMIFS(交易记录!$D$6:$D$605,交易记录!$A$6:$A$605,">="&DATE(YEAR(A80),MONTH(A80),1),交易记录!$A$6:$A$605,"<"&DATE(YEAR(A80),MONTH(A80)+1,1),交易记录!$B$6:$B$605,"SMH",交易记录!$C$6:$C$605,"买入")+SUMIFS(交易记录!$E$6:$E$605,交易记录!$A$6:$A$605,">="&DATE(YEAR(A80),MONTH(A80),1),交易记录!$A$6:$A$605,"<"&DATE(YEAR(A80),MONTH(A80)+1,1),交易记录!$B$6:$B$605,"SMH",交易记录!$C$6:$C$605,"买入") -> 0 | I80: =SUM(F80:H80) -> 0 | J80: =IF(I80=0,"",I80-B80) | K80: =IF(I80=0,"尚未记录买入",IF(ABS(J80)<0.01,"已记录预算金额","已记录，金额有差额")) -> 尚未记录买入
A81: =DATE(2033,1,总览!$E$4) -> 48589 | B81: =回撤计划!J84 -> 500 | C81: =B81*总览!$B$8 -> 450 | D81: =B81*总览!$B$9 -> 50 | E81: =B81*总览!$B$10 -> 0 | F81: =SUMIFS(交易记录!$D$6:$D$605,交易记录!$A$6:$A$605,">="&DATE(YEAR(A81),MONTH(A81),1),交易记录!$A$6:$A$605,"<"&DATE(YEAR(A81),MONTH(A81)+1,1),交易记录!$B$6:$B$605,"VOO",交易记录!$C$6:$C$605,"买入")+SUMIFS(交易记录!$E$6:$E$605,交易记录!$A$6:$A$605,">="&DATE(YEAR(A81),MONTH(A81),1),交易记录!$A$6:$A$605,"<"&DATE(YEAR(A81),MONTH(A81)+1,1),交易记录!$B$6:$B$605,"VOO",交易记录!$C$6:$C$605,"买入") -> 0 | G81: =SUMIFS(交易记录!$D$6:$D$605,交易记录!$A$6:$A$605,">="&DATE(YEAR(A81),MONTH(A81),1),交易记录!$A$6:$A$605,"<"&DATE(YEAR(A81),MONTH(A81)+1,1),交易记录!$B$6:$B$605,"QQQM",交易记录!$C$6:$C$605,"买入")+SUMIFS(交易记录!$E$6:$E$605,交易记录!$A$6:$A$605,">="&DATE(YEAR(A81),MONTH(A81),1),交易记录!$A$6:$A$605,"<"&DATE(YEAR(A81),MONTH(A81)+1,1),交易记录!$B$6:$B$605,"QQQM",交易记录!$C$6:$C$605,"买入") -> 0 | H81: =SUMIFS(交易记录!$D$6:$D$605,交易记录!$A$6:$A$605,">="&DATE(YEAR(A81),MONTH(A81),1),交易记录!$A$6:$A$605,"<"&DATE(YEAR(A81),MONTH(A81)+1,1),交易记录!$B$6:$B$605,"SMH",交易记录!$C$6:$C$605,"买入")+SUMIFS(交易记录!$E$6:$E$605,交易记录!$A$6:$A$605,">="&DATE(YEAR(A81),MONTH(A81),1),交易记录!$A$6:$A$605,"<"&DATE(YEAR(A81),MONTH(A81)+1,1),交易记录!$B$6:$B$605,"SMH",交易记录!$C$6:$C$605,"买入") -> 0 | I81: =SUM(F81:H81) -> 0 | J81: =IF(I81=0,"",I81-B81) | K81: =IF(I81=0,"尚未记录买入",IF(ABS(J81)<0.01,"已记录预算金额","已记录，金额有差额")) -> 尚未记录买入
A82: =DATE(2033,2,总览!$E$4) -> 48620 | B82: =回撤计划!J85 -> 500 | C82: =B82*总览!$B$8 -> 450 | D82: =B82*总览!$B$9 -> 50 | E82: =B82*总览!$B$10 -> 0 | F82: =SUMIFS(交易记录!$D$6:$D$605,交易记录!$A$6:$A$605,">="&DATE(YEAR(A82),MONTH(A82),1),交易记录!$A$6:$A$605,"<"&DATE(YEAR(A82),MONTH(A82)+1,1),交易记录!$B$6:$B$605,"VOO",交易记录!$C$6:$C$605,"买入")+SUMIFS(交易记录!$E$6:$E$605,交易记录!$A$6:$A$605,">="&DATE(YEAR(A82),MONTH(A82),1),交易记录!$A$6:$A$605,"<"&DATE(YEAR(A82),MONTH(A82)+1,1),交易记录!$B$6:$B$605,"VOO",交易记录!$C$6:$C$605,"买入") -> 0 | G82: =SUMIFS(交易记录!$D$6:$D$605,交易记录!$A$6:$A$605,">="&DATE(YEAR(A82),MONTH(A82),1),交易记录!$A$6:$A$605,"<"&DATE(YEAR(A82),MONTH(A82)+1,1),交易记录!$B$6:$B$605,"QQQM",交易记录!$C$6:$C$605,"买入")+SUMIFS(交易记录!$E$6:$E$605,交易记录!$A$6:$A$605,">="&DATE(YEAR(A82),MONTH(A82),1),交易记录!$A$6:$A$605,"<"&DATE(YEAR(A82),MONTH(A82)+1,1),交易记录!$B$6:$B$605,"QQQM",交易记录!$C$6:$C$605,"买入") -> 0 | H82: =SUMIFS(交易记录!$D$6:$D$605,交易记录!$A$6:$A$605,">="&DATE(YEAR(A82),MONTH(A82),1),交易记录!$A$6:$A$605,"<"&DATE(YEAR(A82),MONTH(A82)+1,1),交易记录!$B$6:$B$605,"SMH",交易记录!$C$6:$C$605,"买入")+SUMIFS(交易记录!$E$6:$E$605,交易记录!$A$6:$A$605,">="&DATE(YEAR(A82),MONTH(A82),1),交易记录!$A$6:$A$605,"<"&DATE(YEAR(A82),MONTH(A82)+1,1),交易记录!$B$6:$B$605,"SMH",交易记录!$C$6:$C$605,"买入") -> 0 | I82: =SUM(F82:H82) -> 0 | J82: =IF(I82=0,"",I82-B82) | K82: =IF(I82=0,"尚未记录买入",IF(ABS(J82)<0.01,"已记录预算金额","已记录，金额有差额")) -> 尚未记录买入
A83: =DATE(2033,3,总览!$E$4) -> 48648 | B83: =回撤计划!J86 -> 500 | C83: =B83*总览!$B$8 -> 450 | D83: =B83*总览!$B$9 -> 50 | E83: =B83*总览!$B$10 -> 0 | F83: =SUMIFS(交易记录!$D$6:$D$605,交易记录!$A$6:$A$605,">="&DATE(YEAR(A83),MONTH(A83),1),交易记录!$A$6:$A$605,"<"&DATE(YEAR(A83),MONTH(A83)+1,1),交易记录!$B$6:$B$605,"VOO",交易记录!$C$6:$C$605,"买入")+SUMIFS(交易记录!$E$6:$E$605,交易记录!$A$6:$A$605,">="&DATE(YEAR(A83),MONTH(A83),1),交易记录!$A$6:$A$605,"<"&DATE(YEAR(A83),MONTH(A83)+1,1),交易记录!$B$6:$B$605,"VOO",交易记录!$C$6:$C$605,"买入") -> 0 | G83: =SUMIFS(交易记录!$D$6:$D$605,交易记录!$A$6:$A$605,">="&DATE(YEAR(A83),MONTH(A83),1),交易记录!$A$6:$A$605,"<"&DATE(YEAR(A83),MONTH(A83)+1,1),交易记录!$B$6:$B$605,"QQQM",交易记录!$C$6:$C$605,"买入")+SUMIFS(交易记录!$E$6:$E$605,交易记录!$A$6:$A$605,">="&DATE(YEAR(A83),MONTH(A83),1),交易记录!$A$6:$A$605,"<"&DATE(YEAR(A83),MONTH(A83)+1,1),交易记录!$B$6:$B$605,"QQQM",交易记录!$C$6:$C$605,"买入") -> 0 | H83: =SUMIFS(交易记录!$D$6:$D$605,交易记录!$A$6:$A$605,">="&DATE(YEAR(A83),MONTH(A83),1),交易记录!$A$6:$A$605,"<"&DATE(YEAR(A83),MONTH(A83)+1,1),交易记录!$B$6:$B$605,"SMH",交易记录!$C$6:$C$605,"买入")+SUMIFS(交易记录!$E$6:$E$605,交易记录!$A$6:$A$605,">="&DATE(YEAR(A83),MONTH(A83),1),交易记录!$A$6:$A$605,"<"&DATE(YEAR(A83),MONTH(A83)+1,1),交易记录!$B$6:$B$605,"SMH",交易记录!$C$6:$C$605,"买入") -> 0 | I83: =SUM(F83:H83) -> 0 | J83: =IF(I83=0,"",I83-B83) | K83: =IF(I83=0,"尚未记录买入",IF(ABS(J83)<0.01,"已记录预算金额","已记录，金额有差额")) -> 尚未记录买入
A84: =DATE(2033,4,总览!$E$4) -> 48679 | B84: =回撤计划!J87 -> 500 | C84: =B84*总览!$B$8 -> 450 | D84: =B84*总览!$B$9 -> 50 | E84: =B84*总览!$B$10 -> 0 | F84: =SUMIFS(交易记录!$D$6:$D$605,交易记录!$A$6:$A$605,">="&DATE(YEAR(A84),MONTH(A84),1),交易记录!$A$6:$A$605,"<"&DATE(YEAR(A84),MONTH(A84)+1,1),交易记录!$B$6:$B$605,"VOO",交易记录!$C$6:$C$605,"买入")+SUMIFS(交易记录!$E$6:$E$605,交易记录!$A$6:$A$605,">="&DATE(YEAR(A84),MONTH(A84),1),交易记录!$A$6:$A$605,"<"&DATE(YEAR(A84),MONTH(A84)+1,1),交易记录!$B$6:$B$605,"VOO",交易记录!$C$6:$C$605,"买入") -> 0 | G84: =SUMIFS(交易记录!$D$6:$D$605,交易记录!$A$6:$A$605,">="&DATE(YEAR(A84),MONTH(A84),1),交易记录!$A$6:$A$605,"<"&DATE(YEAR(A84),MONTH(A84)+1,1),交易记录!$B$6:$B$605,"QQQM",交易记录!$C$6:$C$605,"买入")+SUMIFS(交易记录!$E$6:$E$605,交易记录!$A$6:$A$605,">="&DATE(YEAR(A84),MONTH(A84),1),交易记录!$A$6:$A$605,"<"&DATE(YEAR(A84),MONTH(A84)+1,1),交易记录!$B$6:$B$605,"QQQM",交易记录!$C$6:$C$605,"买入") -> 0 | H84: =SUMIFS(交易记录!$D$6:$D$605,交易记录!$A$6:$A$605,">="&DATE(YEAR(A84),MONTH(A84),1),交易记录!$A$6:$A$605,"<"&DATE(YEAR(A84),MONTH(A84)+1,1),交易记录!$B$6:$B$605,"SMH",交易记录!$C$6:$C$605,"买入")+SUMIFS(交易记录!$E$6:$E$605,交易记录!$A$6:$A$605,">="&DATE(YEAR(A84),MONTH(A84),1),交易记录!$A$6:$A$605,"<"&DATE(YEAR(A84),MONTH(A84)+1,1),交易记录!$B$6:$B$605,"SMH",交易记录!$C$6:$C$605,"买入") -> 0 | I84: =SUM(F84:H84) -> 0 | J84: =IF(I84=0,"",I84-B84) | K84: =IF(I84=0,"尚未记录买入",IF(ABS(J84)<0.01,"已记录预算金额","已记录，金额有差额")) -> 尚未记录买入
A85: =DATE(2033,5,总览!$E$4) -> 48709 | B85: =回撤计划!J88 -> 500 | C85: =B85*总览!$B$8 -> 450 | D85: =B85*总览!$B$9 -> 50 | E85: =B85*总览!$B$10 -> 0 | F85: =SUMIFS(交易记录!$D$6:$D$605,交易记录!$A$6:$A$605,">="&DATE(YEAR(A85),MONTH(A85),1),交易记录!$A$6:$A$605,"<"&DATE(YEAR(A85),MONTH(A85)+1,1),交易记录!$B$6:$B$605,"VOO",交易记录!$C$6:$C$605,"买入")+SUMIFS(交易记录!$E$6:$E$605,交易记录!$A$6:$A$605,">="&DATE(YEAR(A85),MONTH(A85),1),交易记录!$A$6:$A$605,"<"&DATE(YEAR(A85),MONTH(A85)+1,1),交易记录!$B$6:$B$605,"VOO",交易记录!$C$6:$C$605,"买入") -> 0 | G85: =SUMIFS(交易记录!$D$6:$D$605,交易记录!$A$6:$A$605,">="&DATE(YEAR(A85),MONTH(A85),1),交易记录!$A$6:$A$605,"<"&DATE(YEAR(A85),MONTH(A85)+1,1),交易记录!$B$6:$B$605,"QQQM",交易记录!$C$6:$C$605,"买入")+SUMIFS(交易记录!$E$6:$E$605,交易记录!$A$6:$A$605,">="&DATE(YEAR(A85),MONTH(A85),1),交易记录!$A$6:$A$605,"<"&DATE(YEAR(A85),MONTH(A85)+1,1),交易记录!$B$6:$B$605,"QQQM",交易记录!$C$6:$C$605,"买入") -> 0 | H85: =SUMIFS(交易记录!$D$6:$D$605,交易记录!$A$6:$A$605,">="&DATE(YEAR(A85),MONTH(A85),1),交易记录!$A$6:$A$605,"<"&DATE(YEAR(A85),MONTH(A85)+1,1),交易记录!$B$6:$B$605,"SMH",交易记录!$C$6:$C$605,"买入")+SUMIFS(交易记录!$E$6:$E$605,交易记录!$A$6:$A$605,">="&DATE(YEAR(A85),MONTH(A85),1),交易记录!$A$6:$A$605,"<"&DATE(YEAR(A85),MONTH(A85)+1,1),交易记录!$B$6:$B$605,"SMH",交易记录!$C$6:$C$605,"买入") -> 0 | I85: =SUM(F85:H85) -> 0 | J85: =IF(I85=0,"",I85-B85) | K85: =IF(I85=0,"尚未记录买入",IF(ABS(J85)<0.01,"已记录预算金额","已记录，金额有差额")) -> 尚未记录买入
A86: =DATE(2033,6,总览!$E$4) -> 48740 | B86: =回撤计划!J89 -> 500 | C86: =B86*总览!$B$8 -> 450 | D86: =B86*总览!$B$9 -> 50 | E86: =B86*总览!$B$10 -> 0 | F86: =SUMIFS(交易记录!$D$6:$D$605,交易记录!$A$6:$A$605,">="&DATE(YEAR(A86),MONTH(A86),1),交易记录!$A$6:$A$605,"<"&DATE(YEAR(A86),MONTH(A86)+1,1),交易记录!$B$6:$B$605,"VOO",交易记录!$C$6:$C$605,"买入")+SUMIFS(交易记录!$E$6:$E$605,交易记录!$A$6:$A$605,">="&DATE(YEAR(A86),MONTH(A86),1),交易记录!$A$6:$A$605,"<"&DATE(YEAR(A86),MONTH(A86)+1,1),交易记录!$B$6:$B$605,"VOO",交易记录!$C$6:$C$605,"买入") -> 0 | G86: =SUMIFS(交易记录!$D$6:$D$605,交易记录!$A$6:$A$605,">="&DATE(YEAR(A86),MONTH(A86),1),交易记录!$A$6:$A$605,"<"&DATE(YEAR(A86),MONTH(A86)+1,1),交易记录!$B$6:$B$605,"QQQM",交易记录!$C$6:$C$605,"买入")+SUMIFS(交易记录!$E$6:$E$605,交易记录!$A$6:$A$605,">="&DATE(YEAR(A86),MONTH(A86),1),交易记录!$A$6:$A$605,"<"&DATE(YEAR(A86),MONTH(A86)+1,1),交易记录!$B$6:$B$605,"QQQM",交易记录!$C$6:$C$605,"买入") -> 0 | H86: =SUMIFS(交易记录!$D$6:$D$605,交易记录!$A$6:$A$605,">="&DATE(YEAR(A86),MONTH(A86),1),交易记录!$A$6:$A$605,"<"&DATE(YEAR(A86),MONTH(A86)+1,1),交易记录!$B$6:$B$605,"SMH",交易记录!$C$6:$C$605,"买入")+SUMIFS(交易记录!$E$6:$E$605,交易记录!$A$6:$A$605,">="&DATE(YEAR(A86),MONTH(A86),1),交易记录!$A$6:$A$605,"<"&DATE(YEAR(A86),MONTH(A86)+1,1),交易记录!$B$6:$B$605,"SMH",交易记录!$C$6:$C$605,"买入") -> 0 | I86: =SUM(F86:H86) -> 0 | J86: =IF(I86=0,"",I86-B86) | K86: =IF(I86=0,"尚未记录买入",IF(ABS(J86)<0.01,"已记录预算金额","已记录，金额有差额")) -> 尚未记录买入
A87: =DATE(2033,7,总览!$E$4) -> 48770 | B87: =回撤计划!J90 -> 500 | C87: =B87*总览!$B$8 -> 450 | D87: =B87*总览!$B$9 -> 50 | E87: =B87*总览!$B$10 -> 0 | F87: =SUMIFS(交易记录!$D$6:$D$605,交易记录!$A$6:$A$605,">="&DATE(YEAR(A87),MONTH(A87),1),交易记录!$A$6:$A$605,"<"&DATE(YEAR(A87),MONTH(A87)+1,1),交易记录!$B$6:$B$605,"VOO",交易记录!$C$6:$C$605,"买入")+SUMIFS(交易记录!$E$6:$E$605,交易记录!$A$6:$A$605,">="&DATE(YEAR(A87),MONTH(A87),1),交易记录!$A$6:$A$605,"<"&DATE(YEAR(A87),MONTH(A87)+1,1),交易记录!$B$6:$B$605,"VOO",交易记录!$C$6:$C$605,"买入") -> 0 | G87: =SUMIFS(交易记录!$D$6:$D$605,交易记录!$A$6:$A$605,">="&DATE(YEAR(A87),MONTH(A87),1),交易记录!$A$6:$A$605,"<"&DATE(YEAR(A87),MONTH(A87)+1,1),交易记录!$B$6:$B$605,"QQQM",交易记录!$C$6:$C$605,"买入")+SUMIFS(交易记录!$E$6:$E$605,交易记录!$A$6:$A$605,">="&DATE(YEAR(A87),MONTH(A87),1),交易记录!$A$6:$A$605,"<"&DATE(YEAR(A87),MONTH(A87)+1,1),交易记录!$B$6:$B$605,"QQQM",交易记录!$C$6:$C$605,"买入") -> 0 | H87: =SUMIFS(交易记录!$D$6:$D$605,交易记录!$A$6:$A$605,">="&DATE(YEAR(A87),MONTH(A87),1),交易记录!$A$6:$A$605,"<"&DATE(YEAR(A87),MONTH(A87)+1,1),交易记录!$B$6:$B$605,"SMH",交易记录!$C$6:$C$605,"买入")+SUMIFS(交易记录!$E$6:$E$605,交易记录!$A$6:$A$605,">="&DATE(YEAR(A87),MONTH(A87),1),交易记录!$A$6:$A$605,"<"&DATE(YEAR(A87),MONTH(A87)+1,1),交易记录!$B$6:$B$605,"SMH",交易记录!$C$6:$C$605,"买入") -> 0 | I87: =SUM(F87:H87) -> 0 | J87: =IF(I87=0,"",I87-B87) | K87: =IF(I87=0,"尚未记录买入",IF(ABS(J87)<0.01,"已记录预算金额","已记录，金额有差额")) -> 尚未记录买入
A88: =DATE(2033,8,总览!$E$4) -> 48801 | B88: =回撤计划!J91 -> 500 | C88: =B88*总览!$B$8 -> 450 | D88: =B88*总览!$B$9 -> 50 | E88: =B88*总览!$B$10 -> 0 | F88: =SUMIFS(交易记录!$D$6:$D$605,交易记录!$A$6:$A$605,">="&DATE(YEAR(A88),MONTH(A88),1),交易记录!$A$6:$A$605,"<"&DATE(YEAR(A88),MONTH(A88)+1,1),交易记录!$B$6:$B$605,"VOO",交易记录!$C$6:$C$605,"买入")+SUMIFS(交易记录!$E$6:$E$605,交易记录!$A$6:$A$605,">="&DATE(YEAR(A88),MONTH(A88),1),交易记录!$A$6:$A$605,"<"&DATE(YEAR(A88),MONTH(A88)+1,1),交易记录!$B$6:$B$605,"VOO",交易记录!$C$6:$C$605,"买入") -> 0 | G88: =SUMIFS(交易记录!$D$6:$D$605,交易记录!$A$6:$A$605,">="&DATE(YEAR(A88),MONTH(A88),1),交易记录!$A$6:$A$605,"<"&DATE(YEAR(A88),MONTH(A88)+1,1),交易记录!$B$6:$B$605,"QQQM",交易记录!$C$6:$C$605,"买入")+SUMIFS(交易记录!$E$6:$E$605,交易记录!$A$6:$A$605,">="&DATE(YEAR(A88),MONTH(A88),1),交易记录!$A$6:$A$605,"<"&DATE(YEAR(A88),MONTH(A88)+1,1),交易记录!$B$6:$B$605,"QQQM",交易记录!$C$6:$C$605,"买入") -> 0 | H88: =SUMIFS(交易记录!$D$6:$D$605,交易记录!$A$6:$A$605,">="&DATE(YEAR(A88),MONTH(A88),1),交易记录!$A$6:$A$605,"<"&DATE(YEAR(A88),MONTH(A88)+1,1),交易记录!$B$6:$B$605,"SMH",交易记录!$C$6:$C$605,"买入")+SUMIFS(交易记录!$E$6:$E$605,交易记录!$A$6:$A$605,">="&DATE(YEAR(A88),MONTH(A88),1),交易记录!$A$6:$A$605,"<"&DATE(YEAR(A88),MONTH(A88)+1,1),交易记录!$B$6:$B$605,"SMH",交易记录!$C$6:$C$605,"买入") -> 0 | I88: =SUM(F88:H88) -> 0 | J88: =IF(I88=0,"",I88-B88) | K88: =IF(I88=0,"尚未记录买入",IF(ABS(J88)<0.01,"已记录预算金额","已记录，金额有差额")) -> 尚未记录买入
A89: =DATE(2033,9,总览!$E$4) -> 48832 | B89: =回撤计划!J92 -> 500 | C89: =B89*总览!$B$8 -> 450 | D89: =B89*总览!$B$9 -> 50 | E89: =B89*总览!$B$10 -> 0 | F89: =SUMIFS(交易记录!$D$6:$D$605,交易记录!$A$6:$A$605,">="&DATE(YEAR(A89),MONTH(A89),1),交易记录!$A$6:$A$605,"<"&DATE(YEAR(A89),MONTH(A89)+1,1),交易记录!$B$6:$B$605,"VOO",交易记录!$C$6:$C$605,"买入")+SUMIFS(交易记录!$E$6:$E$605,交易记录!$A$6:$A$605,">="&DATE(YEAR(A89),MONTH(A89),1),交易记录!$A$6:$A$605,"<"&DATE(YEAR(A89),MONTH(A89)+1,1),交易记录!$B$6:$B$605,"VOO",交易记录!$C$6:$C$605,"买入") -> 0 | G89: =SUMIFS(交易记录!$D$6:$D$605,交易记录!$A$6:$A$605,">="&DATE(YEAR(A89),MONTH(A89),1),交易记录!$A$6:$A$605,"<"&DATE(YEAR(A89),MONTH(A89)+1,1),交易记录!$B$6:$B$605,"QQQM",交易记录!$C$6:$C$605,"买入")+SUMIFS(交易记录!$E$6:$E$605,交易记录!$A$6:$A$605,">="&DATE(YEAR(A89),MONTH(A89),1),交易记录!$A$6:$A$605,"<"&DATE(YEAR(A89),MONTH(A89)+1,1),交易记录!$B$6:$B$605,"QQQM",交易记录!$C$6:$C$605,"买入") -> 0 | H89: =SUMIFS(交易记录!$D$6:$D$605,交易记录!$A$6:$A$605,">="&DATE(YEAR(A89),MONTH(A89),1),交易记录!$A$6:$A$605,"<"&DATE(YEAR(A89),MONTH(A89)+1,1),交易记录!$B$6:$B$605,"SMH",交易记录!$C$6:$C$605,"买入")+SUMIFS(交易记录!$E$6:$E$605,交易记录!$A$6:$A$605,">="&DATE(YEAR(A89),MONTH(A89),1),交易记录!$A$6:$A$605,"<"&DATE(YEAR(A89),MONTH(A89)+1,1),交易记录!$B$6:$B$605,"SMH",交易记录!$C$6:$C$605,"买入") -> 0 | I89: =SUM(F89:H89) -> 0 | J89: =IF(I89=0,"",I89-B89) | K89: =IF(I89=0,"尚未记录买入",IF(ABS(J89)<0.01,"已记录预算金额","已记录，金额有差额")) -> 尚未记录买入
A90: =DATE(2033,10,总览!$E$4) -> 48862 | B90: =回撤计划!J93 -> 500 | C90: =B90*总览!$B$8 -> 450 | D90: =B90*总览!$B$9 -> 50 | E90: =B90*总览!$B$10 -> 0 | F90: =SUMIFS(交易记录!$D$6:$D$605,交易记录!$A$6:$A$605,">="&DATE(YEAR(A90),MONTH(A90),1),交易记录!$A$6:$A$605,"<"&DATE(YEAR(A90),MONTH(A90)+1,1),交易记录!$B$6:$B$605,"VOO",交易记录!$C$6:$C$605,"买入")+SUMIFS(交易记录!$E$6:$E$605,交易记录!$A$6:$A$605,">="&DATE(YEAR(A90),MONTH(A90),1),交易记录!$A$6:$A$605,"<"&DATE(YEAR(A90),MONTH(A90)+1,1),交易记录!$B$6:$B$605,"VOO",交易记录!$C$6:$C$605,"买入") -> 0 | G90: =SUMIFS(交易记录!$D$6:$D$605,交易记录!$A$6:$A$605,">="&DATE(YEAR(A90),MONTH(A90),1),交易记录!$A$6:$A$605,"<"&DATE(YEAR(A90),MONTH(A90)+1,1),交易记录!$B$6:$B$605,"QQQM",交易记录!$C$6:$C$605,"买入")+SUMIFS(交易记录!$E$6:$E$605,交易记录!$A$6:$A$605,">="&DATE(YEAR(A90),MONTH(A90),1),交易记录!$A$6:$A$605,"<"&DATE(YEAR(A90),MONTH(A90)+1,1),交易记录!$B$6:$B$605,"QQQM",交易记录!$C$6:$C$605,"买入") -> 0 | H90: =SUMIFS(交易记录!$D$6:$D$605,交易记录!$A$6:$A$605,">="&DATE(YEAR(A90),MONTH(A90),1),交易记录!$A$6:$A$605,"<"&DATE(YEAR(A90),MONTH(A90)+1,1),交易记录!$B$6:$B$605,"SMH",交易记录!$C$6:$C$605,"买入")+SUMIFS(交易记录!$E$6:$E$605,交易记录!$A$6:$A$605,">="&DATE(YEAR(A90),MONTH(A90),1),交易记录!$A$6:$A$605,"<"&DATE(YEAR(A90),MONTH(A90)+1,1),交易记录!$B$6:$B$605,"SMH",交易记录!$C$6:$C$605,"买入") -> 0 | I90: =SUM(F90:H90) -> 0 | J90: =IF(I90=0,"",I90-B90) | K90: =IF(I90=0,"尚未记录买入",IF(ABS(J90)<0.01,"已记录预算金额","已记录，金额有差额")) -> 尚未记录买入
A91: =DATE(2033,11,总览!$E$4) -> 48893 | B91: =回撤计划!J94 -> 500 | C91: =B91*总览!$B$8 -> 450 | D91: =B91*总览!$B$9 -> 50 | E91: =B91*总览!$B$10 -> 0 | F91: =SUMIFS(交易记录!$D$6:$D$605,交易记录!$A$6:$A$605,">="&DATE(YEAR(A91),MONTH(A91),1),交易记录!$A$6:$A$605,"<"&DATE(YEAR(A91),MONTH(A91)+1,1),交易记录!$B$6:$B$605,"VOO",交易记录!$C$6:$C$605,"买入")+SUMIFS(交易记录!$E$6:$E$605,交易记录!$A$6:$A$605,">="&DATE(YEAR(A91),MONTH(A91),1),交易记录!$A$6:$A$605,"<"&DATE(YEAR(A91),MONTH(A91)+1,1),交易记录!$B$6:$B$605,"VOO",交易记录!$C$6:$C$605,"买入") -> 0 | G91: =SUMIFS(交易记录!$D$6:$D$605,交易记录!$A$6:$A$605,">="&DATE(YEAR(A91),MONTH(A91),1),交易记录!$A$6:$A$605,"<"&DATE(YEAR(A91),MONTH(A91)+1,1),交易记录!$B$6:$B$605,"QQQM",交易记录!$C$6:$C$605,"买入")+SUMIFS(交易记录!$E$6:$E$605,交易记录!$A$6:$A$605,">="&DATE(YEAR(A91),MONTH(A91),1),交易记录!$A$6:$A$605,"<"&DATE(YEAR(A91),MONTH(A91)+1,1),交易记录!$B$6:$B$605,"QQQM",交易记录!$C$6:$C$605,"买入") -> 0 | H91: =SUMIFS(交易记录!$D$6:$D$605,交易记录!$A$6:$A$605,">="&DATE(YEAR(A91),MONTH(A91),1),交易记录!$A$6:$A$605,"<"&DATE(YEAR(A91),MONTH(A91)+1,1),交易记录!$B$6:$B$605,"SMH",交易记录!$C$6:$C$605,"买入")+SUMIFS(交易记录!$E$6:$E$605,交易记录!$A$6:$A$605,">="&DATE(YEAR(A91),MONTH(A91),1),交易记录!$A$6:$A$605,"<"&DATE(YEAR(A91),MONTH(A91)+1,1),交易记录!$B$6:$B$605,"SMH",交易记录!$C$6:$C$605,"买入") -> 0 | I91: =SUM(F91:H91) -> 0 | J91: =IF(I91=0,"",I91-B91) | K91: =IF(I91=0,"尚未记录买入",IF(ABS(J91)<0.01,"已记录预算金额","已记录，金额有差额")) -> 尚未记录买入
A92: =DATE(2033,12,总览!$E$4) -> 48923 | B92: =回撤计划!J95 -> 500 | C92: =B92*总览!$B$8 -> 450 | D92: =B92*总览!$B$9 -> 50 | E92: =B92*总览!$B$10 -> 0 | F92: =SUMIFS(交易记录!$D$6:$D$605,交易记录!$A$6:$A$605,">="&DATE(YEAR(A92),MONTH(A92),1),交易记录!$A$6:$A$605,"<"&DATE(YEAR(A92),MONTH(A92)+1,1),交易记录!$B$6:$B$605,"VOO",交易记录!$C$6:$C$605,"买入")+SUMIFS(交易记录!$E$6:$E$605,交易记录!$A$6:$A$605,">="&DATE(YEAR(A92),MONTH(A92),1),交易记录!$A$6:$A$605,"<"&DATE(YEAR(A92),MONTH(A92)+1,1),交易记录!$B$6:$B$605,"VOO",交易记录!$C$6:$C$605,"买入") -> 0 | G92: =SUMIFS(交易记录!$D$6:$D$605,交易记录!$A$6:$A$605,">="&DATE(YEAR(A92),MONTH(A92),1),交易记录!$A$6:$A$605,"<"&DATE(YEAR(A92),MONTH(A92)+1,1),交易记录!$B$6:$B$605,"QQQM",交易记录!$C$6:$C$605,"买入")+SUMIFS(交易记录!$E$6:$E$605,交易记录!$A$6:$A$605,">="&DATE(YEAR(A92),MONTH(A92),1),交易记录!$A$6:$A$605,"<"&DATE(YEAR(A92),MONTH(A92)+1,1),交易记录!$B$6:$B$605,"QQQM",交易记录!$C$6:$C$605,"买入") -> 0 | H92: =SUMIFS(交易记录!$D$6:$D$605,交易记录!$A$6:$A$605,">="&DATE(YEAR(A92),MONTH(A92),1),交易记录!$A$6:$A$605,"<"&DATE(YEAR(A92),MONTH(A92)+1,1),交易记录!$B$6:$B$605,"SMH",交易记录!$C$6:$C$605,"买入")+SUMIFS(交易记录!$E$6:$E$605,交易记录!$A$6:$A$605,">="&DATE(YEAR(A92),MONTH(A92),1),交易记录!$A$6:$A$605,"<"&DATE(YEAR(A92),MONTH(A92)+1,1),交易记录!$B$6:$B$605,"SMH",交易记录!$C$6:$C$605,"买入") -> 0 | I92: =SUM(F92:H92) -> 0 | J92: =IF(I92=0,"",I92-B92) | K92: =IF(I92=0,"尚未记录买入",IF(ABS(J92)<0.01,"已记录预算金额","已记录，金额有差额")) -> 尚未记录买入
A93: =DATE(2034,1,总览!$E$4) -> 48954 | B93: =回撤计划!J96 -> 500 | C93: =B93*总览!$B$8 -> 450 | D93: =B93*总览!$B$9 -> 50 | E93: =B93*总览!$B$10 -> 0 | F93: =SUMIFS(交易记录!$D$6:$D$605,交易记录!$A$6:$A$605,">="&DATE(YEAR(A93),MONTH(A93),1),交易记录!$A$6:$A$605,"<"&DATE(YEAR(A93),MONTH(A93)+1,1),交易记录!$B$6:$B$605,"VOO",交易记录!$C$6:$C$605,"买入")+SUMIFS(交易记录!$E$6:$E$605,交易记录!$A$6:$A$605,">="&DATE(YEAR(A93),MONTH(A93),1),交易记录!$A$6:$A$605,"<"&DATE(YEAR(A93),MONTH(A93)+1,1),交易记录!$B$6:$B$605,"VOO",交易记录!$C$6:$C$605,"买入") -> 0 | G93: =SUMIFS(交易记录!$D$6:$D$605,交易记录!$A$6:$A$605,">="&DATE(YEAR(A93),MONTH(A93),1),交易记录!$A$6:$A$605,"<"&DATE(YEAR(A93),MONTH(A93)+1,1),交易记录!$B$6:$B$605,"QQQM",交易记录!$C$6:$C$605,"买入")+SUMIFS(交易记录!$E$6:$E$605,交易记录!$A$6:$A$605,">="&DATE(YEAR(A93),MONTH(A93),1),交易记录!$A$6:$A$605,"<"&DATE(YEAR(A93),MONTH(A93)+1,1),交易记录!$B$6:$B$605,"QQQM",交易记录!$C$6:$C$605,"买入") -> 0 | H93: =SUMIFS(交易记录!$D$6:$D$605,交易记录!$A$6:$A$605,">="&DATE(YEAR(A93),MONTH(A93),1),交易记录!$A$6:$A$605,"<"&DATE(YEAR(A93),MONTH(A93)+1,1),交易记录!$B$6:$B$605,"SMH",交易记录!$C$6:$C$605,"买入")+SUMIFS(交易记录!$E$6:$E$605,交易记录!$A$6:$A$605,">="&DATE(YEAR(A93),MONTH(A93),1),交易记录!$A$6:$A$605,"<"&DATE(YEAR(A93),MONTH(A93)+1,1),交易记录!$B$6:$B$605,"SMH",交易记录!$C$6:$C$605,"买入") -> 0 | I93: =SUM(F93:H93) -> 0 | J93: =IF(I93=0,"",I93-B93) | K93: =IF(I93=0,"尚未记录买入",IF(ABS(J93)<0.01,"已记录预算金额","已记录，金额有差额")) -> 尚未记录买入
A94: =DATE(2034,2,总览!$E$4) -> 48985 | B94: =回撤计划!J97 -> 500 | C94: =B94*总览!$B$8 -> 450 | D94: =B94*总览!$B$9 -> 50 | E94: =B94*总览!$B$10 -> 0 | F94: =SUMIFS(交易记录!$D$6:$D$605,交易记录!$A$6:$A$605,">="&DATE(YEAR(A94),MONTH(A94),1),交易记录!$A$6:$A$605,"<"&DATE(YEAR(A94),MONTH(A94)+1,1),交易记录!$B$6:$B$605,"VOO",交易记录!$C$6:$C$605,"买入")+SUMIFS(交易记录!$E$6:$E$605,交易记录!$A$6:$A$605,">="&DATE(YEAR(A94),MONTH(A94),1),交易记录!$A$6:$A$605,"<"&DATE(YEAR(A94),MONTH(A94)+1,1),交易记录!$B$6:$B$605,"VOO",交易记录!$C$6:$C$605,"买入") -> 0 | G94: =SUMIFS(交易记录!$D$6:$D$605,交易记录!$A$6:$A$605,">="&DATE(YEAR(A94),MONTH(A94),1),交易记录!$A$6:$A$605,"<"&DATE(YEAR(A94),MONTH(A94)+1,1),交易记录!$B$6:$B$605,"QQQM",交易记录!$C$6:$C$605,"买入")+SUMIFS(交易记录!$E$6:$E$605,交易记录!$A$6:$A$605,">="&DATE(YEAR(A94),MONTH(A94),1),交易记录!$A$6:$A$605,"<"&DATE(YEAR(A94),MONTH(A94)+1,1),交易记录!$B$6:$B$605,"QQQM",交易记录!$C$6:$C$605,"买入") -> 0 | H94: =SUMIFS(交易记录!$D$6:$D$605,交易记录!$A$6:$A$605,">="&DATE(YEAR(A94),MONTH(A94),1),交易记录!$A$6:$A$605,"<"&DATE(YEAR(A94),MONTH(A94)+1,1),交易记录!$B$6:$B$605,"SMH",交易记录!$C$6:$C$605,"买入")+SUMIFS(交易记录!$E$6:$E$605,交易记录!$A$6:$A$605,">="&DATE(YEAR(A94),MONTH(A94),1),交易记录!$A$6:$A$605,"<"&DATE(YEAR(A94),MONTH(A94)+1,1),交易记录!$B$6:$B$605,"SMH",交易记录!$C$6:$C$605,"买入") -> 0 | I94: =SUM(F94:H94) -> 0 | J94: =IF(I94=0,"",I94-B94) | K94: =IF(I94=0,"尚未记录买入",IF(ABS(J94)<0.01,"已记录预算金额","已记录，金额有差额")) -> 尚未记录买入
A95: =DATE(2034,3,总览!$E$4) -> 49013 | B95: =回撤计划!J98 -> 500 | C95: =B95*总览!$B$8 -> 450 | D95: =B95*总览!$B$9 -> 50 | E95: =B95*总览!$B$10 -> 0 | F95: =SUMIFS(交易记录!$D$6:$D$605,交易记录!$A$6:$A$605,">="&DATE(YEAR(A95),MONTH(A95),1),交易记录!$A$6:$A$605,"<"&DATE(YEAR(A95),MONTH(A95)+1,1),交易记录!$B$6:$B$605,"VOO",交易记录!$C$6:$C$605,"买入")+SUMIFS(交易记录!$E$6:$E$605,交易记录!$A$6:$A$605,">="&DATE(YEAR(A95),MONTH(A95),1),交易记录!$A$6:$A$605,"<"&DATE(YEAR(A95),MONTH(A95)+1,1),交易记录!$B$6:$B$605,"VOO",交易记录!$C$6:$C$605,"买入") -> 0 | G95: =SUMIFS(交易记录!$D$6:$D$605,交易记录!$A$6:$A$605,">="&DATE(YEAR(A95),MONTH(A95),1),交易记录!$A$6:$A$605,"<"&DATE(YEAR(A95),MONTH(A95)+1,1),交易记录!$B$6:$B$605,"QQQM",交易记录!$C$6:$C$605,"买入")+SUMIFS(交易记录!$E$6:$E$605,交易记录!$A$6:$A$605,">="&DATE(YEAR(A95),MONTH(A95),1),交易记录!$A$6:$A$605,"<"&DATE(YEAR(A95),MONTH(A95)+1,1),交易记录!$B$6:$B$605,"QQQM",交易记录!$C$6:$C$605,"买入") -> 0 | H95: =SUMIFS(交易记录!$D$6:$D$605,交易记录!$A$6:$A$605,">="&DATE(YEAR(A95),MONTH(A95),1),交易记录!$A$6:$A$605,"<"&DATE(YEAR(A95),MONTH(A95)+1,1),交易记录!$B$6:$B$605,"SMH",交易记录!$C$6:$C$605,"买入")+SUMIFS(交易记录!$E$6:$E$605,交易记录!$A$6:$A$605,">="&DATE(YEAR(A95),MONTH(A95),1),交易记录!$A$6:$A$605,"<"&DATE(YEAR(A95),MONTH(A95)+1,1),交易记录!$B$6:$B$605,"SMH",交易记录!$C$6:$C$605,"买入") -> 0 | I95: =SUM(F95:H95) -> 0 | J95: =IF(I95=0,"",I95-B95) | K95: =IF(I95=0,"尚未记录买入",IF(ABS(J95)<0.01,"已记录预算金额","已记录，金额有差额")) -> 尚未记录买入
A96: =DATE(2034,4,总览!$E$4) -> 49044 | B96: =回撤计划!J99 -> 500 | C96: =B96*总览!$B$8 -> 450 | D96: =B96*总览!$B$9 -> 50 | E96: =B96*总览!$B$10 -> 0 | F96: =SUMIFS(交易记录!$D$6:$D$605,交易记录!$A$6:$A$605,">="&DATE(YEAR(A96),MONTH(A96),1),交易记录!$A$6:$A$605,"<"&DATE(YEAR(A96),MONTH(A96)+1,1),交易记录!$B$6:$B$605,"VOO",交易记录!$C$6:$C$605,"买入")+SUMIFS(交易记录!$E$6:$E$605,交易记录!$A$6:$A$605,">="&DATE(YEAR(A96),MONTH(A96),1),交易记录!$A$6:$A$605,"<"&DATE(YEAR(A96),MONTH(A96)+1,1),交易记录!$B$6:$B$605,"VOO",交易记录!$C$6:$C$605,"买入") -> 0 | G96: =SUMIFS(交易记录!$D$6:$D$605,交易记录!$A$6:$A$605,">="&DATE(YEAR(A96),MONTH(A96),1),交易记录!$A$6:$A$605,"<"&DATE(YEAR(A96),MONTH(A96)+1,1),交易记录!$B$6:$B$605,"QQQM",交易记录!$C$6:$C$605,"买入")+SUMIFS(交易记录!$E$6:$E$605,交易记录!$A$6:$A$605,">="&DATE(YEAR(A96),MONTH(A96),1),交易记录!$A$6:$A$605,"<"&DATE(YEAR(A96),MONTH(A96)+1,1),交易记录!$B$6:$B$605,"QQQM",交易记录!$C$6:$C$605,"买入") -> 0 | H96: =SUMIFS(交易记录!$D$6:$D$605,交易记录!$A$6:$A$605,">="&DATE(YEAR(A96),MONTH(A96),1),交易记录!$A$6:$A$605,"<"&DATE(YEAR(A96),MONTH(A96)+1,1),交易记录!$B$6:$B$605,"SMH",交易记录!$C$6:$C$605,"买入")+SUMIFS(交易记录!$E$6:$E$605,交易记录!$A$6:$A$605,">="&DATE(YEAR(A96),MONTH(A96),1),交易记录!$A$6:$A$605,"<"&DATE(YEAR(A96),MONTH(A96)+1,1),交易记录!$B$6:$B$605,"SMH",交易记录!$C$6:$C$605,"买入") -> 0 | I96: =SUM(F96:H96) -> 0 | J96: =IF(I96=0,"",I96-B96) | K96: =IF(I96=0,"尚未记录买入",IF(ABS(J96)<0.01,"已记录预算金额","已记录，金额有差额")) -> 尚未记录买入
A97: =DATE(2034,5,总览!$E$4) -> 49074 | B97: =回撤计划!J100 -> 500 | C97: =B97*总览!$B$8 -> 450 | D97: =B97*总览!$B$9 -> 50 | E97: =B97*总览!$B$10 -> 0 | F97: =SUMIFS(交易记录!$D$6:$D$605,交易记录!$A$6:$A$605,">="&DATE(YEAR(A97),MONTH(A97),1),交易记录!$A$6:$A$605,"<"&DATE(YEAR(A97),MONTH(A97)+1,1),交易记录!$B$6:$B$605,"VOO",交易记录!$C$6:$C$605,"买入")+SUMIFS(交易记录!$E$6:$E$605,交易记录!$A$6:$A$605,">="&DATE(YEAR(A97),MONTH(A97),1),交易记录!$A$6:$A$605,"<"&DATE(YEAR(A97),MONTH(A97)+1,1),交易记录!$B$6:$B$605,"VOO",交易记录!$C$6:$C$605,"买入") -> 0 | G97: =SUMIFS(交易记录!$D$6:$D$605,交易记录!$A$6:$A$605,">="&DATE(YEAR(A97),MONTH(A97),1),交易记录!$A$6:$A$605,"<"&DATE(YEAR(A97),MONTH(A97)+1,1),交易记录!$B$6:$B$605,"QQQM",交易记录!$C$6:$C$605,"买入")+SUMIFS(交易记录!$E$6:$E$605,交易记录!$A$6:$A$605,">="&DATE(YEAR(A97),MONTH(A97),1),交易记录!$A$6:$A$605,"<"&DATE(YEAR(A97),MONTH(A97)+1,1),交易记录!$B$6:$B$605,"QQQM",交易记录!$C$6:$C$605,"买入") -> 0 | H97: =SUMIFS(交易记录!$D$6:$D$605,交易记录!$A$6:$A$605,">="&DATE(YEAR(A97),MONTH(A97),1),交易记录!$A$6:$A$605,"<"&DATE(YEAR(A97),MONTH(A97)+1,1),交易记录!$B$6:$B$605,"SMH",交易记录!$C$6:$C$605,"买入")+SUMIFS(交易记录!$E$6:$E$605,交易记录!$A$6:$A$605,">="&DATE(YEAR(A97),MONTH(A97),1),交易记录!$A$6:$A$605,"<"&DATE(YEAR(A97),MONTH(A97)+1,1),交易记录!$B$6:$B$605,"SMH",交易记录!$C$6:$C$605,"买入") -> 0 | I97: =SUM(F97:H97) -> 0 | J97: =IF(I97=0,"",I97-B97) | K97: =IF(I97=0,"尚未记录买入",IF(ABS(J97)<0.01,"已记录预算金额","已记录，金额有差额")) -> 尚未记录买入
A98: =DATE(2034,6,总览!$E$4) -> 49105 | B98: =回撤计划!J101 -> 500 | C98: =B98*总览!$B$8 -> 450 | D98: =B98*总览!$B$9 -> 50 | E98: =B98*总览!$B$10 -> 0 | F98: =SUMIFS(交易记录!$D$6:$D$605,交易记录!$A$6:$A$605,">="&DATE(YEAR(A98),MONTH(A98),1),交易记录!$A$6:$A$605,"<"&DATE(YEAR(A98),MONTH(A98)+1,1),交易记录!$B$6:$B$605,"VOO",交易记录!$C$6:$C$605,"买入")+SUMIFS(交易记录!$E$6:$E$605,交易记录!$A$6:$A$605,">="&DATE(YEAR(A98),MONTH(A98),1),交易记录!$A$6:$A$605,"<"&DATE(YEAR(A98),MONTH(A98)+1,1),交易记录!$B$6:$B$605,"VOO",交易记录!$C$6:$C$605,"买入") -> 0 | G98: =SUMIFS(交易记录!$D$6:$D$605,交易记录!$A$6:$A$605,">="&DATE(YEAR(A98),MONTH(A98),1),交易记录!$A$6:$A$605,"<"&DATE(YEAR(A98),MONTH(A98)+1,1),交易记录!$B$6:$B$605,"QQQM",交易记录!$C$6:$C$605,"买入")+SUMIFS(交易记录!$E$6:$E$605,交易记录!$A$6:$A$605,">="&DATE(YEAR(A98),MONTH(A98),1),交易记录!$A$6:$A$605,"<"&DATE(YEAR(A98),MONTH(A98)+1,1),交易记录!$B$6:$B$605,"QQQM",交易记录!$C$6:$C$605,"买入") -> 0 | H98: =SUMIFS(交易记录!$D$6:$D$605,交易记录!$A$6:$A$605,">="&DATE(YEAR(A98),MONTH(A98),1),交易记录!$A$6:$A$605,"<"&DATE(YEAR(A98),MONTH(A98)+1,1),交易记录!$B$6:$B$605,"SMH",交易记录!$C$6:$C$605,"买入")+SUMIFS(交易记录!$E$6:$E$605,交易记录!$A$6:$A$605,">="&DATE(YEAR(A98),MONTH(A98),1),交易记录!$A$6:$A$605,"<"&DATE(YEAR(A98),MONTH(A98)+1,1),交易记录!$B$6:$B$605,"SMH",交易记录!$C$6:$C$605,"买入") -> 0 | I98: =SUM(F98:H98) -> 0 | J98: =IF(I98=0,"",I98-B98) | K98: =IF(I98=0,"尚未记录买入",IF(ABS(J98)<0.01,"已记录预算金额","已记录，金额有差额")) -> 尚未记录买入
A99: =DATE(2034,7,总览!$E$4) -> 49135 | B99: =回撤计划!J102 -> 500 | C99: =B99*总览!$B$8 -> 450 | D99: =B99*总览!$B$9 -> 50 | E99: =B99*总览!$B$10 -> 0 | F99: =SUMIFS(交易记录!$D$6:$D$605,交易记录!$A$6:$A$605,">="&DATE(YEAR(A99),MONTH(A99),1),交易记录!$A$6:$A$605,"<"&DATE(YEAR(A99),MONTH(A99)+1,1),交易记录!$B$6:$B$605,"VOO",交易记录!$C$6:$C$605,"买入")+SUMIFS(交易记录!$E$6:$E$605,交易记录!$A$6:$A$605,">="&DATE(YEAR(A99),MONTH(A99),1),交易记录!$A$6:$A$605,"<"&DATE(YEAR(A99),MONTH(A99)+1,1),交易记录!$B$6:$B$605,"VOO",交易记录!$C$6:$C$605,"买入") -> 0 | G99: =SUMIFS(交易记录!$D$6:$D$605,交易记录!$A$6:$A$605,">="&DATE(YEAR(A99),MONTH(A99),1),交易记录!$A$6:$A$605,"<"&DATE(YEAR(A99),MONTH(A99)+1,1),交易记录!$B$6:$B$605,"QQQM",交易记录!$C$6:$C$605,"买入")+SUMIFS(交易记录!$E$6:$E$605,交易记录!$A$6:$A$605,">="&DATE(YEAR(A99),MONTH(A99),1),交易记录!$A$6:$A$605,"<"&DATE(YEAR(A99),MONTH(A99)+1,1),交易记录!$B$6:$B$605,"QQQM",交易记录!$C$6:$C$605,"买入") -> 0 | H99: =SUMIFS(交易记录!$D$6:$D$605,交易记录!$A$6:$A$605,">="&DATE(YEAR(A99),MONTH(A99),1),交易记录!$A$6:$A$605,"<"&DATE(YEAR(A99),MONTH(A99)+1,1),交易记录!$B$6:$B$605,"SMH",交易记录!$C$6:$C$605,"买入")+SUMIFS(交易记录!$E$6:$E$605,交易记录!$A$6:$A$605,">="&DATE(YEAR(A99),MONTH(A99),1),交易记录!$A$6:$A$605,"<"&DATE(YEAR(A99),MONTH(A99)+1,1),交易记录!$B$6:$B$605,"SMH",交易记录!$C$6:$C$605,"买入") -> 0 | I99: =SUM(F99:H99) -> 0 | J99: =IF(I99=0,"",I99-B99) | K99: =IF(I99=0,"尚未记录买入",IF(ABS(J99)<0.01,"已记录预算金额","已记录，金额有差额")) -> 尚未记录买入
A100: =DATE(2034,8,总览!$E$4) -> 49166 | B100: =回撤计划!J103 -> 500 | C100: =B100*总览!$B$8 -> 450 | D100: =B100*总览!$B$9 -> 50 | E100: =B100*总览!$B$10 -> 0 | F100: =SUMIFS(交易记录!$D$6:$D$605,交易记录!$A$6:$A$605,">="&DATE(YEAR(A100),MONTH(A100),1),交易记录!$A$6:$A$605,"<"&DATE(YEAR(A100),MONTH(A100)+1,1),交易记录!$B$6:$B$605,"VOO",交易记录!$C$6:$C$605,"买入")+SUMIFS(交易记录!$E$6:$E$605,交易记录!$A$6:$A$605,">="&DATE(YEAR(A100),MONTH(A100),1),交易记录!$A$6:$A$605,"<"&DATE(YEAR(A100),MONTH(A100)+1,1),交易记录!$B$6:$B$605,"VOO",交易记录!$C$6:$C$605,"买入") -> 0 | G100: =SUMIFS(交易记录!$D$6:$D$605,交易记录!$A$6:$A$605,">="&DATE(YEAR(A100),MONTH(A100),1),交易记录!$A$6:$A$605,"<"&DATE(YEAR(A100),MONTH(A100)+1,1),交易记录!$B$6:$B$605,"QQQM",交易记录!$C$6:$C$605,"买入")+SUMIFS(交易记录!$E$6:$E$605,交易记录!$A$6:$A$605,">="&DATE(YEAR(A100),MONTH(A100),1),交易记录!$A$6:$A$605,"<"&DATE(YEAR(A100),MONTH(A100)+1,1),交易记录!$B$6:$B$605,"QQQM",交易记录!$C$6:$C$605,"买入") -> 0 | H100: =SUMIFS(交易记录!$D$6:$D$605,交易记录!$A$6:$A$605,">="&DATE(YEAR(A100),MONTH(A100),1),交易记录!$A$6:$A$605,"<"&DATE(YEAR(A100),MONTH(A100)+1,1),交易记录!$B$6:$B$605,"SMH",交易记录!$C$6:$C$605,"买入")+SUMIFS(交易记录!$E$6:$E$605,交易记录!$A$6:$A$605,">="&DATE(YEAR(A100),MONTH(A100),1),交易记录!$A$6:$A$605,"<"&DATE(YEAR(A100),MONTH(A100)+1,1),交易记录!$B$6:$B$605,"SMH",交易记录!$C$6:$C$605,"买入") -> 0 | I100: =SUM(F100:H100) -> 0 | J100: =IF(I100=0,"",I100-B100) | K100: =IF(I100=0,"尚未记录买入",IF(ABS(J100)<0.01,"已记录预算金额","已记录，金额有差额")) -> 尚未记录买入
A101: =DATE(2034,9,总览!$E$4) -> 49197 | B101: =回撤计划!J104 -> 500 | C101: =B101*总览!$B$8 -> 450 | D101: =B101*总览!$B$9 -> 50 | E101: =B101*总览!$B$10 -> 0 | F101: =SUMIFS(交易记录!$D$6:$D$605,交易记录!$A$6:$A$605,">="&DATE(YEAR(A101),MONTH(A101),1),交易记录!$A$6:$A$605,"<"&DATE(YEAR(A101),MONTH(A101)+1,1),交易记录!$B$6:$B$605,"VOO",交易记录!$C$6:$C$605,"买入")+SUMIFS(交易记录!$E$6:$E$605,交易记录!$A$6:$A$605,">="&DATE(YEAR(A101),MONTH(A101),1),交易记录!$A$6:$A$605,"<"&DATE(YEAR(A101),MONTH(A101)+1,1),交易记录!$B$6:$B$605,"VOO",交易记录!$C$6:$C$605,"买入") -> 0 | G101: =SUMIFS(交易记录!$D$6:$D$605,交易记录!$A$6:$A$605,">="&DATE(YEAR(A101),MONTH(A101),1),交易记录!$A$6:$A$605,"<"&DATE(YEAR(A101),MONTH(A101)+1,1),交易记录!$B$6:$B$605,"QQQM",交易记录!$C$6:$C$605,"买入")+SUMIFS(交易记录!$E$6:$E$605,交易记录!$A$6:$A$605,">="&DATE(YEAR(A101),MONTH(A101),1),交易记录!$A$6:$A$605,"<"&DATE(YEAR(A101),MONTH(A101)+1,1),交易记录!$B$6:$B$605,"QQQM",交易记录!$C$6:$C$605,"买入") -> 0 | H101: =SUMIFS(交易记录!$D$6:$D$605,交易记录!$A$6:$A$605,">="&DATE(YEAR(A101),MONTH(A101),1),交易记录!$A$6:$A$605,"<"&DATE(YEAR(A101),MONTH(A101)+1,1),交易记录!$B$6:$B$605,"SMH",交易记录!$C$6:$C$605,"买入")+SUMIFS(交易记录!$E$6:$E$605,交易记录!$A$6:$A$605,">="&DATE(YEAR(A101),MONTH(A101),1),交易记录!$A$6:$A$605,"<"&DATE(YEAR(A101),MONTH(A101)+1,1),交易记录!$B$6:$B$605,"SMH",交易记录!$C$6:$C$605,"买入") -> 0 | I101: =SUM(F101:H101) -> 0 | J101: =IF(I101=0,"",I101-B101) | K101: =IF(I101=0,"尚未记录买入",IF(ABS(J101)<0.01,"已记录预算金额","已记录，金额有差额")) -> 尚未记录买入
A102: =DATE(2034,10,总览!$E$4) -> 49227 | B102: =回撤计划!J105 -> 500 | C102: =B102*总览!$B$8 -> 450 | D102: =B102*总览!$B$9 -> 50 | E102: =B102*总览!$B$10 -> 0 | F102: =SUMIFS(交易记录!$D$6:$D$605,交易记录!$A$6:$A$605,">="&DATE(YEAR(A102),MONTH(A102),1),交易记录!$A$6:$A$605,"<"&DATE(YEAR(A102),MONTH(A102)+1,1),交易记录!$B$6:$B$605,"VOO",交易记录!$C$6:$C$605,"买入")+SUMIFS(交易记录!$E$6:$E$605,交易记录!$A$6:$A$605,">="&DATE(YEAR(A102),MONTH(A102),1),交易记录!$A$6:$A$605,"<"&DATE(YEAR(A102),MONTH(A102)+1,1),交易记录!$B$6:$B$605,"VOO",交易记录!$C$6:$C$605,"买入") -> 0 | G102: =SUMIFS(交易记录!$D$6:$D$605,交易记录!$A$6:$A$605,">="&DATE(YEAR(A102),MONTH(A102),1),交易记录!$A$6:$A$605,"<"&DATE(YEAR(A102),MONTH(A102)+1,1),交易记录!$B$6:$B$605,"QQQM",交易记录!$C$6:$C$605,"买入")+SUMIFS(交易记录!$E$6:$E$605,交易记录!$A$6:$A$605,">="&DATE(YEAR(A102),MONTH(A102),1),交易记录!$A$6:$A$605,"<"&DATE(YEAR(A102),MONTH(A102)+1,1),交易记录!$B$6:$B$605,"QQQM",交易记录!$C$6:$C$605,"买入") -> 0 | H102: =SUMIFS(交易记录!$D$6:$D$605,交易记录!$A$6:$A$605,">="&DATE(YEAR(A102),MONTH(A102),1),交易记录!$A$6:$A$605,"<"&DATE(YEAR(A102),MONTH(A102)+1,1),交易记录!$B$6:$B$605,"SMH",交易记录!$C$6:$C$605,"买入")+SUMIFS(交易记录!$E$6:$E$605,交易记录!$A$6:$A$605,">="&DATE(YEAR(A102),MONTH(A102),1),交易记录!$A$6:$A$605,"<"&DATE(YEAR(A102),MONTH(A102)+1,1),交易记录!$B$6:$B$605,"SMH",交易记录!$C$6:$C$605,"买入") -> 0 | I102: =SUM(F102:H102) -> 0 | J102: =IF(I102=0,"",I102-B102) | K102: =IF(I102=0,"尚未记录买入",IF(ABS(J102)<0.01,"已记录预算金额","已记录，金额有差额")) -> 尚未记录买入
...

Sheet 交易记录
A1: 交易记录
A3: 每笔成交一行；按实际日期排序。P列空白默认定投；分红再投／其他买入请标明用途。蓝色格填写；成交金额不含手续费。
A5: 成交日期 | B5: ETF | C5: 方向 | D5: 成交金额 USD | E5: 手续费 USD | F5: 成交份额 | G5: 现金变动 USD | H5: 成本变动 USD | I5: 份额变动 | J5: 已实现盈亏 USD | K5: 检查状态 | L5: 备注 | M5: 前序份额 | N5: 前序成本 | O5: 前序缺项 | P5: 买入用途
A6: 46275 | B6: VOO | C6: 买入 | D6: 375 | E6: 0 | F6: 0.5373 | G6: =IF(OR(B6="",D6="",C6=""),"",IF(C6="买入",-(D6+E6),IF(C6="卖出",D6-E6,""))) -> -375 | H6: =IF(K6<>"已记录","",IF(C6="买入",D6+E6,-IF(M6=0,0,N6/M6*F6))) -> 375 | I6: =IF(K6<>"已记录","",IF(C6="买入",F6,-F6)) -> 0.5373 | J6: =IF(K6<>"已记录","",IF(C6="卖出",D6-E6+H6,0)) -> 0 | K6: =IF(B6="","",IF(OR(A6="",D6="",F6="",C6=""),"待补日期／金额／份额",IF(OR(D6<=0,F6<=0,E6<0,AND(C6<>"买入",C6<>"卖出"),AND(C6="卖出",E6>D6)),"请检查输入",IF(O6>0,"待补前序记录",IF(AND(C6="卖出",F6>M6+0.00000001),"卖出超过持仓","已记录"))))) -> 已记录 | M6: =0 -> 0 | N6: =0 -> 0 | O6: =0 -> 0 | P6: 其他
A7: 46275 | B7: QQQM | C7: 买入 | D7: 75 | E7: 0 | F7: 0.256 | G7: =IF(OR(B7="",D7="",C7=""),"",IF(C7="买入",-(D7+E7),IF(C7="卖出",D7-E7,""))) -> -75 | H7: =IF(K7<>"已记录","",IF(C7="买入",D7+E7,-IF(M7=0,0,N7/M7*F7))) -> 75 | I7: =IF(K7<>"已记录","",IF(C7="买入",F7,-F7)) -> 0.256 | J7: =IF(K7<>"已记录","",IF(C7="卖出",D7-E7+H7,0)) -> 0 | K7: =IF(B7="","",IF(OR(A7="",D7="",F7="",C7=""),"待补日期／金额／份额",IF(OR(D7<=0,F7<=0,E7<0,AND(C7<>"买入",C7<>"卖出"),AND(C7="卖出",E7>D7)),"请检查输入",IF(O7>0,"待补前序记录",IF(AND(C7="卖出",F7>M7+0.00000001),"卖出超过持仓","已记录"))))) -> 已记录 | M7: =IF(B7="","",SUMIF($B$6:B6,B7,$I$6:I6)) -> 0 | N7: =IF(B7="","",SUMIF($B$6:B6,B7,$H$6:H6)) -> 0 | O7: =IF(B7="","",COUNTIFS($B$6:B6,B7,$K$6:K6,"<>已记录")) -> 0 | P7: 其他
A8: 46275 | B8: SMH | C8: 买入 | D8: 50 | E8: 0 | F8: 0.0885 | G8: =IF(OR(B8="",D8="",C8=""),"",IF(C8="买入",-(D8+E8),IF(C8="卖出",D8-E8,""))) -> -50 | H8: =IF(K8<>"已记录","",IF(C8="买入",D8+E8,-IF(M8=0,0,N8/M8*F8))) -> 50 | I8: =IF(K8<>"已记录","",IF(C8="买入",F8,-F8)) -> 0.0885 | J8: =IF(K8<>"已记录","",IF(C8="卖出",D8-E8+H8,0)) -> 0 | K8: =IF(B8="","",IF(OR(A8="",D8="",F8="",C8=""),"待补日期／金额／份额",IF(OR(D8<=0,F8<=0,E8<0,AND(C8<>"买入",C8<>"卖出"),AND(C8="卖出",E8>D8)),"请检查输入",IF(O8>0,"待补前序记录",IF(AND(C8="卖出",F8>M8+0.00000001),"卖出超过持仓","已记录"))))) -> 已记录 | M8: =IF(B8="","",SUMIF($B$6:B7,B8,$I$6:I7)) -> 0 | N8: =IF(B8="","",SUMIF($B$6:B7,B8,$H$6:H7)) -> 0 | O8: =IF(B8="","",COUNTIFS($B$6:B7,B8,$K$6:K7,"<>已记录")) -> 0 | P8: 其他
G9: =IF(OR(B9="",D9="",C9=""),"",IF(C9="买入",-(D9+E9),IF(C9="卖出",D9-E9,""))) | H9: =IF(K9<>"已记录","",IF(C9="买入",D9+E9,-IF(M9=0,0,N9/M9*F9))) | I9: =IF(K9<>"已记录","",IF(C9="买入",F9,-F9)) | J9: =IF(K9<>"已记录","",IF(C9="卖出",D9-E9+H9,0)) | K9: =IF(B9="","",IF(OR(A9="",D9="",F9="",C9=""),"待补日期／金额／份额",IF(OR(D9<=0,F9<=0,E9<0,AND(C9<>"买入",C9<>"卖出"),AND(C9="卖出",E9>D9)),"请检查输入",IF(O9>0,"待补前序记录",IF(AND(C9="卖出",F9>M9+0.00000001),"卖出超过持仓","已记录"))))) | M9: =IF(B9="","",SUMIF($B$6:B8,B9,$I$6:I8)) | N9: =IF(B9="","",SUMIF($B$6:B8,B9,$H$6:H8)) | O9: =IF(B9="","",COUNTIFS($B$6:B8,B9,$K$6:K8,"<>已记录"))
G10: =IF(OR(B10="",D10="",C10=""),"",IF(C10="买入",-(D10+E10),IF(C10="卖出",D10-E10,""))) | H10: =IF(K10<>"已记录","",IF(C10="买入",D10+E10,-IF(M10=0,0,N10/M10*F10))) | I10: =IF(K10<>"已记录","",IF(C10="买入",F10,-F10)) | J10: =IF(K10<>"已记录","",IF(C10="卖出",D10-E10+H10,0)) | K10: =IF(B10="","",IF(OR(A10="",D10="",F10="",C10=""),"待补日期／金额／份额",IF(OR(D10<=0,F10<=0,E10<0,AND(C10<>"买入",C10<>"卖出"),AND(C10="卖出",E10>D10)),"请检查输入",IF(O10>0,"待补前序记录",IF(AND(C10="卖出",F10>M10+0.00000001),"卖出超过持仓","已记录"))))) | M10: =IF(B10="","",SUMIF($B$6:B9,B10,$I$6:I9)) | N10: =IF(B10="","",SUMIF($B$6:B9,B10,$H$6:H9)) | O10: =IF(B10="","",COUNTIFS($B$6:B9,B10,$K$6:K9,"<>已记录"))
G11: =IF(OR(B11="",D11="",C11=""),"",IF(C11="买入",-(D11+E11),IF(C11="卖出",D11-E11,""))) | H11: =IF(K11<>"已记录","",IF(C11="买入",D11+E11,-IF(M11=0,0,N11/M11*F11))) | I11: =IF(K11<>"已记录","",IF(C11="买入",F11,-F11)) | J11: =IF(K11<>"已记录","",IF(C11="卖出",D11-E11+H11,0)) | K11: =IF(B11="","",IF(OR(A11="",D11="",F11="",C11=""),"待补日期／金额／份额",IF(OR(D11<=0,F11<=0,E11<0,AND(C11<>"买入",C11<>"卖出"),AND(C11="卖出",E11>D11)),"请检查输入",IF(O11>0,"待补前序记录",IF(AND(C11="卖出",F11>M11+0.00000001),"卖出超过持仓","已记录"))))) | M11: =IF(B11="","",SUMIF($B$6:B10,B11,$I$6:I10)) | N11: =IF(B11="","",SUMIF($B$6:B10,B11,$H$6:H10)) | O11: =IF(B11="","",COUNTIFS($B$6:B10,B11,$K$6:K10,"<>已记录"))
G12: =IF(OR(B12="",D12="",C12=""),"",IF(C12="买入",-(D12+E12),IF(C12="卖出",D12-E12,""))) | H12: =IF(K12<>"已记录","",IF(C12="买入",D12+E12,-IF(M12=0,0,N12/M12*F12))) | I12: =IF(K12<>"已记录","",IF(C12="买入",F12,-F12)) | J12: =IF(K12<>"已记录","",IF(C12="卖出",D12-E12+H12,0)) | K12: =IF(B12="","",IF(OR(A12="",D12="",F12="",C12=""),"待补日期／金额／份额",IF(OR(D12<=0,F12<=0,E12<0,AND(C12<>"买入",C12<>"卖出"),AND(C12="卖出",E12>D12)),"请检查输入",IF(O12>0,"待补前序记录",IF(AND(C12="卖出",F12>M12+0.00000001),"卖出超过持仓","已记录"))))) | M12: =IF(B12="","",SUMIF($B$6:B11,B12,$I$6:I11)) | N12: =IF(B12="","",SUMIF($B$6:B11,B12,$H$6:H11)) | O12: =IF(B12="","",COUNTIFS($B$6:B11,B12,$K$6:K11,"<>已记录"))
G13: =IF(OR(B13="",D13="",C13=""),"",IF(C13="买入",-(D13+E13),IF(C13="卖出",D13-E13,""))) | H13: =IF(K13<>"已记录","",IF(C13="买入",D13+E13,-IF(M13=0,0,N13/M13*F13))) | I13: =IF(K13<>"已记录","",IF(C13="买入",F13,-F13)) | J13: =IF(K13<>"已记录","",IF(C13="卖出",D13-E13+H13,0)) | K13: =IF(B13="","",IF(OR(A13="",D13="",F13="",C13=""),"待补日期／金额／份额",IF(OR(D13<=0,F13<=0,E13<0,AND(C13<>"买入",C13<>"卖出"),AND(C13="卖出",E13>D13)),"请检查输入",IF(O13>0,"待补前序记录",IF(AND(C13="卖出",F13>M13+0.00000001),"卖出超过持仓","已记录"))))) | M13: =IF(B13="","",SUMIF($B$6:B12,B13,$I$6:I12)) | N13: =IF(B13="","",SUMIF($B$6:B12,B13,$H$6:H12)) | O13: =IF(B13="","",COUNTIFS($B$6:B12,B13,$K$6:K12,"<>已记录"))
G14: =IF(OR(B14="",D14="",C14=""),"",IF(C14="买入",-(D14+E14),IF(C14="卖出",D14-E14,""))) | H14: =IF(K14<>"已记录","",IF(C14="买入",D14+E14,-IF(M14=0,0,N14/M14*F14))) | I14: =IF(K14<>"已记录","",IF(C14="买入",F14,-F14)) | J14: =IF(K14<>"已记录","",IF(C14="卖出",D14-E14+H14,0)) | K14: =IF(B14="","",IF(OR(A14="",D14="",F14="",C14=""),"待补日期／金额／份额",IF(OR(D14<=0,F14<=0,E14<0,AND(C14<>"买入",C14<>"卖出"),AND(C14="卖出",E14>D14)),"请检查输入",IF(O14>0,"待补前序记录",IF(AND(C14="卖出",F14>M14+0.00000001),"卖出超过持仓","已记录"))))) | M14: =IF(B14="","",SUMIF($B$6:B13,B14,$I$6:I13)) | N14: =IF(B14="","",SUMIF($B$6:B13,B14,$H$6:H13)) | O14: =IF(B14="","",COUNTIFS($B$6:B13,B14,$K$6:K13,"<>已记录"))
G15: =IF(OR(B15="",D15="",C15=""),"",IF(C15="买入",-(D15+E15),IF(C15="卖出",D15-E15,""))) | H15: =IF(K15<>"已记录","",IF(C15="买入",D15+E15,-IF(M15=0,0,N15/M15*F15))) | I15: =IF(K15<>"已记录","",IF(C15="买入",F15,-F15)) | J15: =IF(K15<>"已记录","",IF(C15="卖出",D15-E15+H15,0)) | K15: =IF(B15="","",IF(OR(A15="",D15="",F15="",C15=""),"待补日期／金额／份额",IF(OR(D15<=0,F15<=0,E15<0,AND(C15<>"买入",C15<>"卖出"),AND(C15="卖出",E15>D15)),"请检查输入",IF(O15>0,"待补前序记录",IF(AND(C15="卖出",F15>M15+0.00000001),"卖出超过持仓","已记录"))))) | M15: =IF(B15="","",SUMIF($B$6:B14,B15,$I$6:I14)) | N15: =IF(B15="","",SUMIF($B$6:B14,B15,$H$6:H14)) | O15: =IF(B15="","",COUNTIFS($B$6:B14,B15,$K$6:K14,"<>已记录"))
G16: =IF(OR(B16="",D16="",C16=""),"",IF(C16="买入",-(D16+E16),IF(C16="卖出",D16-E16,""))) | H16: =IF(K16<>"已记录","",IF(C16="买入",D16+E16,-IF(M16=0,0,N16/M16*F16))) | I16: =IF(K16<>"已记录","",IF(C16="买入",F16,-F16)) | J16: =IF(K16<>"已记录","",IF(C16="卖出",D16-E16+H16,0)) | K16: =IF(B16="","",IF(OR(A16="",D16="",F16="",C16=""),"待补日期／金额／份额",IF(OR(D16<=0,F16<=0,E16<0,AND(C16<>"买入",C16<>"卖出"),AND(C16="卖出",E16>D16)),"请检查输入",IF(O16>0,"待补前序记录",IF(AND(C16="卖出",F16>M16+0.00000001),"卖出超过持仓","已记录"))))) | M16: =IF(B16="","",SUMIF($B$6:B15,B16,$I$6:I15)) | N16: =IF(B16="","",SUMIF($B$6:B15,B16,$H$6:H15)) | O16: =IF(B16="","",COUNTIFS($B$6:B15,B16,$K$6:K15,"<>已记录"))
G17: =IF(OR(B17="",D17="",C17=""),"",IF(C17="买入",-(D17+E17),IF(C17="卖出",D17-E17,""))) | H17: =IF(K17<>"已记录","",IF(C17="买入",D17+E17,-IF(M17=0,0,N17/M17*F17))) | I17: =IF(K17<>"已记录","",IF(C17="买入",F17,-F17)) | J17: =IF(K17<>"已记录","",IF(C17="卖出",D17-E17+H17,0)) | K17: =IF(B17="","",IF(OR(A17="",D17="",F17="",C17=""),"待补日期／金额／份额",IF(OR(D17<=0,F17<=0,E17<0,AND(C17<>"买入",C17<>"卖出"),AND(C17="卖出",E17>D17)),"请检查输入",IF(O17>0,"待补前序记录",IF(AND(C17="卖出",F17>M17+0.00000001),"卖出超过持仓","已记录"))))) | M17: =IF(B17="","",SUMIF($B$6:B16,B17,$I$6:I16)) | N17: =IF(B17="","",SUMIF($B$6:B16,B17,$H$6:H16)) | O17: =IF(B17="","",COUNTIFS($B$6:B16,B17,$K$6:K16,"<>已记录"))
G18: =IF(OR(B18="",D18="",C18=""),"",IF(C18="买入",-(D18+E18),IF(C18="卖出",D18-E18,""))) | H18: =IF(K18<>"已记录","",IF(C18="买入",D18+E18,-IF(M18=0,0,N18/M18*F18))) | I18: =IF(K18<>"已记录","",IF(C18="买入",F18,-F18)) | J18: =IF(K18<>"已记录","",IF(C18="卖出",D18-E18+H18,0)) | K18: =IF(B18="","",IF(OR(A18="",D18="",F18="",C18=""),"待补日期／金额／份额",IF(OR(D18<=0,F18<=0,E18<0,AND(C18<>"买入",C18<>"卖出"),AND(C18="卖出",E18>D18)),"请检查输入",IF(O18>0,"待补前序记录",IF(AND(C18="卖出",F18>M18+0.00000001),"卖出超过持仓","已记录"))))) | M18: =IF(B18="","",SUMIF($B$6:B17,B18,$I$6:I17)) | N18: =IF(B18="","",SUMIF($B$6:B17,B18,$H$6:H17)) | O18: =IF(B18="","",COUNTIFS($B$6:B17,B18,$K$6:K17,"<>已记录"))
G19: =IF(OR(B19="",D19="",C19=""),"",IF(C19="买入",-(D19+E19),IF(C19="卖出",D19-E19,""))) | H19: =IF(K19<>"已记录","",IF(C19="买入",D19+E19,-IF(M19=0,0,N19/M19*F19))) | I19: =IF(K19<>"已记录","",IF(C19="买入",F19,-F19)) | J19: =IF(K19<>"已记录","",IF(C19="卖出",D19-E19+H19,0)) | K19: =IF(B19="","",IF(OR(A19="",D19="",F19="",C19=""),"待补日期／金额／份额",IF(OR(D19<=0,F19<=0,E19<0,AND(C19<>"买入",C19<>"卖出"),AND(C19="卖出",E19>D19)),"请检查输入",IF(O19>0,"待补前序记录",IF(AND(C19="卖出",F19>M19+0.00000001),"卖出超过持仓","已记录"))))) | M19: =IF(B19="","",SUMIF($B$6:B18,B19,$I$6:I18)) | N19: =IF(B19="","",SUMIF($B$6:B18,B19,$H$6:H18)) | O19: =IF(B19="","",COUNTIFS($B$6:B18,B19,$K$6:K18,"<>已记录"))
G20: =IF(OR(B20="",D20="",C20=""),"",IF(C20="买入",-(D20+E20),IF(C20="卖出",D20-E20,""))) | H20: =IF(K20<>"已记录","",IF(C20="买入",D20+E20,-IF(M20=0,0,N20/M20*F20))) | I20: =IF(K20<>"已记录","",IF(C20="买入",F20,-F20)) | J20: =IF(K20<>"已记录","",IF(C20="卖出",D20-E20+H20,0)) | K20: =IF(B20="","",IF(OR(A20="",D20="",F20="",C20=""),"待补日期／金额／份额",IF(OR(D20<=0,F20<=0,E20<0,AND(C20<>"买入",C20<>"卖出"),AND(C20="卖出",E20>D20)),"请检查输入",IF(O20>0,"待补前序记录",IF(AND(C20="卖出",F20>M20+0.00000001),"卖出超过持仓","已记录"))))) | M20: =IF(B20="","",SUMIF($B$6:B19,B20,$I$6:I19)) | N20: =IF(B20="","",SUMIF($B$6:B19,B20,$H$6:H19)) | O20: =IF(B20="","",COUNTIFS($B$6:B19,B20,$K$6:K19,"<>已记录"))
... G605: =IF(OR(B605="",D605="",C605=""),"",IF(C605="买入",-(D605+E605),IF(C605="卖出",D605-E605,""))) | H605: =IF(K605<>"已记录","",IF(C605="买入",D605+E605,-IF(M605=0,0,N605/M605*F605))) | I605: =IF(K605<>"已记录","",IF(C605="买入",F605,-F605)) | J605: =IF(K605<>"已记录","",IF(C605="卖出",D605-E605+H605,0)) | K605: =IF(B605="","",IF(OR(A605="",D605="",F605="",C605=""),"待补日期／金额／份额",IF(OR(D605<=0,F605<=0,E605<0,AND(C605<>"买入",C605<>"卖出"),AND(C605="卖出",E605>D605)),"请检查输入",IF(O605>0,"待补前序记录",IF(AND(C605="卖出",F605>M605+0.00000001),"卖出超过持仓","已记录"))))) | M605: =IF(B605="","",SUMIF($B$6:B604,B605,$I$6:I604)) | N605: =IF(B605="","",SUMIF($B$6:B604,B605,$H$6:H604)) | O605: =IF(B605="","",COUNTIFS($B$6:B604,B605,$K$6:K604,"<>已记录"))

Sheet 换汇记录
A1: 换汇记录
A3: 每次换币一行：人民币→港元、嘉信入金港元→美元分别记录。可多次转账、保留港元；不会把整笔购汇本金算作已投入美元。流水号可与对应转账相同。
A5: 换汇日期 | B5: 流水／关联编号 | C5: 付币账户 | D5: 付出币种 | E5: 换汇本金 | F5: 收币账户 | G5: 收到币种 | H5: 实际收到金额 | I5: 另付费币种 | J5: 另付费用 | K5: 付币／收币汇率 | L5: 计入嘉信入金 USD | M5: 检查状态 | N5: 备注
A6: 46253 | B6: 1 | C6: 国内银行 | D6: RMB | E6: 5000 | F6: 香港汇丰 | G6: HKD | H6: 5786.19 | I6: RMB | J6: 0 | K6: =IF(OR(E6="",H6="",H6<=0),"",E6/H6) -> 0.86412648 | L6: =IF(AND(ISNUMBER(A6),OR(F6="嘉信证券",F6="嘉信入金中转"),C6<>"嘉信证券",G6="USD",ISNUMBER(H6),H6>0),H6,0) -> 0 | M6: =IF(COUNTA(A6:J6)=0,"",IF(OR(A6="",C6="",D6="",E6="",F6="",G6="",H6=""),"待补换汇信息",IF(OR(E6<=0,H6<=0,J6<0,D6=G6,AND(J6>0,I6="")),"请检查币种／金额／费用","已记录"))) -> 已记录 | N6: 交通银行跨境支付通
A7: 46257 | B7: 2 | C7: 国内银行 | D7: RMB | E7: 5000 | F7: 香港汇丰 | G7: HKD | H7: 5820.12 | I7: RMB | J7: 0 | K7: =IF(OR(E7="",H7="",H7<=0),"",E7/H7) -> 0.85908882 | L7: =IF(AND(ISNUMBER(A7),OR(F7="嘉信证券",F7="嘉信入金中转"),C7<>"嘉信证券",G7="USD",ISNUMBER(H7),H7>0),H7,0) -> 0 | M7: =IF(COUNTA(A7:J7)=0,"",IF(OR(A7="",C7="",D7="",E7="",F7="",G7="",H7=""),"待补换汇信息",IF(OR(E7<=0,H7<=0,J7<0,D7=G7,AND(J7>0,I7="")),"请检查币种／金额／费用","已记录"))) -> 已记录 | N7: 交通银行跨境支付通
A8: 46269 | B8: 3 | C8: 国内银行 | D8: RMB | E8: 10000 | F8: 香港汇丰 | G8: HKD | H8: 11666 | I8: RMB | J8: 0 | K8: =IF(OR(E8="",H8="",H8<=0),"",E8/H8) -> 0.85719184 | L8: =IF(AND(ISNUMBER(A8),OR(F8="嘉信证券",F8="嘉信入金中转"),C8<>"嘉信证券",G8="USD",ISNUMBER(H8),H8>0),H8,0) -> 0 | M8: =IF(COUNTA(A8:J8)=0,"",IF(OR(A8="",C8="",D8="",E8="",F8="",G8="",H8=""),"待补换汇信息",IF(OR(E8<=0,H8<=0,J8<0,D8=G8,AND(J8>0,I8="")),"请检查币种／金额／费用","已记录"))) -> 已记录 | N8: 交通银行跨境支付通
A9: 46273 | B9: 4 | C9: 香港汇丰 | D9: HKD | E9: 100 | F9: 嘉信入金中转 | G9: USD | H9: 12.73 | I9: RMB | J9: 0 | K9: =IF(OR(E9="",H9="",H9<=0),"",E9/H9) -> 7.8554595 | L9: =IF(AND(ISNUMBER(A9),OR(F9="嘉信证券",F9="嘉信入金中转"),C9<>"嘉信证券",G9="USD",ISNUMBER(H9),H9>0),H9,0) -> 12.73 | M9: =IF(COUNTA(A9:J9)=0,"",IF(OR(A9="",C9="",D9="",E9="",F9="",G9="",H9=""),"待补换汇信息",IF(OR(E9<=0,H9<=0,J9<0,D9=G9,AND(J9>0,I9="")),"请检查币种／金额／费用","已记录"))) -> 已记录
A10: 46274 | B10: 5 | C10: 香港汇丰 | D10: HKD | E10: 10000 | F10: 嘉信入金中转 | G10: USD | H10: 1273.18 | I10: RMB | J10: 0 | K10: =IF(OR(E10="",H10="",H10<=0),"",E10/H10) -> 7.854349 | L10: =IF(AND(ISNUMBER(A10),OR(F10="嘉信证券",F10="嘉信入金中转"),C10<>"嘉信证券",G10="USD",ISNUMBER(H10),H10>0),H10,0) -> 1273.18 | M10: =IF(COUNTA(A10:J10)=0,"",IF(OR(A10="",C10="",D10="",E10="",F10="",G10="",H10=""),"待补换汇信息",IF(OR(E10<=0,H10<=0,J10<0,D10=G10,AND(J10>0,I10="")),"请检查币种／金额／费用","已记录"))) -> 已记录
A11: 46278 | B11: 6 | C11: 国内银行 | D11: RMB | E11: 10000 | F11: 香港汇丰 | G11: HKD | H11: 11678.15 | I11: RMB | J11: 0 | K11: =IF(OR(E11="",H11="",H11<=0),"",E11/H11) -> 0.85630001 | L11: =IF(AND(ISNUMBER(A11),OR(F11="嘉信证券",F11="嘉信入金中转"),C11<>"嘉信证券",G11="USD",ISNUMBER(H11),H11>0),H11,0) -> 0 | M11: =IF(COUNTA(A11:J11)=0,"",IF(OR(A11="",C11="",D11="",E11="",F11="",G11="",H11=""),"待补换汇信息",IF(OR(E11<=0,H11<=0,J11<0,D11=G11,AND(J11>0,I11="")),"请检查币种／金额／费用","已记录"))) -> 已记录 | N11: 业兴银行购汇并转账
A12: 46289 | B12: 7 | C12: 国内银行 | D12: RMB | E12: 5000 | F12: 香港汇丰 | G12: HKD | H12: 5834.85 | I12: RMB | J12: 0 | K12: =IF(OR(E12="",H12="",H12<=0),"",E12/H12) -> 0.85692006 | L12: =IF(AND(ISNUMBER(A12),OR(F12="嘉信证券",F12="嘉信入金中转"),C12<>"嘉信证券",G12="USD",ISNUMBER(H12),H12>0),H12,0) -> 0 | M12: =IF(COUNTA(A12:J12)=0,"",IF(OR(A12="",C12="",D12="",E12="",F12="",G12="",H12=""),"待补换汇信息",IF(OR(E12<=0,H12<=0,J12<0,D12=G12,AND(J12>0,I12="")),"请检查币种／金额／费用","已记录"))) -> 已记录 | N12: 业兴银行购汇并转账
A13: 46289 | B13: 8 | C13: 国内银行 | D13: RMB | E13: 5000 | F13: 香港汇丰 | G13: HKD | H13: 5835.33 | I13: RMB | J13: 0 | K13: =IF(OR(E13="",H13="",H13<=0),"",E13/H13) -> 0.85684957 | L13: =IF(AND(ISNUMBER(A13),OR(F13="嘉信证券",F13="嘉信入金中转"),C13<>"嘉信证券",G13="USD",ISNUMBER(H13),H13>0),H13,0) -> 0 | M13: =IF(COUNTA(A13:J13)=0,"",IF(OR(A13="",C13="",D13="",E13="",F13="",G13="",H13=""),"待补换汇信息",IF(OR(E13<=0,H13<=0,J13<0,D13=G13,AND(J13>0,I13="")),"请检查币种／金额／费用","已记录"))) -> 已记录 | N13: 业兴银行购汇并转账
A14: 46300 | B14: 9 | C14: 香港汇丰 | D14: HKD | E14: 8000 | F14: 嘉信入金中转 | G14: USD | H14: 1017.89 | I14: RMB | J14: 0 | K14: =IF(OR(E14="",H14="",H14<=0),"",E14/H14) -> 7.8593954 | L14: =IF(AND(ISNUMBER(A14),OR(F14="嘉信证券",F14="嘉信入金中转"),C14<>"嘉信证券",G14="USD",ISNUMBER(H14),H14>0),H14,0) -> 1017.89 | M14: =IF(COUNTA(A14:J14)=0,"",IF(OR(A14="",C14="",D14="",E14="",F14="",G14="",H14=""),"待补换汇信息",IF(OR(E14<=0,H14<=0,J14<0,D14=G14,AND(J14>0,I14="")),"请检查币种／金额／费用","已记录"))) -> 已记录
K15: =IF(OR(E15="",H15="",H15<=0),"",E15/H15) | L15: =IF(AND(ISNUMBER(A15),OR(F15="嘉信证券",F15="嘉信入金中转"),C15<>"嘉信证券",G15="USD",ISNUMBER(H15),H15>0),H15,0) -> 0 | M15: =IF(COUNTA(A15:J15)=0,"",IF(OR(A15="",C15="",D15="",E15="",F15="",G15="",H15=""),"待补换汇信息",IF(OR(E15<=0,H15<=0,J15<0,D15=G15,AND(J15>0,I15="")),"请检查币种／金额／费用","已记录")))
K16: =IF(OR(E16="",H16="",H16<=0),"",E16/H16) | L16: =IF(AND(ISNUMBER(A16),OR(F16="嘉信证券",F16="嘉信入金中转"),C16<>"嘉信证券",G16="USD",ISNUMBER(H16),H16>0),H16,0) -> 0 | M16: =IF(COUNTA(A16:J16)=0,"",IF(OR(A16="",C16="",D16="",E16="",F16="",G16="",H16=""),"待补换汇信息",IF(OR(E16<=0,H16<=0,J16<0,D16=G16,AND(J16>0,I16="")),"请检查币种／金额／费用","已记录")))
K17: =IF(OR(E17="",H17="",H17<=0),"",E17/H17) | L17: =IF(AND(ISNUMBER(A17),OR(F17="嘉信证券",F17="嘉信入金中转"),C17<>"嘉信证券",G17="USD",ISNUMBER(H17),H17>0),H17,0) -> 0 | M17: =IF(COUNTA(A17:J17)=0,"",IF(OR(A17="",C17="",D17="",E17="",F17="",G17="",H17=""),"待补换汇信息",IF(OR(E17<=0,H17<=0,J17<0,D17=G17,AND(J17>0,I17="")),"请检查币种／金额／费用","已记录")))
K18: =IF(OR(E18="",H18="",H18<=0),"",E18/H18) | L18: =IF(AND(ISNUMBER(A18),OR(F18="嘉信证券",F18="嘉信入金中转"),C18<>"嘉信证券",G18="USD",ISNUMBER(H18),H18>0),H18,0) -> 0 | M18: =IF(COUNTA(A18:J18)=0,"",IF(OR(A18="",C18="",D18="",E18="",F18="",G18="",H18=""),"待补换汇信息",IF(OR(E18<=0,H18<=0,J18<0,D18=G18,AND(J18>0,I18="")),"请检查币种／金额／费用","已记录")))
K19: =IF(OR(E19="",H19="",H19<=0),"",E19/H19) | L19: =IF(AND(ISNUMBER(A19),OR(F19="嘉信证券",F19="嘉信入金中转"),C19<>"嘉信证券",G19="USD",ISNUMBER(H19),H19>0),H19,0) -> 0 | M19: =IF(COUNTA(A19:J19)=0,"",IF(OR(A19="",C19="",D19="",E19="",F19="",G19="",H19=""),"待补换汇信息",IF(OR(E19<=0,H19<=0,J19<0,D19=G19,AND(J19>0,I19="")),"请检查币种／金额／费用","已记录")))
K20: =IF(OR(E20="",H20="",H20<=0),"",E20/H20) | L20: =IF(AND(ISNUMBER(A20),OR(F20="嘉信证券",F20="嘉信入金中转"),C20<>"嘉信证券",G20="USD",ISNUMBER(H20),H20>0),H20,0) -> 0 | M20: =IF(COUNTA(A20:J20)=0,"",IF(OR(A20="",C20="",D20="",E20="",F20="",G20="",H20=""),"待补换汇信息",IF(OR(E20<=0,H20<=0,J20<0,D20=G20,AND(J20>0,I20="")),"请检查币种／金额／费用","已记录")))
K21: =IF(OR(E21="",H21="",H21<=0),"",E21/H21) | L21: =IF(AND(ISNUMBER(A21),OR(F21="嘉信证券",F21="嘉信入金中转"),C21<>"嘉信证券",G21="USD",ISNUMBER(H21),H21>0),H21,0) -> 0 | M21: =IF(COUNTA(A21:J21)=0,"",IF(OR(A21="",C21="",D21="",E21="",F21="",G21="",H21=""),"待补换汇信息",IF(OR(E21<=0,H21<=0,J21<0,D21=G21,AND(J21>0,I21="")),"请检查币种／金额／费用","已记录")))
K22: =IF(OR(E22="",H22="",H22<=0),"",E22/H22) | L22: =IF(AND(ISNUMBER(A22),OR(F22="嘉信证券",F22="嘉信入金中转"),C22<>"嘉信证券",G22="USD",ISNUMBER(H22),H22>0),H22,0) -> 0 | M22: =IF(COUNTA(A22:J22)=0,"",IF(OR(A22="",C22="",D22="",E22="",F22="",G22="",H22=""),"待补换汇信息",IF(OR(E22<=0,H22<=0,J22<0,D22=G22,AND(J22>0,I22="")),"请检查币种／金额／费用","已记录")))
K23: =IF(OR(E23="",H23="",H23<=0),"",E23/H23) | L23: =IF(AND(ISNUMBER(A23),OR(F23="嘉信证券",F23="嘉信入金中转"),C23<>"嘉信证券",G23="USD",ISNUMBER(H23),H23>0),H23,0) -> 0 | M23: =IF(COUNTA(A23:J23)=0,"",IF(OR(A23="",C23="",D23="",E23="",F23="",G23="",H23=""),"待补换汇信息",IF(OR(E23<=0,H23<=0,J23<0,D23=G23,AND(J23>0,I23="")),"请检查币种／金额／费用","已记录")))
K24: =IF(OR(E24="",H24="",H24<=0),"",E24/H24) | L24: =IF(AND(ISNUMBER(A24),OR(F24="嘉信证券",F24="嘉信入金中转"),C24<>"嘉信证券",G24="USD",ISNUMBER(H24),H24>0),H24,0) -> 0 | M24: =IF(COUNTA(A24:J24)=0,"",IF(OR(A24="",C24="",D24="",E24="",F24="",G24="",H24=""),"待补换汇信息",IF(OR(E24<=0,H24<=0,J24<0,D24=G24,AND(J24>0,I24="")),"请检查币种／金额／费用","已记录")))
K25: =IF(OR(E25="",H25="",H25<=0),"",E25/H25) | L25: =IF(AND(ISNUMBER(A25),OR(F25="嘉信证券",F25="嘉信入金中转"),C25<>"嘉信证券",G25="USD",ISNUMBER(H25),H25>0),H25,0) -> 0 | M25: =IF(COUNTA(A25:J25)=0,"",IF(OR(A25="",C25="",D25="",E25="",F25="",G25="",H25=""),"待补换汇信息",IF(OR(E25<=0,H25<=0,J25<0,D25=G25,AND(J25>0,I25="")),"请检查币种／金额／费用","已记录")))
K26: =IF(OR(E26="",H26="",H26<=0),"",E26/H26) | L26: =IF(AND(ISNUMBER(A26),OR(F26="嘉信证券",F26="嘉信入金中转"),C26<>"嘉信证券",G26="USD",ISNUMBER(H26),H26>0),H26,0) -> 0 | M26: =IF(COUNTA(A26:J26)=0,"",IF(OR(A26="",C26="",D26="",E26="",F26="",G26="",H26=""),"待补换汇信息",IF(OR(E26<=0,H26<=0,J26<0,D26=G26,AND(J26>0,I26="")),"请检查币种／金额／费用","已记录")))
... K246: =IF(OR(E246="",H246="",H246<=0),"",E246/H246) | L246: =IF(AND(ISNUMBER(A246),OR(F246="嘉信证券",F246="嘉信入金中转"),C246<>"嘉信证券",G246="USD",ISNUMBER(H246),H246>0),H246,0) -> 0 | M246: =IF(COUNTA(A246:J246)=0,"",IF(OR(A246="",C246="",D246="",E246="",F246="",G246="",H246=""),"待补换汇信息",IF(OR(E246<=0,H246<=0,J246<0,D246=G246,AND(J246>0,I246="")),"请检查币种／金额／费用","已记录")))

Sheet 入金记录
A1: 入金记录
A3: 每次转账一行，可只转出部分港元。转账两端为同一币种；涉及自动换汇时另填“换汇记录”。本金不含另外支付的费用；同一笔资金可沿用关联编号。
A5: 汇出日期 | B5: 流水／关联编号 | C5: 汇出账户 | D5: 币种 | E5: 汇出本金 | F5: 收款账户 | G5: 实际到账本金 | H5: 到账日期 | I5: 另付费币种 | J5: 另付费用 | K5: 到账差额 | L5: 检查状态 | M5: 备注
A6: 46273 | B6: 1 | C6: 嘉信入金中转 | D6: USD | E6: 12.73 | F6: 嘉信证券 | G6: 12.73 | H6: 46273 | I6: RMB | J6: 0 | K6: =IF(OR(E6="",G6=""),"",E6-G6) -> 0 | L6: =IF(COUNTA(A6:J6)=0,"",IF(OR(A6="",C6="",D6="",E6="",F6=""),"待补汇出信息",IF(OR(E6<=0,J6<0,AND(J6>0,I6=""),C6=F6),"请检查本金／费用／账户",IF(OR(G6="",H6=""),"在途／待补到账",IF(OR(G6<0,H6<A6),"请检查到账信息","已记录"))))) -> 已记录
A7: 46274 | B7: 2 | C7: 嘉信入金中转 | D7: USD | E7: 1273.18 | F7: 嘉信证券 | G7: 1273.18 | H7: 46274 | I7: RMB | J7: 0 | K7: =IF(OR(E7="",G7=""),"",E7-G7) -> 0 | L7: =IF(COUNTA(A7:J7)=0,"",IF(OR(A7="",C7="",D7="",E7="",F7=""),"待补汇出信息",IF(OR(E7<=0,J7<0,AND(J7>0,I7=""),C7=F7),"请检查本金／费用／账户",IF(OR(G7="",H7=""),"在途／待补到账",IF(OR(G7<0,H7<A7),"请检查到账信息","已记录"))))) -> 已记录
A8: 46300 | B8: 3 | C8: 嘉信入金中转 | D8: USD | E8: 1017.89 | F8: 嘉信证券 | G8: 1017.89 | H8: 46300 | I8: RMB | J8: 0 | K8: =IF(OR(E8="",G8=""),"",E8-G8) -> 0 | L8: =IF(COUNTA(A8:J8)=0,"",IF(OR(A8="",C8="",D8="",E8="",F8=""),"待补汇出信息",IF(OR(E8<=0,J8<0,AND(J8>0,I8=""),C8=F8),"请检查本金／费用／账户",IF(OR(G8="",H8=""),"在途／待补到账",IF(OR(G8<0,H8<A8),"请检查到账信息","已记录"))))) -> 已记录
K9: =IF(OR(E9="",G9=""),"",E9-G9) | L9: =IF(COUNTA(A9:J9)=0,"",IF(OR(A9="",C9="",D9="",E9="",F9=""),"待补汇出信息",IF(OR(E9<=0,J9<0,AND(J9>0,I9=""),C9=F9),"请检查本金／费用／账户",IF(OR(G9="",H9=""),"在途／待补到账",IF(OR(G9<0,H9<A9),"请检查到账信息","已记录")))))
K10: =IF(OR(E10="",G10=""),"",E10-G10) | L10: =IF(COUNTA(A10:J10)=0,"",IF(OR(A10="",C10="",D10="",E10="",F10=""),"待补汇出信息",IF(OR(E10<=0,J10<0,AND(J10>0,I10=""),C10=F10),"请检查本金／费用／账户",IF(OR(G10="",H10=""),"在途／待补到账",IF(OR(G10<0,H10<A10),"请检查到账信息","已记录")))))
K11: =IF(OR(E11="",G11=""),"",E11-G11) | L11: =IF(COUNTA(A11:J11)=0,"",IF(OR(A11="",C11="",D11="",E11="",F11=""),"待补汇出信息",IF(OR(E11<=0,J11<0,AND(J11>0,I11=""),C11=F11),"请检查本金／费用／账户",IF(OR(G11="",H11=""),"在途／待补到账",IF(OR(G11<0,H11<A11),"请检查到账信息","已记录")))))
K12: =IF(OR(E12="",G12=""),"",E12-G12) | L12: =IF(COUNTA(A12:J12)=0,"",IF(OR(A12="",C12="",D12="",E12="",F12=""),"待补汇出信息",IF(OR(E12<=0,J12<0,AND(J12>0,I12=""),C12=F12),"请检查本金／费用／账户",IF(OR(G12="",H12=""),"在途／待补到账",IF(OR(G12<0,H12<A12),"请检查到账信息","已记录")))))
K13: =IF(OR(E13="",G13=""),"",E13-G13) | L13: =IF(COUNTA(A13:J13)=0,"",IF(OR(A13="",C13="",D13="",E13="",F13=""),"待补汇出信息",IF(OR(E13<=0,J13<0,AND(J13>0,I13=""),C13=F13),"请检查本金／费用／账户",IF(OR(G13="",H13=""),"在途／待补到账",IF(OR(G13<0,H13<A13),"请检查到账信息","已记录")))))
K14: =IF(OR(E14="",G14=""),"",E14-G14) | L14: =IF(COUNTA(A14:J14)=0,"",IF(OR(A14="",C14="",D14="",E14="",F14=""),"待补汇出信息",IF(OR(E14<=0,J14<0,AND(J14>0,I14=""),C14=F14),"请检查本金／费用／账户",IF(OR(G14="",H14=""),"在途／待补到账",IF(OR(G14<0,H14<A14),"请检查到账信息","已记录")))))
K15: =IF(OR(E15="",G15=""),"",E15-G15) | L15: =IF(COUNTA(A15:J15)=0,"",IF(OR(A15="",C15="",D15="",E15="",F15=""),"待补汇出信息",IF(OR(E15<=0,J15<0,AND(J15>0,I15=""),C15=F15),"请检查本金／费用／账户",IF(OR(G15="",H15=""),"在途／待补到账",IF(OR(G15<0,H15<A15),"请检查到账信息","已记录")))))
K16: =IF(OR(E16="",G16=""),"",E16-G16) | L16: =IF(COUNTA(A16:J16)=0,"",IF(OR(A16="",C16="",D16="",E16="",F16=""),"待补汇出信息",IF(OR(E16<=0,J16<0,AND(J16>0,I16=""),C16=F16),"请检查本金／费用／账户",IF(OR(G16="",H16=""),"在途／待补到账",IF(OR(G16<0,H16<A16),"请检查到账信息","已记录")))))
K17: =IF(OR(E17="",G17=""),"",E17-G17) | L17: =IF(COUNTA(A17:J17)=0,"",IF(OR(A17="",C17="",D17="",E17="",F17=""),"待补汇出信息",IF(OR(E17<=0,J17<0,AND(J17>0,I17=""),C17=F17),"请检查本金／费用／账户",IF(OR(G17="",H17=""),"在途／待补到账",IF(OR(G17<0,H17<A17),"请检查到账信息","已记录")))))
K18: =IF(OR(E18="",G18=""),"",E18-G18) | L18: =IF(COUNTA(A18:J18)=0,"",IF(OR(A18="",C18="",D18="",E18="",F18=""),"待补汇出信息",IF(OR(E18<=0,J18<0,AND(J18>0,I18=""),C18=F18),"请检查本金／费用／账户",IF(OR(G18="",H18=""),"在途／待补到账",IF(OR(G18<0,H18<A18),"请检查到账信息","已记录")))))
K19: =IF(OR(E19="",G19=""),"",E19-G19) | L19: =IF(COUNTA(A19:J19)=0,"",IF(OR(A19="",C19="",D19="",E19="",F19=""),"待补汇出信息",IF(OR(E19<=0,J19<0,AND(J19>0,I19=""),C19=F19),"请检查本金／费用／账户",IF(OR(G19="",H19=""),"在途／待补到账",IF(OR(G19<0,H19<A19),"请检查到账信息","已记录")))))
K20: =IF(OR(E20="",G20=""),"",E20-G20) | L20: =IF(COUNTA(A20:J20)=0,"",IF(OR(A20="",C20="",D20="",E20="",F20=""),"待补汇出信息",IF(OR(E20<=0,J20<0,AND(J20>0,I20=""),C20=F20),"请检查本金／费用／账户",IF(OR(G20="",H20=""),"在途／待补到账",IF(OR(G20<0,H20<A20),"请检查到账信息","已记录")))))
... K245: =IF(OR(E245="",G245=""),"",E245-G245) | L245: =IF(COUNTA(A245:J245)=0,"",IF(OR(A245="",C245="",D245="",E245="",F245=""),"待补汇出信息",IF(OR(E245<=0,J245<0,AND(J245>0,I245=""),C245=F245),"请检查本金／费用／账户",IF(OR(G245="",H245=""),"在途／待补到账",IF(OR(G245<0,H245<A245),"请检查到账信息","已记录")))))

Sheet 分红记录
A1: 分红记录
A3: 每次分红一行。税前、预扣税、其他费用按嘉信流水填写；税后分红自动计算。再投资另记一笔买入。
A5: 到账日期 | B5: ETF | C5: 税前分红 USD | D5: 预扣税 USD | E5: 其他费用 USD | F5: 税后分红 USD | G5: 备注
F6: =IF(C6="","",C6-D6-E6)
F7: =IF(C7="","",C7-D7-E7)
F8: =IF(C8="","",C8-D8-E8)
F9: =IF(C9="","",C9-D9-E9)
F10: =IF(C10="","",C10-D10-E10)
F11: =IF(C11="","",C11-D11-E11)
F12: =IF(C12="","",C12-D12-E12)
F13: =IF(C13="","",C13-D13-E13)
F14: =IF(C14="","",C14-D14-E14)
F15: =IF(C15="","",C15-D15-E15)
F16: =IF(C16="","",C16-D16-E16)
F17: =IF(C17="","",C17-D17-E17)
... F245: =IF(C245="","",C245-D245-E245)

Sheet 使用说明
A1: 使用说明
A3: 适用：电脑 Excel／WPS；人民币—港元—美元入金；长期 ETF 定投。无宏，无实时行情连接。
A5: 首次填写与已保留数据
A6: 已保留你填写的历史买入、实际份额、行情、嘉信现金及换汇／入金记录。“资金余额”工作表已移除；隐藏的“原入金记录”继续留作备份。金额和份额均以你的记录为准。
A9: 每月操作顺序
A10: ① 交易前在回撤计划填最近已结束美股交易日收盘日、指数收盘，核对历史最高收盘；② 按计算结果安排换汇、转账；③ 成交后逐笔记录实际金额、费用、份额；④ 更新现金／行情，有分红则另记。每月10日遇休市顺延，不自动下单。
A13: 金额与费用
A14: 所有本金均不含另付费用。费用已体现在汇出与到账差额或换汇实收中时，不再重复登记；“另付费用”默认从该行付币／汇出账户扣除，用币种字段区分。若费用由另一账户承担，调整备注并另行核对余额；不能直接相加不同币种。
A17: 转账与换汇分开；允许部分入金
A18: 每次换汇和每次转账分别记一行，允许只转出部分港元。兼容两条记录路径：① 香港汇丰HKD→嘉信入金中转USD（换汇记录），再中转USD→嘉信证券USD（入金记录）；② 港元转至中转（入金记录），再中转HKD→嘉信证券USD（换汇记录）。按实际流水选择对应步骤，勿把同一到账重复记录。
A21: 部分入金与余额示例
A22: 示例（未写入实际流水）：购得10000HKD，只汇6000HKD至汇丰，再汇4000HKD至嘉信；其余港元可以保留。不必全部转出，也不要用全部购汇人民币本金除以部分美元到账。每次实际金额、账户、币种和到账日期分别填，相关步骤可共用流水编号。
... A50: 新表按各次实际换汇显示付币／收币汇率，不用全部购汇人民币本金除以部分美元到账。由于港元可能保留、混合、多次转出，未自动虚构整条人民币／美元成本。转账差额与另外支付的费用分列；实际银行账单和嘉信记录为核对依据。5000美元预算仅为额外ETF买入（含买入手续费），不包含汇款／换汇费用。

Sheet 原入金记录
A1: 入金记录
A3: 一行对应一批资金。逐段填实际金额；留在原账户的港元会显示为余额。尚未全额划转时，不计算整批人民币／美元成本。
A5: 购汇日期 | B5: 批次编号 | C5: 购汇本金 RMB | D5: 购得港元 HKD | E5: 额外费用 RMB | F5: 国内汇出 HKD | G5: 汇丰到账 HKD | H5: 汇丰汇出 HKD | I5: 另扣费用 HKD | J5: 嘉信到账 USD | K5: 美元到账日期 | L5: 购汇 RMB／HKD | M5: 首段扣减 HKD | N5: 国内余款 HKD | O5: 汇丰余款 HKD | P5: 汇出 HKD／USD | Q5: 整批成本 RMB | R5: 成本 RMB／USD | S5: 检查状态 | T5: 备注
A6: 46273 | B6: 1 | L6: =IF(OR(C6="",D6="",D6<=0),"",C6/D6) | M6: =IF(OR(F6="",G6=""),"",F6-G6) | N6: =IF(OR(D6="",F6=""),"",D6-F6) | O6: =IF(OR(G6="",H6=""),"",G6-H6-I6) | P6: =IF(OR(H6="",J6="",J6<=0),"",H6/J6) | Q6: =IF(S6<>"已完整划转","",C6+E6) | R6: =IF(Q6="","",Q6/J6) | S6: =IF(COUNTA(A6:K6)=0,"",IF(OR(A6="",C6="",D6="",F6="",G6="",H6="",J6="",K6=""),"待补分段记录",IF(OR(C6<=0,D6<=0,J6<=0,E6<0,I6<0,M6< -0.01,N6< -0.01,O6< -0.01),"金额关系待检查",IF(OR(ABS(N6)>0.01,ABS(O6)>0.01),"尚有港元余额","已完整划转")))) -> 待补分段记录
A7: 46274 | B7: 2 | L7: =IF(OR(C7="",D7="",D7<=0),"",C7/D7) | M7: =IF(OR(F7="",G7=""),"",F7-G7) | N7: =IF(OR(D7="",F7=""),"",D7-F7) | O7: =IF(OR(G7="",H7=""),"",G7-H7-I7) | P7: =IF(OR(H7="",J7="",J7<=0),"",H7/J7) | Q7: =IF(S7<>"已完整划转","",C7+E7) | R7: =IF(Q7="","",Q7/J7) | S7: =IF(COUNTA(A7:K7)=0,"",IF(OR(A7="",C7="",D7="",F7="",G7="",H7="",J7="",K7=""),"待补分段记录",IF(OR(C7<=0,D7<=0,J7<=0,E7<0,I7<0,M7< -0.01,N7< -0.01,O7< -0.01),"金额关系待检查",IF(OR(ABS(N7)>0.01,ABS(O7)>0.01),"尚有港元余额","已完整划转")))) -> 待补分段记录
A8: 46300 | B8: 3 | L8: =IF(OR(C8="",D8="",D8<=0),"",C8/D8) | M8: =IF(OR(F8="",G8=""),"",F8-G8) | N8: =IF(OR(D8="",F8=""),"",D8-F8) | O8: =IF(OR(G8="",H8=""),"",G8-H8-I8) | P8: =IF(OR(H8="",J8="",J8<=0),"",H8/J8) | Q8: =IF(S8<>"已完整划转","",C8+E8) | R8: =IF(Q8="","",Q8/J8) | S8: =IF(COUNTA(A8:K8)=0,"",IF(OR(A8="",C8="",D8="",F8="",G8="",H8="",J8="",K8=""),"待补分段记录",IF(OR(C8<=0,D8<=0,J8<=0,E8<0,I8<0,M8< -0.01,N8< -0.01,O8< -0.01),"金额关系待检查",IF(OR(ABS(N8)>0.01,ABS(O8)>0.01),"尚有港元余额","已完整划转")))) -> 待补分段记录
L9: =IF(OR(C9="",D9="",D9<=0),"",C9/D9) | M9: =IF(OR(F9="",G9=""),"",F9-G9) | N9: =IF(OR(D9="",F9=""),"",D9-F9) | O9: =IF(OR(G9="",H9=""),"",G9-H9-I9) | P9: =IF(OR(H9="",J9="",J9<=0),"",H9/J9) | Q9: =IF(S9<>"已完整划转","",C9+E9) | R9: =IF(Q9="","",Q9/J9) | S9: =IF(COUNTA(A9:K9)=0,"",IF(OR(A9="",C9="",D9="",F9="",G9="",H9="",J9="",K9=""),"待补分段记录",IF(OR(C9<=0,D9<=0,J9<=0,E9<0,I9<0,M9< -0.01,N9< -0.01,O9< -0.01),"金额关系待检查",IF(OR(ABS(N9)>0.01,ABS(O9)>0.01),"尚有港元余额","已完整划转"))))
L10: =IF(OR(C10="",D10="",D10<=0),"",C10/D10) | M10: =IF(OR(F10="",G10=""),"",F10-G10) | N10: =IF(OR(D10="",F10=""),"",D10-F10) | O10: =IF(OR(G10="",H10=""),"",G10-H10-I10) | P10: =IF(OR(H10="",J10="",J10<=0),"",H10/J10) | Q10: =IF(S10<>"已完整划转","",C10+E10) | R10: =IF(Q10="","",Q10/J10) | S10: =IF(COUNTA(A10:K10)=0,"",IF(OR(A10="",C10="",D10="",F10="",G10="",H10="",J10="",K10=""),"待补分段记录",IF(OR(C10<=0,D10<=0,J10<=0,E10<0,I10<0,M10< -0.01,N10< -0.01,O10< -0.01),"金额关系待检查",IF(OR(ABS(N10)>0.01,ABS(O10)>0.01),"尚有港元余额","已完整划转"))))
L11: =IF(OR(C11="",D11="",D11<=0),"",C11/D11) | M11: =IF(OR(F11="",G11=""),"",F11-G11) | N11: =IF(OR(D11="",F11=""),"",D11-F11) | O11: =IF(OR(G11="",H11=""),"",G11-H11-I11) | P11: =IF(OR(H11="",J11="",J11<=0),"",H11/J11) | Q11: =IF(S11<>"已完整划转","",C11+E11) | R11: =IF(Q11="","",Q11/J11) | S11: =IF(COUNTA(A11:K11)=0,"",IF(OR(A11="",C11="",D11="",F11="",G11="",H11="",J11="",K11=""),"待补分段记录",IF(OR(C11<=0,D11<=0,J11<=0,E11<0,I11<0,M11< -0.01,N11< -0.01,O11< -0.01),"金额关系待检查",IF(OR(ABS(N11)>0.01,ABS(O11)>0.01),"尚有港元余额","已完整划转"))))
L12: =IF(OR(C12="",D12="",D12<=0),"",C12/D12) | M12: =IF(OR(F12="",G12=""),"",F12-G12) | N12: =IF(OR(D12="",F12=""),"",D12-F12) | O12: =IF(OR(G12="",H12=""),"",G12-H12-I12) | P12: =IF(OR(H12="",J12="",J12<=0),"",H12/J12) | Q12: =IF(S12<>"已完整划转","",C12+E12) | R12: =IF(Q12="","",Q12/J12) | S12: =IF(COUNTA(A12:K12)=0,"",IF(OR(A12="",C12="",D12="",F12="",G12="",H12="",J12="",K12=""),"待补分段记录",IF(OR(C12<=0,D12<=0,J12<=0,E12<0,I12<0,M12< -0.01,N12< -0.01,O12< -0.01),"金额关系待检查",IF(OR(ABS(N12)>0.01,ABS(O12)>0.01),"尚有港元余额","已完整划转"))))
L13: =IF(OR(C13="",D13="",D13<=0),"",C13/D13) | M13: =IF(OR(F13="",G13=""),"",F13-G13) | N13: =IF(OR(D13="",F13=""),"",D13-F13) | O13: =IF(OR(G13="",H13=""),"",G13-H13-I13) | P13: =IF(OR(H13="",J13="",J13<=0),"",H13/J13) | Q13: =IF(S13<>"已完整划转","",C13+E13) | R13: =IF(Q13="","",Q13/J13) | S13: =IF(COUNTA(A13:K13)=0,"",IF(OR(A13="",C13="",D13="",F13="",G13="",H13="",J13="",K13=""),"待补分段记录",IF(OR(C13<=0,D13<=0,J13<=0,E13<0,I13<0,M13< -0.01,N13< -0.01,O13< -0.01),"金额关系待检查",IF(OR(ABS(N13)>0.01,ABS(O13)>0.01),"尚有港元余额","已完整划转"))))
L14: =IF(OR(C14="",D14="",D14<=0),"",C14/D14) | M14: =IF(OR(F14="",G14=""),"",F14-G14) | N14: =IF(OR(D14="",F14=""),"",D14-F14) | O14: =IF(OR(G14="",H14=""),"",G14-H14-I14) | P14: =IF(OR(H14="",J14="",J14<=0),"",H14/J14) | Q14: =IF(S14<>"已完整划转","",C14+E14) | R14: =IF(Q14="","",Q14/J14) | S14: =IF(COUNTA(A14:K14)=0,"",IF(OR(A14="",C14="",D14="",F14="",G14="",H14="",J14="",K14=""),"待补分段记录",IF(OR(C14<=0,D14<=0,J14<=0,E14<0,I14<0,M14< -0.01,N14< -0.01,O14< -0.01),"金额关系待检查",IF(OR(ABS(N14)>0.01,ABS(O14)>0.01),"尚有港元余额","已完整划转"))))
L15: =IF(OR(C15="",D15="",D15<=0),"",C15/D15) | M15: =IF(OR(F15="",G15=""),"",F15-G15) | N15: =IF(OR(D15="",F15=""),"",D15-F15) | O15: =IF(OR(G15="",H15=""),"",G15-H15-I15) | P15: =IF(OR(H15="",J15="",J15<=0),"",H15/J15) | Q15: =IF(S15<>"已完整划转","",C15+E15) | R15: =IF(Q15="","",Q15/J15) | S15: =IF(COUNTA(A15:K15)=0,"",IF(OR(A15="",C15="",D15="",F15="",G15="",H15="",J15="",K15=""),"待补分段记录",IF(OR(C15<=0,D15<=0,J15<=0,E15<0,I15<0,M15< -0.01,N15< -0.01,O15< -0.01),"金额关系待检查",IF(OR(ABS(N15)>0.01,ABS(O15)>0.01),"尚有港元余额","已完整划转"))))
L16: =IF(OR(C16="",D16="",D16<=0),"",C16/D16) | M16: =IF(OR(F16="",G16=""),"",F16-G16) | N16: =IF(OR(D16="",F16=""),"",D16-F16) | O16: =IF(OR(G16="",H16=""),"",G16-H16-I16) | P16: =IF(OR(H16="",J16="",J16<=0),"",H16/J16) | Q16: =IF(S16<>"已完整划转","",C16+E16) | R16: =IF(Q16="","",Q16/J16) | S16: =IF(COUNTA(A16:K16)=0,"",IF(OR(A16="",C16="",D16="",F16="",G16="",H16="",J16="",K16=""),"待补分段记录",IF(OR(C16<=0,D16<=0,J16<=0,E16<0,I16<0,M16< -0.01,N16< -0.01,O16< -0.01),"金额关系待检查",IF(OR(ABS(N16)>0.01,ABS(O16)>0.01),"尚有港元余额","已完整划转"))))
L17: =IF(OR(C17="",D17="",D17<=0),"",C17/D17) | M17: =IF(OR(F17="",G17=""),"",F17-G17) | N17: =IF(OR(D17="",F17=""),"",D17-F17) | O17: =IF(OR(G17="",H17=""),"",G17-H17-I17) | P17: =IF(OR(H17="",J17="",J17<=0),"",H17/J17) | Q17: =IF(S17<>"已完整划转","",C17+E17) | R17: =IF(Q17="","",Q17/J17) | S17: =IF(COUNTA(A17:K17)=0,"",IF(OR(A17="",C17="",D17="",F17="",G17="",H17="",J17="",K17=""),"待补分段记录",IF(OR(C17<=0,D17<=0,J17<=0,E17<0,I17<0,M17< -0.01,N17< -0.01,O17< -0.01),"金额关系待检查",IF(OR(ABS(N17)>0.01,ABS(O17)>0.01),"尚有港元余额","已完整划转"))))
L18: =IF(OR(C18="",D18="",D18<=0),"",C18/D18) | M18: =IF(OR(F18="",G18=""),"",F18-G18) | N18: =IF(OR(D18="",F18=""),"",D18-F18) | O18: =IF(OR(G18="",H18=""),"",G18-H18-I18) | P18: =IF(OR(H18="",J18="",J18<=0),"",H18/J18) | Q18: =IF(S18<>"已完整划转","",C18+E18) | R18: =IF(Q18="","",Q18/J18) | S18: =IF(COUNTA(A18:K18)=0,"",IF(OR(A18="",C18="",D18="",F18="",G18="",H18="",J18="",K18=""),"待补分段记录",IF(OR(C18<=0,D18<=0,J18<=0,E18<0,I18<0,M18< -0.01,N18< -0.01,O18< -0.01),"金额关系待检查",IF(OR(ABS(N18)>0.01,ABS(O18)>0.01),"尚有港元余额","已完整划转"))))
L19: =IF(OR(C19="",D19="",D19<=0),"",C19/D19) | M19: =IF(OR(F19="",G19=""),"",F19-G19) | N19: =IF(OR(D19="",F19=""),"",D19-F19) | O19: =IF(OR(G19="",H19=""),"",G19-H19-I19) | P19: =IF(OR(H19="",J19="",J19<=0),"",H19/J19) | Q19: =IF(S19<>"已完整划转","",C19+E19) | R19: =IF(Q19="","",Q19/J19) | S19: =IF(COUNTA(A19:K19)=0,"",IF(OR(A19="",C19="",D19="",F19="",G19="",H19="",J19="",K19=""),"待补分段记录",IF(OR(C19<=0,D19<=0,J19<=0,E19<0,I19<0,M19< -0.01,N19< -0.01,O19< -0.01),"金额关系待检查",IF(OR(ABS(N19)>0.01,ABS(O19)>0.01),"尚有港元余额","已完整划转"))))
L20: =IF(OR(C20="",D20="",D20<=0),"",C20/D20) | M20: =IF(OR(F20="",G20=""),"",F20-G20) | N20: =IF(OR(D20="",F20=""),"",D20-F20) | O20: =IF(OR(G20="",H20=""),"",G20-H20-I20) | P20: =IF(OR(H20="",J20="",J20<=0),"",H20/J20) | Q20: =IF(S20<>"已完整划转","",C20+E20) | R20: =IF(Q20="","",Q20/J20) | S20: =IF(COUNTA(A20:K20)=0,"",IF(OR(A20="",C20="",D20="",F20="",G20="",H20="",J20="",K20=""),"待补分段记录",IF(OR(C20<=0,D20<=0,J20<=0,E20<0,I20<0,M20< -0.01,N20< -0.01,O20< -0.01),"金额关系待检查",IF(OR(ABS(N20)>0.01,ABS(O20)>0.01),"尚有港元余额","已完整划转"))))
... L245: =IF(OR(C245="",D245="",D245<=0),"",C245/D245) | M245: =IF(OR(F245="",G245=""),"",F245-G245) | N245: =IF(OR(D245="",F245=""),"",D245-F245) | O245: =IF(OR(G245="",H245=""),"",G245-H245-I245) | P245: =IF(OR(H245="",J245="",J245<=0),"",H245/J245) | Q245: =IF(S245<>"已完整划转","",C245+E245) | R245: =IF(Q245="","",Q245/J245) | S245: =IF(COUNTA(A245:K245)=0,"",IF(OR(A245="",C245="",D245="",F245="",G245="",H245="",J245="",K245=""),"待补分段记录",IF(OR(C245<=0,D245<=0,J245<=0,E245<0,I245<0,M245< -0.01,N245< -0.01,O245< -0.01),"金额关系待检查",IF(OR(ABS(N245)>0.01,ABS(O245)>0.01),"尚有港元余额","已完整划转"))))
